Workbook
Name CopyVars: ReadMe!$A$253:$A$352
Name D: [1]REPORTS!#REF!
Name D: [2]REPORTS!#REF!
Name PROFITS: COMPETITORS!$A$85
Name QTR: COMPETITORS!$B$1
Name test: 'FIN-RPT'!$E$57:$F$60

Sheet ReadMe
A1: Welcome to the simulation!
A3: In order for this file to function properly, you will need to enable the macros.
A5: This file is divided into a number of worksheets. Here is a description of how to use this information
A6: Worksheet
A7: Name | B7: Description
B8: RESULTS OF THE SIMULATION
A9: Market Report | B9: This is a report which present marketing information for the time period that you choose to display
A10: Prod-Rpt | B10: This is a report which presents Operations information for the time period that you choose to display
A11: Fin-Rpt | B11: This is a report which present Financial informaiton for the time period that you choose to display
A12: Cash Flow | B12: This is a report which present a single period cash flow statement for the currently displayed time period
B13: At the top of each report, you can select whatever time period that you wish to display.
B15: TOOLS
A16: Tabulate | B16: This is a visual basic tool which will extract data from all time periods which contain data and display this data as a column
B17: This tool is very useful for extracting information over multiple time periods quickly for analysis or graphical display.
B19: INFORMATION
A20: Competitors | B20: This worksheet contains information about your competitors so that you can monitor them more closely.
A21: InputHistory | B21: This worksheet contains a history of all past input decisions. This information will update as each simulation cycle is executed.
A22: P0, P1 …..P75 | B22: These 32 worksheets contain raw data which represent the output or results of the simulation
B23: This data is divided into 3 sections:
C24: Rows 51 and above contain data which is public (common to all 5 teams). Columns represent COUNTRIES within these rows
C25: Rows 52 through 77 contain data which is public (common to all 5 teams). Columns represent COMPANIES within these rows
C26: Rows 78 and below contain confidential company specific data for just your company
B28: Temportary holding sheets which you should never edit
A29: ACTIVE | B29: This is a temporary holding area for data which is mapped into the 4 reports. Please do not edit this worksheet.
A30: Active -1 | B30: This is a temporary holding area for data which is mapped into the 4 reports. Please do not edit this worksheet.
A31: Data | B31: This is a temporary holding area for data which is mapped into the competitors graphs. Please do not edit this worksheet.
B33: Very Important -- Period zero output data is not real output data. It is
B34: provided only to initialize the simulation. This data should be ignored for analysis purposes
A252: CopyVar (DO NOT TOUCH)
A253: 1
A254: 2
A255: 3
A256: 4
A257: 5
A258: 6
A259: 7
A260: 8
A261: 9
A262: 10
A263: 11
A264: 12
... A352: 100

Sheet Analysis
B2: U.S. | C2: Germany | D2: Japan
A3: R&D Expenditure | B3: 3300000 | C3: =B3/1.1 -> 3000000 | D3: =B3/1.1 -> 3000000
A5: WACC | B5: 0.126
A6: Quarterly discount rate | B6: =((1+B5)^(0.25))-1 -> 0.030112359
A7: Time Horizon (QTR) | B7: 80
A9: Plant capacity | B9: 230000
A10: Cost differential | B10: 4
A12: Annuity | B12: U.S. | C12: Germany | D12: Japan | E12: Net Benefit
A13: R&D Expenditure | B13: =B3 -> 3300000 | C13: =B13/1.1 -> 3000000 | D13: =B13/1.1 -> 3000000 | E13: =B13-C13 -> 300000
A14: Transportation | B14: 119301.75 | C14: 132099 | E14: =B14-C14 -> -12797.25
A15: Tarrifs | B15: 637964.77 | C15: 719044.29 | E15: =B15-C15 -> -81079.519
E16: =SUM(E13:E15) -> 206123.23
A19: NPV of annuity | B19: =E16*(1/B6)*(1-(1/((1+B6)^B7))) -> 6207440.4
A20: Additional Capital Costs | B20: =B9*B10 -> 920000 | E20: 5 | F20: 10 | G20: 20 | H20: BE
A21: Residual | B21: =((0.9875^B7)*B20)/((1+B6)^B7) -> 31332.018 | D21: 3.5 | E21: 1613151.5 | F21: 3249043.4 | G21: 4702267.3 | H21: 8 Quarters
A22: NPV of Capital Expenditure | B22: =B20-B21 -> 888667.98 | D22: 3 | E22: 937604.6 | F22: 2200277.7 | G22: 3333395 | H22: 11 Quarters
A23: Factory write down | B23: =(0.25)*(ACTIVE!E59) -> 2730000 | D23: 2.5 | E23: 262057.71 | F23: 1151512 | G23: 1964522.7 | H23: 16 Quarters
A24: Union buy-out | B24: 0 | D24: 2 | E24: -413489.19 | F24: 102746.25 | G24: 595650.38 | H24: 36 Quarters
A25: Total NPV | B25: =B19-SUM(B22:B24) -> 2588772.4
B30: 2000 Q4 | C30: 2001 Q1 | D30: 2001 Q2 | E30: 2001 Q3 | F30: 2001 Q4
A31: RICO
A32: Quality position | B32: 0.93944889 | C32: 1.1234076 | D32: 1.2045228 | E32: 1.0739922 | F32: 0.98107179
A33: Factory capacity | B33: 194270.45 | C33: 191842.05 | D33: 208444 | E33: 236838.45 | F33: 233877.95
A34: Net income | B34: -387137.22 | C34: -1773659.4 | D34: -1166174.7 | E34: 1078427 | F34: 28813.471
A35: Income | B35: =B34/(1-0.34) -> -586571.54 | C35: =C34/(1-0.34) -> -2687362.7 | D35: =D34/(1-0.34) -> -1766931.4 | E35: =E34/(1-0.34) -> 1633980.3 | F35: =F34/(1-0.34) -> 43656.775
A36: Debt / Equity ratio | B36: 0.25650577 | C36: 0.36859944 | D36: 0.37496164 | E36: 0.33951797 | F36: 0.34384282
A37: Cash & cash equivalents | B37: 8237696.5 | C37: 6591041.1 | D37: 1808746.4 | E37: 824634.37 | F37: 980543.84
A38: Receivables | B38: 15497217 | C38: 16732835 | D38: 20002581 | E38: 20092633 | F38: 18060233
A40: Chronologic
A41: Quality position | B41: 1.0286238 | C41: 1.1285863 | D41: 1.170918 | E41: 1.2040246 | F41: 1.2061316
A42: R&D expenditure | B42: 3 | C42: 3.5 | D42: 3.5 | E42: 3.5 | F42: 3.4
A43: Product Losses | B43: -1060903 | C43: -438885.37 | D43: -827053.51 | E43: 71287.225 | F43: 494174.69
B45: 1 | C45: =B45 -> 1 | D45: =C45 -> 1 | E45: =D45 -> 1 | F45: =E45 -> 1 | G45: =F45 -> 1 | H45: =G45 -> 1 | I45: =H45 -> 1 | J45: =I45 -> 1 | ... FC45: =FB45 -> 1
B46: -1 | C46: 0 | D46: 1 | E46: 2 | F46: 3 | G46: 4 | H46: 5 | I46: 6 | J46: 7 | K46: 8 | L46: 9 | M46: 10 | N46: 11 | O46: 12 | P46: 13 | Q46: 14 | R46: 15 | S46: 16 | T46: 17 | U46: 18 | V46: 19 | W46: 20 | X46: 21 | Y46: 22 | Z46: 23 | AA46: 24 | AB46: 25 | AC46: 26 | AD46: 27 | AE46: 28 | AF46: 29 | AG46: 30 | AH46: 31 | AI46: 32 | AJ46: 33 | AK46: 34 | AL46: 35 | AM46: 36 | AN46: 37 | AO46: 38 | AP46: 39 | AQ46: 40 | AR46: 41 | AS46: 42 | AT46: 43 | AU46: 44 | AV46: 45 | AW46: 46 | AX46: 47 | AY46: 48 | AZ46: 49 | BA46: 50 | BB46: 51 | BC46: 52 | BD46: 53 | BE46: 54 | BF46: 55 | BG46: 56 | BH46: 57 | BI46: 58 | BJ46: 59 | BK46: 60 | BL46: 61 | BM46: 62 | BN46: 63 | BO46: 64 | BP46: 65 | BQ46: 66 | BR46: 67 | BS46: 68 | BT46: 69 | BU46: 70 | BV46: 71 | BW46: 72 | BX46: 73 | BY46: 74 | BZ46: 75 | CA46: 76 | CB46: 77 | CC46: 78 | CD46: 79 | CE46: 80 | CF46: 81 | CG46: 82 | CH46: 83 | CI46: 84 | CJ46: 85 | CK46: 86 | CL46: 87 | CM46: 88 | CN46: 89 | CO46: 90 | CP46: 91 | CQ46: 92 | CR46: 93 | CS46: 94 | CT46: 95 | CU46: 96 | CV46: 97 | CW46: 98 | CX46: 99 | CY46: 100 | CZ46: 101 | DA46: 102 | DB46: 103 | DC46: 104 | DD46: 105 | DE46: 106 | DF46: 107 | DG46: 108 | DH46: 109 | DI46: 110 | DJ46: 111 | DK46: 112 | DL46: 113 | DM46: 114 | DN46: 115 | DO46: 116 | DP46: 117 | DQ46: 118 | DR46: 119 | DS46: 120 | DT46: 121 | DU46: 122 | DV46: 123 | DW46: 124 | DX46: 125 | DY46: 126 | DZ46: 127 | EA46: 128 | EB46: 129 | EC46: 130 | ED46: 131 | EE46: 132 | EF46: 133 | EG46: 134 | EH46: 135 | EI46: 136 | EJ46: 137 | EK46: 138 | EL46: 139 | EM46: 140 | EN46: 141 | EO46: 142 | EP46: 143 | EQ46: 144 | ER46: 145 | ES46: 146 | ET46: 147 | EU46: 148 | EV46: 149 | EW46: 150 | EX46: 151 | EY46: 152 | EZ46: 153 | FA46: 154 | FB46: 155 | FC46: 156
B47: 2003 Q3 | C47: 2003 Q4 | D47: 2004 Q1 | E47: 2004 Q2 | F47: 2004 Q3 | G47: 2004 Q4 | H47: 2005 Q1 | I47: 2005 Q2 | J47: 2005 Q3 | K47: 2005 Q4 | L47: 2006 Q1 | M47: 2006 Q2 | N47: 2006 Q3 | O47: 2006 Q4 | P47: 2007 Q1 | Q47: 2007 Q2 | R47: 2007 Q3 | S47: 2007 Q4 | T47: 2008 Q1 | U47: 2008 Q2 | V47: 2008 Q3 | W47: 2008 Q4 | X47: 2009 Q1 | Y47: 2009 Q2 | Z47: 2009 Q3 | AA47: 2009 Q4 | AB47: 2010 Q1 | AC47: 2010 Q2 | AD47: 2010 Q3 | AE47: 2010 Q4 | AF47: 2011 Q1 | AG47: 2011 Q2 | AH47: 2011 Q3 | AI47: 2011 Q4 | AJ47: 2012 Q1 | AK47: 2012 Q2 | AL47: 2012 Q3 | AM47: 2012 Q4 | AN47: 2013 Q1 | AO47: 2013 Q2 | AP47: 2013 Q3 | AQ47: 2013 Q4 | AR47: 2014 Q1 | AS47: 2014 Q2 | AT47: 2014 Q3 | AU47: 2014 Q4 | AV47: 2015 Q1 | AW47: 2015 Q2 | AX47: 2015 Q3 | AY47: 2015 Q4 | AZ47: 2016 Q1 | BA47: 2016 Q2 | BB47: 2016 Q3 | BC47: 2016 Q4 | BD47: 2017 Q1 | BE47: 2017 Q2 | BF47: 2017 Q3 | BG47: 2017 Q4 | BH47: 2018 Q1 | BI47: 2018 Q2 | BJ47: 2018 Q3 | BK47: 2018 Q4 | BL47: 2019 Q1 | BM47: 2019 Q2 | BN47: 2019 Q3 | BO47: 2019 Q4 | BP47: 2020 Q1 | BQ47: 2020 Q2 | BR47: 2020 Q3 | BS47: 2020 Q4 | BT47: 2021 Q1 | BU47: 2021 Q2 | BV47: 2021 Q3 | BW47: 2021 Q4 | BX47: 2022 Q1 | BY47: 2022 Q2 | BZ47: 2022 Q3 | CA47: 2022 Q4 | CB47: 2023 Q1 | CC47: 2023 Q2 | CD47: 2023 Q3 | CE47: 2023 Q4 | CF47: 2024 Q1 | CG47: 2024 Q2 | CH47: 2024 Q3 | CI47: 2024 Q4 | CJ47: 2025 Q1 | CK47: 2025 Q2 | CL47: 2025 Q3 | CM47: 2025 Q4 | CN47: 2026 Q1 | CO47: 2026 Q2 | CP47: 2026 Q3 | CQ47: 2026 Q4 | CR47: 2027 Q1 | CS47: 2027 Q2 | CT47: 2027 Q3 | CU47: 2027 Q4 | CV47: 2028 Q1 | CW47: 2028 Q2 | CX47: 2028 Q3 | CY47: 2028 Q4 | CZ47: 2029 Q1 | DA47: 2029 Q2 | DB47: 2029 Q3 | DC47: 2029 Q4 | DD47: 2030 Q1 | DE47: 2030 Q2 | DF47: 2030 Q3 | DG47: 2030 Q4 | DH47: 2031 Q1 | DI47: 2031 Q2 | DJ47: 2031 Q3 | DK47: 2031 Q4 | DL47: 2032 Q1 | DM47: 2032 Q2 | DN47: 2032 Q3 | DO47: 2032 Q4 | DP47: 2033 Q1 | DQ47: 2033 Q2 | DR47: 2033 Q3 | DS47: 2033 Q4 | DT47: 2034 Q1 | DU47: 2034 Q2 | DV47: 2034 Q3 | DW47: 2034 Q4 | DX47: 2035 Q1 | DY47: 2035 Q2 | DZ47: 2035 Q3 | EA47: 2035 Q4 | EB47: 2036 Q1 | EC47: 2036 Q2 | ED47: 2036 Q3 | EE47: 2036 Q4 | EF47: 2037 Q1 | EG47: 2037 Q2 | EH47: 2037 Q3 | EI47: 2037 Q4 | EJ47: 2038 Q1 | EK47: 2038 Q2 | EL47: 2038 Q3 | EM47: 2038 Q4 | EN47: 2039 Q1 | EO47: 2039 Q2 | EP47: 2039 Q3 | EQ47: 2039 Q4 | ER47: 2040 Q1 | ES47: 2040 Q2 | ET47: 2040 Q3 | EU47: 2040 Q4 | EV47: 2041 Q1 | EW47: 2041 Q2 | EX47: 2041 Q3 | EY47: 2041 Q4 | EZ47: 2042 Q1 | FA47: 2042 Q2 | FB47: 2042 Q3 | FC47: 2042 Q4
A48: Total Unit Cost | B48: 17.5 | C48: =B48*C45 -> 17.5 | D48: =C48*D45 -> 17.5 | E48: =D48*E45 -> 17.5 | F48: =E48*F45 -> 17.5 | G48: =F48*G45 -> 17.5 | H48: =G48*H45 -> 17.5 | I48: =H48*I45 -> 17.5 | J48: =I48*J45 -> 17.5 | ... FC48: =FB48*FC45 -> 17.5
A49: Contract advantage | B49: 6.73 | C49: 6.88 | D49: 7.021 | E49: 7.161 | F49: 7.297 | G49: 7.429 | H49: 7.557 | I49: 7.681 | J49: 7.801 | K49: 7.917 | L49: 8.029 | M49: 8.137 | N49: 8.241 | O49: 8.341 | P49: 8.437 | Q49: 8.529 | R49: 8.617 | S49: 8.701 | T49: 8.781 | U49: 8.857 | V49: 8.929 | W49: 8.997 | X49: 9.061 | Y49: 9.121 | Z49: 9.177 | AA49: 9.229 | AB49: 9.277 | AC49: 9.321 | AD49: 9.361 | AE49: 9.397 | AF49: 9.429 | AG49: 9.457 | AH49: 9.481 | AI49: 9.501 | AJ49: 9.517 | AK49: 9.529 | AL49: 9.537 | AM49: 9.54 | AN49: 9.54 | AO49: 9.54 | AP49: 9.54 | AQ49: 9.54 | AR49: 9.54 | AS49: 9.54 | AT49: 9.54 | AU49: 9.54 | AV49: 9.54 | AW49: 9.54 | AX49: 9.54 | AY49: 9.54 | AZ49: 9.54 | BA49: 9.54 | BB49: 9.54 | BC49: 9.54 | BD49: 9.54 | BE49: 9.54 | BF49: 9.54 | BG49: 9.54 | BH49: 9.54 | BI49: 9.54 | BJ49: 9.54 | BK49: 9.54 | BL49: 9.54 | BM49: 9.54 | BN49: 9.54 | BO49: 9.54 | BP49: 9.54 | BQ49: 9.54 | BR49: 9.54 | BS49: 9.54 | BT49: 9.54 | BU49: 9.54 | BV49: 9.54 | BW49: 9.54 | BX49: 9.54 | BY49: 9.54 | BZ49: 9.54 | CA49: 9.54 | CB49: 9.54 | CC49: 9.54 | CD49: 9.54 | CE49: 9.54 | CF49: 9.54 | CG49: 9.54 | CH49: 9.54 | CI49: 9.54 | CJ49: 9.54 | CK49: 9.54 | CL49: 9.54 | CM49: 9.54 | CN49: 9.54 | CO49: 9.54 | CP49: 9.54 | CQ49: 9.54 | CR49: 9.54 | CS49: 9.54 | CT49: 9.54 | CU49: 9.54 | CV49: 9.54 | CW49: 9.54 | CX49: 9.54 | CY49: 9.54 | CZ49: 9.54 | DA49: 9.54 | DB49: 9.54 | DC49: 9.54 | DD49: 9.54 | DE49: 9.54 | DF49: 9.54 | DG49: 9.54 | DH49: 9.54 | DI49: 9.54 | DJ49: 9.54 | DK49: 9.54 | DL49: 9.54 | DM49: 9.54 | DN49: 9.54 | DO49: 9.54 | DP49: 9.54 | DQ49: 9.54 | DR49: 9.54 | DS49: 9.54 | DT49: 9.54 | DU49: 9.54 | DV49: 9.54 | DW49: 9.54 | DX49: 9.54 | DY49: 9.54 | DZ49: 9.54 | EA49: 9.54 | EB49: 9.54 | EC49: 9.54 | ED49: 9.54 | EE49: 9.54 | EF49: 9.54 | EG49: 9.54 | EH49: 9.54 | EI49: 9.54 | EJ49: 9.54 | EK49: 9.54 | EL49: 9.54 | EM49: 9.54 | EN49: 9.54 | EO49: 9.54 | EP49: 9.54 | EQ49: 9.54 | ER49: 9.54 | ES49: 9.54 | ET49: 9.54 | EU49: 9.54 | EV49: 9.54 | EW49: 9.54 | EX49: 9.54 | EY49: 9.54 | EZ49: 9.54 | FA49: 9.54 | FB49: 9.54 | FC49: 9.54
A50: Effective bid | B50: 13.4 | C50: =B50 -> 13.4 | D50: =C50 -> 13.4 | E50: =D50 -> 13.4 | F50: =E50 -> 13.4 | G50: =F50 -> 13.4 | H50: =G50 -> 13.4 | I50: =H50 -> 13.4 | J50: =I50 -> 13.4 | ... FC50: =FB50 -> 13.4
A51: VC plus CA | B51: =B50+B49 -> 20.13 | C51: =C50+C49 -> 20.28 | D51: =D50+D49 -> 20.421 | E51: =E50+E49 -> 20.561 | F51: =F50+F49 -> 20.697 | G51: =G50+G49 -> 20.829 | H51: =H50+H49 -> 20.957 | I51: =I50+I49 -> 21.081 | ... FC51: =FC50+FC49 -> 22.94
A52: Profit per unit | B52: =B51-B48 -> 2.63 | C52: =C51-C48 -> 2.78 | D52: =D51-D48 -> 2.921 | E52: =E51-E48 -> 3.061 | F52: =F51-F48 -> 3.197 | G52: =G51-G48 -> 3.329 | H52: =H51-H48 -> 3.457 | I52: =I51-I48 -> 3.581 | ... FC52: =FC51-FC48 -> 5.44
A53: Unit Sales | B53: 50000 | C53: 50000 | D53: 50000 | E53: 50000 | F53: 50000 | G53: 50000 | H53: 50000 | I53: 50000 | J53: 50000 | K53: 50000 | L53: 50000 | M53: 50000 | N53: 50000 | O53: 50000 | P53: 50000 | Q53: 50000 | R53: 50000 | S53: 50000 | T53: 50000 | U53: 50000 | V53: 50000 | W53: 50000 | X53: 50000 | Y53: 50000 | Z53: 50000 | AA53: 50000 | AB53: 50000 | AC53: 50000 | AD53: 50000 | AE53: 50000 | AF53: 50000 | AG53: 50000 | AH53: 50000 | AI53: 50000 | AJ53: 50000 | AK53: 50000 | AL53: 50000 | AM53: 50000 | AN53: 50000 | AO53: 50000 | AP53: 50000 | AQ53: 50000 | AR53: 50000 | AS53: 50000 | AT53: 50000 | AU53: 50000 | AV53: 50000 | AW53: 50000 | AX53: 50000 | AY53: 50000 | AZ53: 50000 | BA53: 50000 | BB53: 50000 | BC53: 50000 | BD53: 50000 | BE53: 50000 | BF53: 50000 | BG53: 50000 | BH53: 50000 | BI53: 50000 | BJ53: 50000 | BK53: 50000 | BL53: 50000 | BM53: 50000 | BN53: 50000 | BO53: 50000 | BP53: 50000 | BQ53: 50000 | BR53: 50000 | BS53: 50000 | BT53: 50000 | BU53: 50000 | BV53: 50000 | BW53: 50000 | BX53: 50000 | BY53: 50000 | BZ53: 50000 | CA53: 50000 | CB53: 50000 | CC53: 50000 | CD53: 50000 | CE53: 50000 | CF53: 50000 | CG53: 50000 | CH53: 50000 | CI53: 50000 | CJ53: 50000 | CK53: 50000 | CL53: 50000 | CM53: 50000 | CN53: 50000 | CO53: 50000 | CP53: 50000 | CQ53: 50000 | CR53: 50000 | CS53: 50000 | CT53: 50000 | CU53: 50000 | CV53: 50000 | CW53: 50000 | CX53: 50000 | CY53: 50000 | CZ53: 50000 | DA53: 50000 | DB53: 50000 | DC53: 50000 | DD53: 50000 | DE53: 50000 | DF53: 50000 | DG53: 50000 | DH53: 50000 | DI53: 50000 | DJ53: 50000 | DK53: 50000 | DL53: 50000 | DM53: 50000 | DN53: 50000 | DO53: 50000 | DP53: 50000 | DQ53: 50000 | DR53: 50000 | DS53: 50000 | DT53: 50000 | DU53: 50000 | DV53: 50000 | DW53: 50000 | DX53: 50000 | DY53: 50000 | DZ53: 50000 | EA53: 50000 | EB53: 50000 | EC53: 50000 | ED53: 50000 | EE53: 50000 | EF53: 50000 | EG53: 50000 | EH53: 50000 | EI53: 50000 | EJ53: 50000 | EK53: 50000 | EL53: 50000 | EM53: 50000 | EN53: 50000 | EO53: 50000 | EP53: 50000 | EQ53: 50000 | ER53: 50000 | ES53: 50000 | ET53: 50000 | EU53: 50000 | EV53: 50000 | EW53: 50000 | EX53: 50000 | EY53: 50000 | EZ53: 50000 | FA53: 50000 | FB53: 50000 | FC53: 50000
A54: Revenue | B54: =B51*B53 -> 1006500 | C54: =C51*C53 -> 1014000 | D54: =D51*D53 -> 1021050 | E54: =E51*E53 -> 1028050 | F54: =F51*F53 -> 1034850 | G54: =G51*G53 -> 1041450 | H54: =H51*H53 -> 1047850 | I54: =I51*I53 -> 1054050 | ... FC54: =FC51*FC53 -> 1147000
A55: Profit ($) | B55: =B52*B53 -> 131500 | C55: =C52*C53 -> 139000 | D55: =D52*D53 -> 146050 | E55: =E52*E53 -> 153050 | F55: =F52*F53 -> 159850 | G55: =G52*G53 -> 166450 | H55: =H52*H53 -> 172850 | I55: =I52*I53 -> 179050 | ... FC55: =FC52*FC53 -> 272000
A56: Discount | D56: =D55/(1+$B$62)^D46 -> 143937.88 | E56: =E55/(1+$B$62)^E46 -> 148655.3 | F56: =F55/(1+$B$62)^F46 -> 153014.73 | G56: =G55/(1+$B$62)^G46 -> 157028.3 | H56: =H55/(1+$B$62)^H46 -> 160707.84 | I56: =I55/(1+$B$62)^I46 -> 164064.84 | J56: =J55/(1+$B$62)^J46 -> 167110.53 | K56: =K55/(1+$B$62)^K46 -> 169855.82 | ... FC56: =FC55/(1+$B$62)^FC46 -> 28031.101
A57: Present Value 5 years | B57: =SUM(D56:W56) -> 3421120.5
A58: Present Value 10 years | B58: =SUM(D56:AQ56) -> 6827191
A59: Present Value 20 years | B59: =SUM(D56:CE56) -> 11398078
B61: 0.06
B62: =((1+B61)^(1/4)-1) -> 0.014673846

Sheet Market Report
A1: Period Currently Displayed | C1: =ACTIVE!A2 -> 62 | F1: MARKET REPORT | K1: Select Period to View
A2: Company Number | C2: =ACTIVE!B78 -> 1
A3: Green Value of My Product 1 | C3: =ACTIVE!B273 -> 0.69763018
A4: Average Green Value of all Product 1 | C4: =ACTIVE!B275 -> 0.66862151 | F4: Product 1 Market Statistics | N4: World
B5: Japan | C5: % Wld | D5: Mexico | E5: % Wld | F5: China | G5: % Wld | H5: U.K. | I5: % Wld | J5: Germany | K5: % Wld | L5: U.S. | M5: % Wld | N5: Totals
A6: Total Demand (Units) | B6: =ACTIVE!B3 -> 373964 | C6: =B6/N6 -> 0.19655667 | D6: =ACTIVE!C3 -> 170225 | E6: =D6/N6 -> 0.089470802 | F6: =ACTIVE!D3 -> 117041 | G6: =F6/N6 -> 0.061517122 | H6: =ACTIVE!E3 -> 249421 | I6: =H6/N6 -> 0.13109647 | J6: =ACTIVE!F3 -> 272291 | K6: =J6/N6 -> 0.14311702 | L6: =ACTIVE!G3 -> 719634 | M6: =L6/N6 -> 0.37824192 | N6: =ACTIVE!H3 -> 1902576
A7: Total Sales (Units) | B7: =ACTIVE!B4 -> 373964 | C7: =B7/N7 -> 0.19655667 | D7: =ACTIVE!C4 -> 170225 | E7: =D7/N7 -> 0.089470802 | F7: =ACTIVE!D4 -> 117041 | G7: =F7/N7 -> 0.061517122 | H7: =ACTIVE!E4 -> 249421 | I7: =H7/N7 -> 0.13109647 | J7: =ACTIVE!F4 -> 272291 | K7: =J7/N7 -> 0.14311702 | L7: =ACTIVE!G4 -> 719634 | M7: =L7/N7 -> 0.37824192 | N7: =ACTIVE!H4 -> 1902576
A8: Total Marketing Exp P1 | B8: =ACTIVE!B33 -> 81400050 | C8: =(B8/ACTIVE!B49)/'Market Report'!N8 -> 0.087130819 | D8: =ACTIVE!C33 -> 3060019.2 | E8: =(D8/ACTIVE!C49)/'Market Report'!N8 -> 0.023030524 | F8: =ACTIVE!D33 -> 3360006 | G8: =(F8/ACTIVE!D49)/'Market Report'!N8 -> 0.049798508 | H8: =ACTIVE!E33 -> 889999.5 | I8: =(H8/ACTIVE!E49)/'Market Report'!N8 -> 0.13190645 | J8: =ACTIVE!F33 -> 1424999 | K8: =(J8/ACTIVE!F49)/'Market Report'!N8 -> 0.17828445 | L8: =ACTIVE!G33 -> 5500000 | M8: =L8/N8 -> 0.52984925 | N8: =ACTIVE!H33 -> 10380311
C9: Mkt sh | E9: Mkt sh | G9: Mkt sh | I9: Mkt sh | K9: Mkt sh | M9: Mkt sh
A10: Company Demand (Units) | B10: =ACTIVE!B85 -> 73793 | C10: =B10/B6 -> 0.19732648 | D10: =ACTIVE!B86 -> 30809 | E10: =D10/D6 -> 0.18098987 | F10: =ACTIVE!B87 -> 21253 | G10: =F10/F6 -> 0.18158594 | H10: =ACTIVE!B88 -> 48634 | I10: =H10/H6 -> 0.19498759 | J10: =ACTIVE!B89 -> 51834 | K10: =J10/J6 -> 0.19036252 | L10: =ACTIVE!B90 -> 156527 | M10: =L10/L6 -> 0.21750918 | N10: =SUM(ACTIVE!B85:B90) -> 382850
A11: Company Sales (Units) | B11: =ACTIVE!B91 -> 73793 | C11: =B11/B7 -> 0.19732648 | D11: =ACTIVE!B92 -> 30809 | E11: =D11/D7 -> 0.18098987 | F11: =ACTIVE!B93 -> 21253 | G11: =F11/F7 -> 0.18158594 | H11: =ACTIVE!B94 -> 48634 | I11: =H11/H7 -> 0.19498759 | J11: =ACTIVE!B95 -> 51834 | K11: =J11/J7 -> 0.19036252 | L11: =ACTIVE!B96 -> 127968 | M11: =L11/L7 -> 0.17782373 | N11: =SUM(ACTIVE!B91:B96) -> 354291
A12: Additional Sales (Units) | B12: =ACTIVE!B97 -> 0 | C12: =B12/B7 -> 0 | D12: =ACTIVE!B98 -> 0 | E12: =D12/D7 -> 0 | F12: =ACTIVE!B99 -> 0 | G12: =F12/F7 -> 0 | H12: =ACTIVE!B100 -> 0 | I12: =H12/H7 -> 0 | J12: =ACTIVE!B101 -> 0 | K12: =J12/J7 -> 0 | L12: =ACTIVE!B102 -> 0 | M12: =L12/L7 -> 0 | N12: =SUM(ACTIVE!B97:B102) -> 0
A13: Company Marketing Exp | B13: =B18 -> 14000040 | C13: =B13/B8 -> 0.17199056 | D13: =D18 -> 600000 | E13: =D13/D8 -> 0.1960772 | F13: =F18 -> 600002 | G13: =F13/F8 -> 0.1785717 | H13: =H18 -> 149999.85 | I13: =H13/H8 -> 0.16853925 | J13: =J18 -> 249999.75 | K13: =J13/J8 -> 0.17543855 | L13: =L18 -> 1000000 | M13: =L13/L8 -> 0.18181818
C14: % Sls | E14: % Sls | G14: % Sls | I14: % Sls | K14: % Sls | M14: % Sls
A15: Company Sales (currency) | B15: =ACTIVE!B103 -> 295172000 | C15: =(B15/ACTIVE!B49)/'Market Report'!N15 -> 0.20283744 | D15: =ACTIVE!B104 -> 11091240 | E15: =(D15/ACTIVE!C49)/'Market Report'!N15 -> 0.053590228 | F15: =ACTIVE!B105 -> 7226020 | G15: =(F15/ACTIVE!D49)/'Market Report'!N15 -> 0.068754522 | H15: =ACTIVE!B106 -> 1459020 | I15: =(H15/ACTIVE!E49)/'Market Report'!N15 -> 0.13882362 | J15: =ACTIVE!B107 -> 2436198 | K15: =(J15/ACTIVE!F49)/'Market Report'!N15 -> 0.19567589 | L15: =ACTIVE!B108 -> 5502624 | M15: =L15/N15 -> 0.3403183 | N15: =L15+(J15/ACTIVE!F$49)+('Market Report'!H15/ACTIVE!E$49)+('Market Report'!F15/ACTIVE!D$49)+('Market Report'!D15/ACTIVE!C$49)+('Market Report'!B15/ACTIVE!B$49) -> 16169051
A16: Delivered Mfg Cost | B16: =ACTIVE!B109*ACTIVE!B91 -> 1.2704897e+08 | C16: =B16/B15 -> 0.43042352 | D16: =ACTIVE!B110*ACTIVE!B92 -> 8017215.2 | E16: =D16/D$15 -> 0.7228421 | F16: =ACTIVE!B111*ACTIVE!B93 -> 2642695.2 | G16: =F16/F$15 -> 0.36571933 | H16: =ACTIVE!B112*ACTIVE!B94 -> 623704.65 | I16: =H16/H$15 -> 0.4274819 | J16: =ACTIVE!B113*ACTIVE!B95 -> 787464.68 | K16: =J16/J$15 -> 0.32323509 | L16: =ACTIVE!B114*ACTIVE!B96 -> 2524800.2 | M16: =L16/L$15 -> 0.45883567 | N16: =L16+(J16/ACTIVE!F$49)+('Market Report'!H16/ACTIVE!E$49)+('Market Report'!F16/ACTIVE!D$49)+('Market Report'!D16/ACTIVE!C$49)+('Market Report'!B16/ACTIVE!B$49) -> 6951595.9
A17: Gross Margin | B17: =B15-B16 -> 1.6812303e+08 | C17: =B17/B15 -> 0.56957648 | D17: =D15-D16 -> 3074024.8 | E17: =D17/D$15 -> 0.2771579 | F17: =F15-F16 -> 4583324.8 | G17: =F17/F$15 -> 0.63428067 | H17: =H15-H16 -> 835315.35 | I17: =H17/H$15 -> 0.5725181 | J17: =J15-J16 -> 1648733.3 | K17: =J17/J$15 -> 0.67676491 | L17: =L15-L16 -> 2977823.8 | M17: =L17/L$15 -> 0.54116433 | N17: =L17+(J17/ACTIVE!F$49)+('Market Report'!H17/ACTIVE!E$49)+('Market Report'!F17/ACTIVE!D$49)+('Market Report'!D17/ACTIVE!C$49)+('Market Report'!B17/ACTIVE!B$49) -> 9217455.2
A18: Company Marketing Exp | B18: =ACTIVE!B115 -> 14000040 | C18: =B18/B15 -> 0.047430109 | D18: =ACTIVE!B116 -> 600000 | E18: =D18/D$15 -> 0.054096747 | F18: =ACTIVE!B117 -> 600002 | G18: =F18/F$15 -> 0.083033537 | H18: =ACTIVE!B118 -> 149999.85 | I18: =H18/H$15 -> 0.10280863 | J18: =ACTIVE!B119 -> 249999.75 | K18: =J18/J$15 -> 0.10261881 | L18: =ACTIVE!B120 -> 1000000 | M18: =L18/L$15 -> 0.18173148 | N18: =L18+(J18/ACTIVE!F$49)+('Market Report'!H18/ACTIVE!E$49)+('Market Report'!F18/ACTIVE!D$49)+('Market Report'!D18/ACTIVE!C$49)+('Market Report'!B18/ACTIVE!B$49) -> 1850183
A19: Import Tariffs | B19: =ACTIVE!B121 -> 26565480 | C19: =B19/B15 -> 0.09 | D19: =ACTIVE!B122 -> 765295.56 | E19: =D19/D$15 -> 0.069 | F19: =ACTIVE!B123 -> 0 | G19: =F19/F$15 -> 0 | H19: =ACTIVE!B124 -> 167787.3 | I19: =H19/H$15 -> 0.115 | J19: =ACTIVE!B125 -> 280162.77 | K19: =J19/J$15 -> 0.115 | L19: =ACTIVE!B126 -> 316400.88 | M19: =L19/L$15 -> 0.0575 | N19: =L19+(J19/ACTIVE!F$49)+('Market Report'!H19/ACTIVE!E$49)+('Market Report'!F19/ACTIVE!D$49)+('Market Report'!D19/ACTIVE!C$49)+('Market Report'!B19/ACTIVE!B$49) -> 1293343.7
A20: Contribution Margin | B20: =B17-B18-B19 -> 1.2755751e+08 | C20: =B20/B15 -> 0.43214638 | D20: =D17-D18-D19 -> 1708729.2 | E20: =D20/D$15 -> 0.15406116 | F20: =F17-F18-F19 -> 3983322.8 | G20: =F20/F$15 -> 0.55124714 | H20: =H17-H18-H19 -> 517528.2 | I20: =H20/H$15 -> 0.35470946 | J20: =J17-J18-J19 -> 1118570.8 | K20: =J20/J$15 -> 0.4591461 | L20: =L17-L18-L19 -> 1661422.9 | M20: =L20/L$15 -> 0.30193285 | N20: =L20+(J20/ACTIVE!F$49)+('Market Report'!H20/ACTIVE!E$49)+('Market Report'!F20/ACTIVE!D$49)+('Market Report'!D20/ACTIVE!C$49)+('Market Report'!B20/ACTIVE!B$49) -> 6073928.6
A21: Green Value of My Product 2 | C21: =ACTIVE!B274 -> 0.63942685
A22: Average Green Value of all Product 2 | C22: =ACTIVE!B276 -> 0.64317896 | F22: Product 2 Market Statistics | N22: World
B23: Japan | C23: % Wld | D23: Mexico | E23: % Wld | F23: China | G23: % Wld | H23: U.K. | I23: % Wld | J23: Germany | K23: % Wld | L23: U.S. | M23: % Wld | N23: Totals
A24: Total Demand (Units) | B24: =ACTIVE!B8 -> 309515 | C24: =B24/N24 -> 0.16535122 | D24: =ACTIVE!C8 -> 107891 | E24: =D24/N24 -> 0.057638269 | F24: =ACTIVE!D8 -> 107891 | G24: =F24/N24 -> 0.057638269 | H24: =ACTIVE!E8 -> 256574 | I24: =H24/N24 -> 0.13706872 | J24: =ACTIVE!F8 -> 321427 | K24: =J24/N24 -> 0.17171493 | L24: =ACTIVE!G8 -> 768566 | M24: =L24/N24 -> 0.41058859 | N24: =ACTIVE!H8 -> 1871864
A25: Total Sales (Units) | B25: =ACTIVE!B9 -> 309515 | C25: =B25/N25 -> 0.16535122 | D25: =ACTIVE!C9 -> 107891 | E25: =D25/N25 -> 0.057638269 | F25: =ACTIVE!D9 -> 107891 | G25: =F25/N25 -> 0.057638269 | H25: =ACTIVE!E9 -> 256574 | I25: =H25/N25 -> 0.13706872 | J25: =ACTIVE!F9 -> 321427 | K25: =J25/N25 -> 0.17171493 | L25: =ACTIVE!G9 -> 768566 | M25: =L25/N25 -> 0.41058859 | N25: =ACTIVE!H9 -> 1871864
A26: Total Marketing Exp P2 | B26: =ACTIVE!B34 -> 83700000 | C26: =(B26/ACTIVE!B49)/'Market Report'!N26 -> 0.076795871 | D26: =ACTIVE!C34 -> 3700006.4 | E26: =(D26/ACTIVE!C49)/'Market Report'!N26 -> 0.023869726 | F26: =ACTIVE!D34 -> 3971006 | G26: =(F26/ACTIVE!D49)/'Market Report'!N26 -> 0.050447786 | H26: =ACTIVE!E34 -> 1089999.9 | I26: =(H26/ACTIVE!E49)/'Market Report'!N26 -> 0.13847394 | J26: =ACTIVE!F34 -> 1834999.3 | K26: =(J26/ACTIVE!F49)/'Market Report'!N26 -> 0.19678868 | L26: =ACTIVE!G34 -> 6220000 | M26: =L26/N26 -> 0.513624 | N26: =ACTIVE!H34 -> 12110026
C27: Mkt sh | E27: Mkt sh | G27: Mkt sh | I27: Mkt sh | K27: Mkt sh | M27: Mkt sh
A28: Company Demand (Units) | B28: =ACTIVE!B127 -> 66044 | C28: =B28/B24 -> 0.213379 | D28: =ACTIVE!B128 -> 22257 | E28: =D28/D24 -> 0.20629153 | F28: =ACTIVE!B129 -> 22786 | G28: =F28/F24 -> 0.21119463 | H28: =ACTIVE!B130 -> 56320 | I28: =H28/H24 -> 0.21950782 | J28: =ACTIVE!B131 -> 65387 | K28: =J28/J24 -> 0.20342722 | L28: =ACTIVE!B132 -> 156719 | M28: =L28/L24 -> 0.20391092 | N28: =SUM(ACTIVE!B127:B132) -> 389513
A29: Company Sales (Units) | B29: =ACTIVE!B133 -> 66044 | C29: =B29/B25 -> 0.213379 | D29: =ACTIVE!B134 -> 22257 | E29: =D29/D25 -> 0.20629153 | F29: =ACTIVE!B135 -> 22786 | G29: =F29/F25 -> 0.21119463 | H29: =ACTIVE!B136 -> 56320 | I29: =H29/H25 -> 0.21950782 | J29: =ACTIVE!B137 -> 65387 | K29: =J29/J25 -> 0.20342722 | L29: =ACTIVE!B138 -> 156719 | M29: =L29/L25 -> 0.20391092 | N29: =SUM(ACTIVE!B133:B138) -> 389513
A30: Excess Demand (Units) | B30: =ACTIVE!B139 -> 0 | C30: =B30/B25 -> 0 | D30: =ACTIVE!B140 -> 0 | E30: =D30/D25 -> 0 | F30: =ACTIVE!B141 -> 0 | G30: =F30/F25 -> 0 | H30: =ACTIVE!B142 -> 0 | I30: =H30/H25 -> 0 | J30: =ACTIVE!B143 -> 0 | K30: =J30/J25 -> 0 | L30: =ACTIVE!B144 -> 0 | M30: =L30/L25 -> 0 | N30: =SUM(ACTIVE!B139:B144) -> 0
A31: Company Marketing Exp | B31: =ACTIVE!B157 -> 17000010 | C31: =B31/B26 -> 0.20310645 | D31: =ACTIVE!B158 -> 800000 | E31: =D31/D26 -> 0.21621584 | F31: =ACTIVE!B159 -> 880002.5 | G31: =F31/F26 -> 0.22160694 | H31: =ACTIVE!B160 -> 220000.3 | I31: =H31/H26 -> 0.20183515 | J31: =ACTIVE!B161 -> 349999.65 | K31: =J31/J26 -> 0.19073557 | L31: =ACTIVE!B162 -> 1200000 | M31: =L31/L26 -> 0.19292605
C32: % Sls | E32: % Sls | G32: % Sls | I32: % Sls | K32: % Sls | M32: % Sls
A33: Company Sales (currency) | B33: =ACTIVE!B145 -> 4.028684e+08 | C33: =(B33/ACTIVE!B49)/'Market Report'!N33 -> 0.18848525 | D33: =ACTIVE!B146 -> 10015650 | E33: =(D33/ACTIVE!C49)/'Market Report'!N33 -> 0.032947756 | F33: =ACTIVE!B147 -> 10253700 | G33: =(F33/ACTIVE!D49)/'Market Report'!N33 -> 0.066423831 | H33: =ACTIVE!B148 -> 2252800 | I33: =(H33/ACTIVE!E49)/'Market Report'!N33 -> 0.14593718 | J33: =ACTIVE!B149 -> 3596285 | K33: =(J33/ACTIVE!F49)/'Market Report'!N33 -> 0.19666182 | L33: =ACTIVE!B150 -> 8776264 | M33: =L33/N33 -> 0.36954417 | N33: =L33+(J33/ACTIVE!F$49)+('Market Report'!H33/ACTIVE!E$49)+('Market Report'!F33/ACTIVE!D$49)+('Market Report'!D33/ACTIVE!C$49)+('Market Report'!B33/ACTIVE!B$49) -> 23748891
A34: Delivered Mfg Cost | B34: =ACTIVE!B151*ACTIVE!B133 -> 1.6400095e+08 | C34: =B34/B$33 -> 0.40708319 | D34: =ACTIVE!B152*ACTIVE!B134 -> 8031378 | E34: =D34/D$33 -> 0.80188286 | F34: =ACTIVE!B153*ACTIVE!B135 -> 4086504.2 | G34: =F34/F$33 -> 0.39853947 | H34: =ACTIVE!B154*ACTIVE!B136 -> 1043005.6 | I34: =H34/H$33 -> 0.46298191 | J34: =ACTIVE!B155*ACTIVE!B137 -> 1434474.4 | K34: =J34/J$33 -> 0.39887672 | L34: =ACTIVE!B156*ACTIVE!B138 -> 4418095.8 | M34: =L34/L$33 -> 0.50341418 | N34: =L34+(J34/ACTIVE!F$49)+('Market Report'!H34/ACTIVE!E$49)+('Market Report'!F34/ACTIVE!D$49)+('Market Report'!D34/ACTIVE!C$49)+('Market Report'!B34/ACTIVE!B$49) -> 10964051
A35: Gross Margin | B35: =B33-B34 -> 2.3886745e+08 | C35: =B35/B$33 -> 0.59291681 | D35: =D33-D34 -> 1984272 | E35: =D35/D$33 -> 0.19811714 | F35: =F33-F34 -> 6167195.8 | G35: =F35/F$33 -> 0.60146053 | H35: =H33-H34 -> 1209794.4 | I35: =H35/H$33 -> 0.53701809 | J35: =J33-J34 -> 2161810.6 | K35: =J35/J$33 -> 0.60112328 | L35: =L33-L34 -> 4358168.2 | M35: =L35/L$33 -> 0.49658582 | N35: =L35+(J35/ACTIVE!F$49)+('Market Report'!H35/ACTIVE!E$49)+('Market Report'!F35/ACTIVE!D$49)+('Market Report'!D35/ACTIVE!C$49)+('Market Report'!B35/ACTIVE!B$49) -> 12784840
A36: Marketing Expenses | B36: =B31 -> 17000010 | C36: =B36/B$33 -> 0.042197427 | D36: =D31 -> 800000 | E36: =D36/D$33 -> 0.079874996 | F36: =F31 -> 880002.5 | G36: =F36/F$33 -> 0.085822922 | H36: =H31 -> 220000.3 | I36: =H36/H$33 -> 0.097656383 | J36: =J31 -> 349999.65 | K36: =J36/J$33 -> 0.097322556 | L36: =L31 -> 1200000 | M36: =L36/L$33 -> 0.13673244 | N36: =L36+(J36/ACTIVE!F$49)+('Market Report'!H36/ACTIVE!E$49)+('Market Report'!F36/ACTIVE!D$49)+('Market Report'!D36/ACTIVE!C$49)+('Market Report'!B36/ACTIVE!B$49) -> 2379781
A37: Import Tariffs | B37: =ACTIVE!B163 -> 0 | C37: =B37/B$33 -> 0 | D37: =ACTIVE!B164 -> 691079.85 | E37: =D37/D$33 -> 0.069 | F37: =ACTIVE!B165 -> 943340.4 | G37: =F37/F$33 -> 0.092 | H37: =ACTIVE!B166 -> 259072 | I37: =H37/H$33 -> 0.115 | J37: =ACTIVE!B167 -> 413572.78 | K37: =J37/J$33 -> 0.115 | L37: =ACTIVE!B168 -> 504635.18 | M37: =L37/L$33 -> 0.0575 | N37: =L37+(J37/ACTIVE!F$49)+('Market Report'!H37/ACTIVE!E$49)+('Market Report'!F37/ACTIVE!D$49)+('Market Report'!D37/ACTIVE!C$49)+('Market Report'!B37/ACTIVE!B$49) -> 1639434.9
A38: Contribution Margin | B38: =B35-B36-B37 -> 2.2186744e+08 | C38: =B38/B$33 -> 0.55071938 | D38: =D35-D36-D37 -> 493192.1 | E38: =D38/D$33 -> 0.049242146 | F38: =F35-F36-F37 -> 4343852.9 | G38: =F38/F$33 -> 0.42363761 | H38: =H35-H36-H37 -> 730722.06 | I38: =H38/H$33 -> 0.32436171 | J38: =J35-J36-J37 -> 1398238.2 | K38: =J38/J$33 -> 0.38880072 | L38: =L35-L36-L37 -> 2653533.1 | M38: =L38/L$33 -> 0.30235338 | N38: =L38+(J38/ACTIVE!F$49)+('Market Report'!H38/ACTIVE!E$49)+('Market Report'!F38/ACTIVE!D$49)+('Market Report'!D38/ACTIVE!C$49)+('Market Report'!B38/ACTIVE!B$49) -> 8765624
F40: Product 1 Prices | I40: Absolute Quality of My Product 1 | L40: =ACTIVE!B271 -> 0.67340925 | N40: RELATIVE
B41: Japan | C41: rel prc | D41: Mexico | E41: rel prc | F41: China | G41: rel prc | H41: U.K. | I41: rel prc | J41: Germany | K41: rel prc | L41: U.S. | M41: rel prc | N41: QUALITY
A42: Company 1 | B42: =IF(ACTIVE!B13=0,"",ACTIVE!B13) -> 4000 | C42: =IF(B42="","",B42/B$47) -> 1.0362694 | D42: =IF(ACTIVE!C13=0,"",ACTIVE!C13) -> 360 | E42: =IF(D42="","",D42/D$47) -> 1.0538642 | F42: =IF(ACTIVE!D13=0,"",ACTIVE!D13) -> 340 | G42: =IF(F42="","",F42/F$47) -> 1.0519802 | H42: =IF(ACTIVE!E13=0,"",ACTIVE!E13) -> 30 | I42: =IF(H42="","",H42/H$47) -> 1.0273973 | J42: =IF(ACTIVE!F13=0,"",ACTIVE!F13) -> 47 | K42: =IF(J42="","",J42/J$47) -> 1.0523959 | L42: =IF(ACTIVE!G13=0,"",ACTIVE!G13) -> 43 | M42: =IF(L42="","",L42/L$47) -> 0.97660686 | N42: =ACTIVE!B$71 -> 1.0515906
A43: Company 2 | B43: =IF(ACTIVE!B14=0,"",ACTIVE!B14) -> 3400 | C43: =IF(B43="","",B43/B$47) -> 0.88082902 | D43: =IF(ACTIVE!C14=0,"",ACTIVE!C14) -> 306 | E43: =IF(D43="","",D43/D$47) -> 0.89578454 | F43: =IF(ACTIVE!D14=0,"",ACTIVE!D14) -> 289 | G43: =IF(F43="","",F43/F$47) -> 0.89418317 | H43: =IF(ACTIVE!E14=0,"",ACTIVE!E14) -> 26 | I43: =IF(H43="","",H43/H$47) -> 0.89041096 | J43: =IF(ACTIVE!F14=0,"",ACTIVE!F14) -> 41 | K43: =IF(J43="","",J43/J$47) -> 0.91804747 | L43: =IF(ACTIVE!G14=0,"",ACTIVE!G14) -> 37 | M43: =IF(L43="","",L43/L$47) -> 0.84033613 | N43: =ACTIVE!C$71 -> 0.98487861
A44: Company 3 | B44: =IF(ACTIVE!B15=0,"",ACTIVE!B15) -> 4100 | C44: =IF(B44="","",B44/B$47) -> 1.0621762 | D44: =IF(ACTIVE!C15=0,"",ACTIVE!C15) -> 400 | E44: =IF(D44="","",D44/D$47) -> 1.1709602 | F44: =IF(ACTIVE!D15=0,"",ACTIVE!D15) -> 350 | G44: =IF(F44="","",F44/F$47) -> 1.0829208 | H44: =IF(ACTIVE!E15=0,"",ACTIVE!E15) -> 30 | I44: =IF(H44="","",H44/H$47) -> 1.0273973 | J44: =IF(ACTIVE!F15=0,"",ACTIVE!F15) -> 46 | K44: =IF(J44="","",J44/J$47) -> 1.0300045 | L44: =IF(ACTIVE!G15=0,"",ACTIVE!G15) -> 45 | M44: =IF(L44="","",L44/L$47) -> 1.0220304 | N44: =ACTIVE!D$71 -> 1.0293533
A45: Company 4 | B45: =IF(ACTIVE!B16=0,"",ACTIVE!B16) -> 4000 | C45: =IF(B45="","",B45/B$47) -> 1.0362694 | D45: =IF(ACTIVE!C16=0,"",ACTIVE!C16) -> 300 | E45: =IF(D45="","",D45/D$47) -> 0.87822014 | F45: =IF(ACTIVE!D16=0,"",ACTIVE!D16) -> 280 | G45: =IF(F45="","",F45/F$47) -> 0.86633663 | H45: =IF(ACTIVE!E16=0,"",ACTIVE!E16) -> 28.5 | I45: =IF(H45="","",H45/H$47) -> 0.9760274 | J45: =IF(ACTIVE!F16=0,"",ACTIVE!F16) -> 44.65 | K45: =IF(J45="","",J45/J$47) -> 0.99977609 | L45: =IF(ACTIVE!G16=0,"",ACTIVE!G16) -> 50 | M45: =IF(L45="","",L45/L$47) -> 1.1355894 | N45: =ACTIVE!E$71 -> 1.0590031
A46: Company 5 | B46: =IF(ACTIVE!B17=0,"",ACTIVE!B17) -> 3800 | C46: =IF(B46="","",B46/B$47) -> 0.98445596 | D46: =IF(ACTIVE!C17=0,"",ACTIVE!C17) -> 342 | E46: =IF(D46="","",D46/D$47) -> 1.001171 | F46: =IF(ACTIVE!D17=0,"",ACTIVE!D17) -> 357 | G46: =IF(F46="","",F46/F$47) -> 1.1045792 | H46: =IF(ACTIVE!E17=0,"",ACTIVE!E17) -> 31.5 | I46: =IF(H46="","",H46/H$47) -> 1.0787671 | J46: =IF(ACTIVE!F17=0,"",ACTIVE!F17) -> 44.65 | K46: =IF(J46="","",J46/J$47) -> 0.99977609 | L46: =IF(ACTIVE!G17=0,"",ACTIVE!G17) -> 45.15 | M46: =IF(L46="","",L46/L$47) -> 1.0254372 | N46: =ACTIVE!F$71 -> 0.87517443
A47: Average Price | B47: =AVERAGE(B42:B46) -> 3860 | D47: =AVERAGE(D42:D46) -> 341.6 | F47: =AVERAGE(F42:F46) -> 323.2 | H47: =AVERAGE(H42:H46) -> 29.2 | J47: =AVERAGE(J42:J46) -> 44.66 | L47: =AVERAGE(L42:L46) -> 44.03
F49: Product 2 Prices | I49: Absolute Quality of My Product 2 | L49: =ACTIVE!B272 -> 0.74003205 | N49: RELATIVE
B50: Japan | C50: rel prc | D50: Mexico | E50: rel prc | F50: China | G50: rel prc | H50: U.K. | I50: rel prc | J50: Germany | K50: rel prc | L50: U.S. | M50: rel prc | N50: QUALITY
A51: Company 1 | B51: =IF(ACTIVE!B23=0,"",ACTIVE!B23) -> 6100 | C51: =IF(B51="","",B51/B$56) -> 1.0080978 | D51: =IF(ACTIVE!C23=0,"",ACTIVE!C23) -> 450 | E51: =IF(D51="","",D51/D$56) -> 1.0078387 | F51: =IF(ACTIVE!D23=0,"",ACTIVE!D23) -> 450 | G51: =IF(F51="","",F51/F$56) -> 1.0192525 | H51: =IF(ACTIVE!E23=0,"",ACTIVE!E23) -> 40 | I51: =IF(H51="","",H51/H$56) -> 0.98522167 | J51: =IF(ACTIVE!F23=0,"",ACTIVE!F23) -> 55 | K51: =IF(J51="","",J51/J$56) -> 1.0367578 | L51: =IF(ACTIVE!G23=0,"",ACTIVE!G23) -> 56 | M51: =IF(L51="","",L51/L$56) -> 1.0339734 | N51: =ACTIVE!B$72 -> 1.0709262
A52: Company 2 | B52: =IF(ACTIVE!B24=0,"",ACTIVE!B24) -> 5760 | C52: =B52/B$56 -> 0.95190878 | D52: =IF(ACTIVE!C24=0,"",ACTIVE!C24) -> 405 | E52: =D52/D$56 -> 0.90705487 | F52: =IF(ACTIVE!D24=0,"",ACTIVE!D24) -> 405 | G52: =F52/F$56 -> 0.91732729 | H52: =IF(ACTIVE!E24=0,"",ACTIVE!E24) -> 36 | I52: =H52/H$56 -> 0.88669951 | J52: =IF(ACTIVE!F24=0,"",ACTIVE!F24) -> 50 | K52: =J52/J$56 -> 0.94250707 | L52: =IF(ACTIVE!G24=0,"",ACTIVE!G24) -> 51 | M52: =L52/L$56 -> 0.94165436 | N52: =ACTIVE!C$72 -> 0.97445288
A53: Company 3 | B53: =IF(ACTIVE!B25=0,"",ACTIVE!B25) -> 6500 | C53: =B53/B$56 -> 1.0742026 | D53: =IF(ACTIVE!C25=0,"",ACTIVE!C25) -> 500 | E53: =D53/D$56 -> 1.1198208 | F53: =IF(ACTIVE!D25=0,"",ACTIVE!D25) -> 430 | G53: =F53/F$56 -> 0.97395243 | H53: =IF(ACTIVE!E25=0,"",ACTIVE!E25) -> 40 | I53: =H53/H$56 -> 0.98522167 | J53: =IF(ACTIVE!F25=0,"",ACTIVE!F25) -> 53 | K53: =J53/J$56 -> 0.99905749 | L53: =IF(ACTIVE!G25=0,"",ACTIVE!G25) -> 55 | M53: =L53/L$56 -> 1.0155096 | N53: =ACTIVE!D$72 -> 0.91949969
A54: Company 4 | B54: =IF(ACTIVE!B26=0,"",ACTIVE!B26) -> 6100 | C54: =B54/B$56 -> 1.0080978 | D54: =IF(ACTIVE!C26=0,"",ACTIVE!C26) -> 450 | E54: =D54/D$56 -> 1.0078387 | F54: =IF(ACTIVE!D26=0,"",ACTIVE!D26) -> 450 | G54: =F54/F$56 -> 1.0192525 | H54: =IF(ACTIVE!E26=0,"",ACTIVE!E26) -> 45 | I54: =H54/H$56 -> 1.1083744 | J54: =IF(ACTIVE!F26=0,"",ACTIVE!F26) -> 55 | K54: =J54/J$56 -> 1.0367578 | L54: =IF(ACTIVE!G26=0,"",ACTIVE!G26) -> 50 | M54: =L54/L$56 -> 0.92319055 | N54: =ACTIVE!E$72 -> 1.0142634
A55: Company 5 | B55: =IF(ACTIVE!B27=0,"",ACTIVE!B27) -> 5795 | C55: =B55/B$56 -> 0.95769294 | D55: =IF(ACTIVE!C27=0,"",ACTIVE!C27) -> 427.5 | E55: =D55/D$56 -> 0.95744681 | F55: =IF(ACTIVE!D27=0,"",ACTIVE!D27) -> 472.5 | G55: =F55/F$56 -> 1.0702152 | H55: =IF(ACTIVE!E27=0,"",ACTIVE!E27) -> 42 | I55: =H55/H$56 -> 1.0344828 | J55: =IF(ACTIVE!F27=0,"",ACTIVE!F27) -> 52.25 | K55: =J55/J$56 -> 0.98491989 | L55: =IF(ACTIVE!G27=0,"",ACTIVE!G27) -> 58.8 | M55: =L55/L$56 -> 1.0856721 | N55: =ACTIVE!F$72 -> 1.0208578
A56: Average price | B56: =AVERAGE(B51:B55) -> 6051 | D56: =AVERAGE(D51:D55) -> 446.5 | F56: =AVERAGE(F51:F55) -> 441.5 | H56: =AVERAGE(H51:H55) -> 40.6 | J56: =AVERAGE(J51:J55) -> 53.05 | L56: =AVERAGE(L51:L55) -> 54.16
D58: Contract Market information
D59: Price to beat
B60: Contract | D60: With zeo | F60: Your contract | H60: Your Contract | J60: Your Contract | L60: Contract
B61: Volume | D61: Contract | F61: Sales revenue | H61: Sales cost | I61: USD / | J61: Image for | L61: Volume
B62: This period | C62: Winner | D62: Advantage | F62: This period | G62: UNITS | H62: This period | I62: UNIT | J62: Next Period | L62: Next period
C63: =IF(SUM(ACTIVE!B73:K73)-MAX(ACTIVE!B73:K73)>0,"multi","") -> multi
B64: =ACTIVE!B79 -> 30000 | C64: =IF(SUM(ACTIVE!B73:K73)>MAX(ACTIVE!B73:K73),"",MAX(ACTIVE!B73:K73)) | D64: =ACTIVE!B81 -> 20 | F64: =ACTIVE!B83 -> 2800800 | G64: =ACTIVE!B82 -> 180000 | H64: =G64*I64 -> 3279251 | I64: =ACTIVE!B84 -> 18.218061 | J64: =ACTIVE!B246 -> 0 | L64: =ACTIVE!B245 -> 45000

Sheet PROD-RPT
A1: Period Currently Displayed | C1: =ACTIVE!A2 -> 62 | D1: PRODUCTION REPORT | I1: Select Period to View
A2: Company Number | C2: =ACTIVE!B78 -> 1
E3: PRODUCT # 1
E4: =IF(ACTIVE!B169=1,"JAPAN",IF(ACTIVE!B169=2,"MEXICO",IF(ACTIVE!B169=3,"CHINA",IF(ACTIVE!B169=4,"UNITED KINGDOM",IF(ACTIVE!B169=5,"GERMANY","UNITED STATES"))))) -> CHINA
C6: LOCAL CURRENCY | H6: RESTATED IN USD
B7: This period | C7: % Of Full | D7: This period @ | E7: Next Period @ | G7: This period | H7: This period @ | I7: Next Period @
B8: Actual | C8: Capacity | D8: Full Capacity | E8: Full Capacity | G8: Actual | H8: Full Capacity | I8: Full Capacity
A9: Production Quantity | B9: =ACTIVE!B171 -> 381774 | C9: =IF(B9=0,"",B9/D9) -> 1 | D9: =ACTIVE!B174 -> 381774 | E9: =ACTIVE!B177 -> 381834 | G9: =ACTIVE!B171 -> 381774 | H9: =ACTIVE!B174 -> 381774 | I9: =ACTIVE!B177 -> 381834
A10: Fixed Cost | B10: =ACTIVE!B172 -> 9262470.9 | C10: =IF(B10=0,"",B10/D10) -> 1 | D10: =ACTIVE!B175 -> 9262470.9 | E10: =ACTIVE!B178 -> 9186670.5 | G10: =ACTIVE!B172/(IF(ACTIVE!B$169=1,ACTIVE!B$49,IF(ACTIVE!B$169=2,ACTIVE!C$49,IF(ACTIVE!B$169=3,ACTIVE!D$49,IF(ACTIVE!B$169=4,ACTIVE!E$49,IF(ACTIVE!B$169=5,ACTIVE!F$49,ACTIVE!G$49)))))) -> 1424995.5 | H10: =ACTIVE!B175/(IF(ACTIVE!B$169=1,ACTIVE!$B$49,IF(ACTIVE!B$169=2,ACTIVE!$C$49,IF(ACTIVE!B$169=3,ACTIVE!$D$49,IF(ACTIVE!B$169=4,ACTIVE!$E$49,IF(ACTIVE!B$169=5,ACTIVE!$F$49,ACTIVE!$G$49)))))) -> 1424995.5 | I10: =ACTIVE!B178/(IF(ACTIVE!B$169=1,ACTIVE!$B$50,IF(ACTIVE!B$169=2,ACTIVE!$C$50,IF(ACTIVE!B$169=3,ACTIVE!$D$50,IF(ACTIVE!B$169=4,ACTIVE!$E$50,IF(ACTIVE!B$169=5,ACTIVE!$F$50,ACTIVE!$G$50)))))) -> 1506011.5
A11: Variable Cost | B11: =ACTIVE!B173 -> 35058253 | C11: =IF(B11=0,"",B11/D11) -> 1 | D11: =ACTIVE!B176 -> 35058253 | E11: =ACTIVE!B179 -> 34821776 | G11: =ACTIVE!B173/(IF(ACTIVE!B$169=1,ACTIVE!B$49,IF(ACTIVE!B$169=2,ACTIVE!C$49,IF(ACTIVE!B$169=3,ACTIVE!D$49,IF(ACTIVE!B$169=4,ACTIVE!E$49,IF(ACTIVE!B$169=5,ACTIVE!F$49,ACTIVE!G$49)))))) -> 5393577.3 | H11: =ACTIVE!B176/(IF(ACTIVE!B$169=1,ACTIVE!$B$49,IF(ACTIVE!B$169=2,ACTIVE!$C$49,IF(ACTIVE!B$169=3,ACTIVE!$D$49,IF(ACTIVE!B$169=4,ACTIVE!$E$49,IF(ACTIVE!B$169=5,ACTIVE!$F$49,ACTIVE!$G$49)))))) -> 5393577.3 | I11: =ACTIVE!B179/(IF(ACTIVE!B$169=1,ACTIVE!$B$50,IF(ACTIVE!B$169=2,ACTIVE!$C$50,IF(ACTIVE!B$169=3,ACTIVE!$D$50,IF(ACTIVE!B$169=4,ACTIVE!$E$50,IF(ACTIVE!B$169=5,ACTIVE!$F$50,ACTIVE!$G$50)))))) -> 5708487.9
A12: Total Cost | B12: =B10+B11 -> 44320724 | C12: =IF(B12=0,"",B12/D12) -> 1 | D12: =D10+D11 -> 44320724 | E12: =E11+E10 -> 44008447 | G12: =G10+G11 -> 6818572.8 | H12: =H10+H11 -> 6818572.8 | I12: =I10+I11 -> 7214499.5
A13: Variable Cost per unit | B13: =IF(B11=0,0,B11/B9) -> 91.829859 | C13: =IF(B13=0,"",B13/D13) -> 1 | D13: =IF(D11=0,0,D11/D9) -> 91.829859 | E13: =IF(E11=0,0,E11/E9) -> 91.196112 | G13: =IF(G11=0,0,G11/G9) -> 14.127671 | H13: =IF(H11=0,0,H11/H9) -> 14.127671 | I13: =IF(I11=0,0,I11/I9) -> 14.950182
A14: Total Cost per unit | B14: =IF(B12=0,0,B12/B9) -> 116.09152 | C14: =IF(B14=0,"",B14/D14) -> 1 | D14: =IF(D12=0,0,D12/D9) -> 116.09152 | E14: =IF(E12=0,0,E12/E9) -> 115.25544 | G14: =IF(G12=0,0,G12/G9) -> 17.860234 | H14: =IF(H12=0,0,H12/H9) -> 17.860234 | I14: =IF(I12=0,0,I12/I9) -> 18.894335
D16: INVENTORY PRODUCT 1
A17: Inventory is valued | B17: Inventory | D17: Inventory | E17: Inventory | F17: Total | G17: Months of | H17: Maximum Possible construction
A18: in local currency | B18: Produced | D18: Produced | E18: Purchased | F18: Inventory | G18: Sales | H18: Next Time Period - Product 1
B19: Previously | D19: This period | E19: This period | H19: Max Units | I19: =0.15*I9 -> 57275.1
A20: UNITS | B20: =ACTIVE!B189 -> 0 | D20: =ACTIVE!B192 -> 0 | E20: =ACTIVE!B195 -> 38285 | F20: =B20+D20+E20 -> 38285 | G20: =3*F20/SUM(ACTIVE!B91:B102) -> 0.32418266 | H20: Max Dollars | I20: =ACTIVE!B268 -> 916401.6
A21: VALUE | B21: =ACTIVE!B190 -> 0 | D21: =ACTIVE!B193 -> 0 | E21: =ACTIVE!B196 -> 5191121 | F21: =B21+D21+E21 -> 5191121
A22: COST / UNIT | B22: =ACTIVE!B191 -> 0 | D22: =ACTIVE!B194 -> 0 | E22: =ACTIVE!B197 -> 135.59152 | F22: =F21/F20 -> 135.59151
E24: PRODUCT # 2
E25: =IF(ACTIVE!B170=1,"JAPAN",IF(ACTIVE!B170=2,"MEXICO",IF(ACTIVE!B170=3,"CHINA",IF(ACTIVE!B170=4,"UNITED KINGDOM",IF(ACTIVE!B170=5,"GERMANY","UNITED STATES"))))) -> JAPAN
C27: LOCAL CURRENCY | H27: RESTATED IN USD
B28: This period | C28: % Of Full | D28: This period @ | E28: Next Period @ | G28: This period | H28: This period @ | I28: Next Period @
A29: PRODUCT # 2 | B29: Actual | C29: Capacity | D29: Full Capacity | E29: Full Capacity | G29: Actual | H29: Full Capacity | I29: Full Capacity
A30: Production Quantity | B30: =ACTIVE!B180 -> 365570 | C30: =IF(B30=0,"",B30/D30) -> 1 | D30: =ACTIVE!B183 -> 365570 | E30: =ACTIVE!B186 -> 364656 | G30: =ACTIVE!B180 -> 365570 | H30: =ACTIVE!B183 -> 365570 | I30: =ACTIVE!B186 -> 364656
A31: Fixed Cost | B31: =ACTIVE!B181 -> 214154470 | C31: =IF(B31=0,"",B31/D31) -> 1 | D31: =ACTIVE!B184 -> 214154470 | E31: =ACTIVE!B187 -> 2.1383576e+08 | G31: =ACTIVE!B181/(IF(ACTIVE!$B$170=1,ACTIVE!$B$49,IF(ACTIVE!$B$170=2,ACTIVE!$C$49,IF(ACTIVE!$B$170=3,ACTIVE!$D$49,IF(ACTIVE!$B$170=4,ACTIVE!$E$49,IF(ACTIVE!$B$170=5,ACTIVE!$F$49,ACTIVE!$G$49)))))) -> 2379494.1 | H31: =ACTIVE!$B184/(IF(ACTIVE!$B$170=1,ACTIVE!$B$49,IF(ACTIVE!$B$170=2,ACTIVE!$C$49,IF(ACTIVE!$B$170=3,ACTIVE!$D$49,IF(ACTIVE!$B$170=4,ACTIVE!$E$49,IF(ACTIVE!$B$170=5,ACTIVE!$F$49,ACTIVE!$G$49)))))) -> 2379494.1 | I31: =ACTIVE!$B187/(IF(ACTIVE!$B$170=1,ACTIVE!$B$50,IF(ACTIVE!$B$170=2,ACTIVE!$C$50,IF(ACTIVE!$B$170=3,ACTIVE!$D$50,IF(ACTIVE!$B$170=4,ACTIVE!$E$50,IF(ACTIVE!$B$170=5,ACTIVE!$F$50,ACTIVE!$G$50)))))) -> 2375952.9
A32: Variable Cost | B32: =ACTIVE!B182 -> 650645803 | C32: =IF(B32=0,"",B32/D32) -> 1 | D32: =ACTIVE!B185 -> 650645803 | E32: =ACTIVE!B188 -> 652737820 | G32: =ACTIVE!B182/(IF(ACTIVE!$B$170=1,ACTIVE!B$49,IF(ACTIVE!$B$170=2,ACTIVE!C$49,IF(ACTIVE!$B$170=3,ACTIVE!D$49,IF(ACTIVE!$B$170=4,ACTIVE!E$49,IF(ACTIVE!$B$170=5,ACTIVE!F$49,ACTIVE!G$49)))))) -> 7229397.8 | H32: =ACTIVE!$B185/(IF(ACTIVE!$B$170=1,ACTIVE!$B$49,IF(ACTIVE!$B$170=2,ACTIVE!$C$49,IF(ACTIVE!$B$170=3,ACTIVE!$D$49,IF(ACTIVE!$B$170=4,ACTIVE!$E$49,IF(ACTIVE!$B$170=5,ACTIVE!$F$49,ACTIVE!$G$49)))))) -> 7229397.8 | I32: =ACTIVE!$B188/(IF(ACTIVE!$B$170=1,ACTIVE!$B$50,IF(ACTIVE!$B$170=2,ACTIVE!$C$50,IF(ACTIVE!$B$170=3,ACTIVE!$D$50,IF(ACTIVE!$B$170=4,ACTIVE!$E$50,IF(ACTIVE!$B$170=5,ACTIVE!$F$50,ACTIVE!$G$50)))))) -> 7252642.4
A33: Total Cost | B33: =B32+B31 -> 864800273 | C33: =IF(B33=0,"",B33/D33) -> 1 | D33: =D31+D32 -> 864800273 | E33: =E31+E32 -> 8.6657358e+08 | G33: =G31+G32 -> 9608891.9 | H33: =H31+H32 -> 9608891.9 | I33: =I31+I32 -> 9628595.3
A34: Variable Cost per unit | B34: =IF(B32=0,0,B32/B30) -> 1779.8118 | C34: =IF(B34=0,"",B34/D34) -> 1 | D34: =IF(D32=0,0,D32/D30) -> 1779.8118 | E34: =IF(E32=0,0,E32/E30) -> 1790.0098 | G34: =IF(G32=0,0,G32/G30) -> 19.775687 | H34: =IF(H32=0,0,H32/H30) -> 19.775687 | I34: =IF(I32=0,0,I32/I30) -> 19.888998
A35: Total Cost per unit | B35: =IF(B33=0,0,B33/B30) -> 2365.6216 | C35: =IF(B35=0,"",B35/D35) -> 1 | D35: =IF(D33=0,0,D33/D30) -> 2365.6216 | E35: =IF(E33=0,0,E33/E30) -> 2376.4139 | G35: =IF(G33=0,0,G33/G30) -> 26.284684 | H35: =IF(H33=0,0,H33/H30) -> 26.284684 | I35: =IF(I33=0,0,I33/I30) -> 26.404599
D37: INVENTORY PRODUCT 2
A38: Inventory is valued | B38: Inventory | D38: Inventory | E38: Inventory | F38: Total | G38: Months of | H38: Maximum Possible construction
A39: in local currency | B39: Produced | D39: Produced | E39: Purchased | F39: Inventory | G39: Sales | H39: Next Time Period - Product 2
B40: Previously | D40: This period | E40: This period | H40: Max Units | I40: =0.15*I30 -> 54698.4
A41: UNITS | B41: =ACTIVE!B198 -> 0 | D41: =ACTIVE!B201 -> 30349 | E41: =ACTIVE!B204 -> 8602 | F41: =B41+D41+E41 -> 38951 | G41: =3*F41/SUM(ACTIVE!B133:B138) -> 0.29999769 | H41: Max Dollars | I41: =ACTIVE!B269 -> 1367460
A42: VALUE | B42: =ACTIVE!B199 -> 0 | D42: =ACTIVE!B202 -> 71794260 | E42: =ACTIVE!B205 -> 22671630 | F42: =B42+D42+E42 -> 94465890
A43: COST / UNIT | B43: =ACTIVE!B200 -> 0 | D43: =ACTIVE!B203 -> 2365.6216 | E43: =ACTIVE!B206 -> 2635.6216
B45: TRANSPORTATION REPORT
F46: USD | H46: FACTORY RELOCATION ACTIVITY
E47: Number of shipping containers you have now | F47: =TRUNC((F56/1000)+0.5) -> 1080 | G47: NEW | H47: Company 1 | I47: Company 2 | J47: Company 3 | K47: Company 4 | L47: Company 5
E48: Depreciation cost of your shipping containers in USD | F48: =ACTIVE!B207 -> 170498 | G48: Location P1 | H48: =IF(ACTIVE!B74=0,"",IF(ACTIVE!B74=1,"Japan",IF(ACTIVE!B74=2,"Mexico",IF(ACTIVE!B74=3,"China",IF(ACTIVE!B74=4,"U.K.",IF(ACTIVE!B74=5,"Germany","U.S.")))))) | I48: =IF(ACTIVE!C74=0,"",IF(ACTIVE!C74=1,"Japan",IF(ACTIVE!C74=2,"Mexico",IF(ACTIVE!C74=3,"China",IF(ACTIVE!C74=4,"U.K.",IF(ACTIVE!C74=5,"Germany","U.S.")))))) | J48: =IF(ACTIVE!D74=0,"",IF(ACTIVE!D74=1,"Japan",IF(ACTIVE!D74=2,"Mexico",IF(ACTIVE!D74=3,"China",IF(ACTIVE!D74=4,"U.K.",IF(ACTIVE!D74=5,"Germany","U.S.")))))) | K48: =IF(ACTIVE!E74=0,"",IF(ACTIVE!E74=1,"Japan",IF(ACTIVE!E74=2,"Mexico",IF(ACTIVE!E74=3,"China",IF(ACTIVE!E74=4,"U.K.",IF(ACTIVE!E74=5,"Germany","U.S.")))))) | L48: =IF(ACTIVE!F74=0,"",IF(ACTIVE!F74=1,"Japan",IF(ACTIVE!F74=2,"Mexico",IF(ACTIVE!F74=3,"China",IF(ACTIVE!F74=4,"U.K.",IF(ACTIVE!F74=5,"Germany","U.S."))))))
E49: Fixed cost of maintaining your shipping containers USD | F49: =ACTIVE!B208 -> 318263 | G49: Location P2 | H49: =IF(ACTIVE!B75=0,"",IF(ACTIVE!B75=1,"Japan",IF(ACTIVE!B75=2,"Mexico",IF(ACTIVE!B75=3,"China",IF(ACTIVE!B75=4,"U.K.",IF(ACTIVE!B75=5,"Germany","U.S.")))))) | I49: =IF(ACTIVE!C75=0,"",IF(ACTIVE!C75=1,"Japan",IF(ACTIVE!C75=2,"Mexico",IF(ACTIVE!C75=3,"China",IF(ACTIVE!C75=4,"U.K.",IF(ACTIVE!C75=5,"Germany","U.S.")))))) | J49: =IF(ACTIVE!D75=0,"",IF(ACTIVE!D75=1,"Japan",IF(ACTIVE!D75=2,"Mexico",IF(ACTIVE!D75=3,"China",IF(ACTIVE!D75=4,"U.K.",IF(ACTIVE!D75=5,"Germany","U.S.")))))) | K49: =IF(ACTIVE!E75=0,"",IF(ACTIVE!E75=1,"Japan",IF(ACTIVE!E75=2,"Mexico",IF(ACTIVE!E75=3,"China",IF(ACTIVE!E75=4,"U.K.",IF(ACTIVE!E75=5,"Germany","U.S.")))))) | L49: =IF(ACTIVE!F75=0,"",IF(ACTIVE!F75=1,"Japan",IF(ACTIVE!F75=2,"Mexico",IF(ACTIVE!F75=3,"China",IF(ACTIVE!F75=4,"U.K.",IF(ACTIVE!F75=5,"Germany","U.S."))))))
E50: Cost of Renting containers requested by you USD | F50: =ACTIVE!B209 -> 0 | G50: Capacity P1 | H50: =IF(ACTIVE!B74=0,"",ACTIVE!B76) | I50: =IF(ACTIVE!C74=0,"",ACTIVE!C76) | J50: =IF(ACTIVE!D74=0,"",ACTIVE!D76) | K50: =IF(ACTIVE!E74=0,"",ACTIVE!E76) | L50: =IF(ACTIVE!F74=0,"",ACTIVE!F76)
E51: Emergency cost of renting containers NOT requested by you USD | F51: =ACTIVE!B210 -> 0 | G51: Capacity P2 | H51: =IF(ACTIVE!B75=0,"",ACTIVE!B77) | I51: =IF(ACTIVE!C75=0,"",ACTIVE!C77) | J51: =IF(ACTIVE!D75=0,"",ACTIVE!D77) | K51: =IF(ACTIVE!E75=0,"",ACTIVE!E77) | L51: =IF(ACTIVE!F75=0,"",ACTIVE!F77)
E52: Variable costs of shipping product -- USD | F52: =ACTIVE!B211 -> 837236.7 | G52: 1 = Japan | H52: 2 = Mexico | I52: 3 = China | J52: 4 = UK | K52: 5=Germany | L52: 6=US
E53: TOTAL SHIPPING COSTS - USD | F53: =SUM(F48:F52) -> 1325997.7
F55: UNITS
A56: Next period shipping capacity (units) if you do not buy any containers | F56: =ACTIVE!B212 -> 1079819
B58: Capacity Analysis | F58: Construction Costs for new factory capacity | G58: Japan | H58: Mexico | I58: China | J58: U.K. | K58: Germany | L58: United States
F59: Cost is in US dollars per unit of capacity | G59: 25 | H59: 17 | I59: 16 | J59: 22 | K59: 24 | L59: 20
B60: Company 1 | C60: Company 2 | D60: Company 3 | E60: Company 4 | F60: Company 5
A61: Product 1 Factroy Value | B61: =ACTIVE!B58 -> 6109343 | C61: =ACTIVE!C58 -> 6032023 | D61: =ACTIVE!D58 -> 6032023 | E61: =ACTIVE!E58 -> 8003715 | F61: =ACTIVE!F58 -> 6032023 | G61: Note: Divide by construction cost per unit for the country where
A62: Product 2 Factory Value | B62: =ACTIVE!B59 -> 9116399 | C62: =ACTIVE!C59 -> 7129774 | D62: =ACTIVE!D59 -> 7129774 | E62: =ACTIVE!E59 -> 10920000 | F62: =ACTIVE!F59 -> 9963480 | G62: each factory is located to calculate unit capacity.
B64: Inventory Analysis
B65: Company 1 | C65: Company 2 | D65: Company 3 | E65: Company 4 | F65: Company 5
A66: Product 1 Inventory Value | B66: =ACTIVE!B54 -> 798634 | C66: =ACTIVE!C54 -> 1943033 | D66: =ACTIVE!D54 -> 4499260 | E66: =ACTIVE!E54 -> 3189686 | F66: =ACTIVE!F54 -> 1199248
A67: Product 2 Inventory Value | B67: =ACTIVE!B55 -> 1049621 | C67: =ACTIVE!C55 -> 1012132 | D67: =ACTIVE!D55 -> 1822770 | E67: =ACTIVE!E55 -> 2218618 | F67: =ACTIVE!F55 -> 1044821

Sheet FIN-RPT
A1: Period Currently Displayed | C1: =ACTIVE!A2 -> 62 | G1: FINANCE REPORT | L1: Select Period to View
A2: Company Number | C2: =ACTIVE!B78 -> 1
A3: PERIOD NUMBER | B3: =ACTIVE!A2 -> 62 | F3: BALANCE SHEET DATA
B4: Company 1 | C4: % | D4: Company 2 | E4: % | F4: Company 3 | G4: % | H4: Company 4 | I4: % | J4: Company 5 | K4: % | N4: DETAILED INCOME STATEMENT
A5: Cash and Securities | B5: =ACTIVE!B52 -> 17058310 | C5: =B5/B$10 -> 0.33309835 | D5: =ACTIVE!C52 -> 14337599 | E5: =D5/D$10 -> 0.30051949 | F5: =ACTIVE!D52 -> 13181975 | G5: =F5/F$10 -> 0.26912181 | H5: =ACTIVE!E52 -> 15953846 | I5: =H5/H$10 -> 0.26559683 | J5: =ACTIVE!F52 -> 18473814 | K5: =IF(J$10=0,0,J5/J$10) -> 0.29581649 | N5: Sales Revenues | Q5: {=ACTIVE!$B$213:$B$216} -> 42718742 | R5: =Q5/Q$8 -> 0.99469619
A6: Receivables | B6: =ACTIVE!B53 -> 13839266 | C6: =B6/B$10 -> 0.27023994 | D6: =ACTIVE!C53 -> 13815783 | E6: =D6/D$10 -> 0.2895821 | F6: =ACTIVE!D53 -> 13068165 | G6: =F6/F$10 -> 0.26679827 | H6: =ACTIVE!E53 -> 16279448 | I6: =H6/H$10 -> 0.27101739 | J6: =ACTIVE!F53 -> 22480549 | K6: =IF(J$10=0,0,J6/J$10) -> 0.35997532 | N6: Interest Income | Q6: 227780 | R6: =Q6/Q$8 -> 0.0053038055
A7: Inventories | B7: =ACTIVE!B54+ACTIVE!B55 -> 1848255 | C7: =B7/B$10 -> 0.036090955 | D7: =ACTIVE!C54+ACTIVE!C55 -> 2955165 | E7: =D7/D$10 -> 0.061940962 | F7: =ACTIVE!D56 -> 6322030 | G7: =F7/F$10 -> 0.1290699 | H7: =ACTIVE!E56 -> 5408304 | I7: =H7/H$10 -> 0.090036495 | J7: =ACTIVE!F56 -> 2244069 | K7: =IF(J$10=0,0,J7/J$10) -> 0.035933707 | N7: Currency Trading Income | Q7: 0 | R7: =Q7/Q$8 -> 0
A8: Shipping Cont (Net) | B8: =ACTIVE!B57 -> 3239458 | C8: =B8/B$10 -> 0.063257035 | D8: =ACTIVE!C57 -> 3439038 | E8: =D8/D$10 -> 0.072083055 | F8: =ACTIVE!D57 -> 3247478 | G8: =F8/F$10 -> 0.066300167 | H8: =ACTIVE!E57 -> 3502596 | I8: =H8/H$10 -> 0.058310603 | J8: =ACTIVE!F57 -> 3256316 | K8: =IF(J$10=0,0,J8/J$10) -> 0.052142561 | N8: TOTAL REVENUES | Q8: 42946522 | R8: =Q8/Q$8 -> 1
A9: Plant and Equip (Net) | B9: =ACTIVE!B58+ACTIVE!B59 -> 15225742 | C9: =B9/B$10 -> 0.29731372 | D9: =ACTIVE!C60 -> 13161797 | E9: =D9/D$10 -> 0.2758744 | F9: =ACTIVE!D60 -> 13161797 | G9: =F9/F$10 -> 0.26870986 | H9: =ACTIVE!E60 -> 18923715 | I9: =H9/H$10 -> 0.31503868 | J9: =ACTIVE!F60 -> 15995503 | K9: =IF(J$10=0,0,J9/J$10) -> 0.25613193
A10: TOTAL ASSETS | B10: =ACTIVE!B61 -> 51211031 | D10: =ACTIVE!C61 -> 47709382 | F10: =ACTIVE!D61 -> 48981445 | G10: =F10/F$10 -> 1 | H10: =ACTIVE!E61 -> 60067909 | J10: =ACTIVE!F61 -> 62450251 | N10: Cost of goods sold | Q10: =ACTIVE!B217 -> 19859535 | R10: =Q10/Q$8 -> 0.46242476
N11: Gross Margin | Q11: =Q8-Q10 -> 23086987 | R11: =Q11/Q$8 -> 0.53757524
A12: Trade Payables | B12: {=ACTIVE!$B$62:$B$67} -> 8213732.4 | C12: =B12/B$17 -> 0.1603899 | D12: {=ACTIVE!$C$62:$C$67} -> 8029973.4 | E12: =D12/D$17 -> 0.16831015 | F12: {=ACTIVE!$D$62:$D$67} -> 8029973.4 | G12: =F12/F$17 -> 0.16393909 | H12: {=ACTIVE!$E$62:$E$67} -> 9294741.4 | I12: =H12/H$17 -> 0.15473722 | J12: {=ACTIVE!$F$62:$F$67} -> 7750000.2 | K12: =IF(J$17=0,0,J12/J$17) -> 0.12409878 | N12: OPERATING EXPENSES
A13: Taxes Payable | B13: 782650 | C13: =B13/B$17 -> 0.01528284 | D13: 794437 | E13: =D13/D$17 -> 0.016651589 | F13: 1113469 | G13: =F13/F$17 -> 0.022732465 | H13: -177067 | I13: =H13/H$17 -> -0.0029477803 | J13: 1521924 | K13: =IF(J$17=0,0,J13/J$17) -> 0.024370182 | N13: Transportation Expenses | Q13: {=ACTIVE!$B$218:$B$231} -> 1325997.7 | R13: =Q13/Q$8 -> 0.030875555
A14: Loans and Interest | B14: 22283217 | C14: =B14/B$17 -> 0.43512533 | D14: 21248394 | E14: =D14/D$17 -> 0.4453714 | F14: 23318568 | G14: =F14/F$17 -> 0.47606942 | H14: 32664757 | I14: =H14/H$17 -> 0.54379713 | J14: 32122418 | K14: =IF(J$17=0,0,J14/J$17) -> 0.51436812 | N14: Marketing Expenses | Q14: 4229964 | R14: =Q14/Q$8 -> 0.098493751
A15: Common Stock | B15: 1000000 | C15: =B15/B$17 -> 0.019527043 | D15: 1000000 | E15: =D15/D$17 -> 0.020960238 | F15: 1000000 | G15: =F15/F$17 -> 0.020415894 | H15: 1000000 | I15: =H15/H$17 -> 0.016647824 | J15: 1000000 | K15: =IF(J$17=0,0,J15/J$17) -> 0.016012746 | N15: Warehousing Expenses | Q15: 177236 | R15: =Q15/Q$8 -> 0.0041269
A16: Retained Earnings | B16: 18931432 | C16: =B16/B$17 -> 0.36967488 | D16: 16636578 | E16: =D16/D$17 -> 0.34870662 | F16: 15519435 | G16: =F16/F$17 -> 0.31684313 | H16: 17285478 | I16: =H16/H$17 -> 0.2877656 | J16: 20055909 | K16: =IF(J$17=0,0,J16/J$17) -> 0.32115017 | N16: Research & Development | Q16: 6240000 | R16: =Q16/Q$8 -> 0.14529698
A17: TOTAL LIAB & EQUITY | B17: 51211031 | D17: 47709382 | F17: 48981445 | H17: 60067909 | J17: 62450251 | N17: Interest Expense | Q17: 815763 | R17: =Q17/Q$8 -> 0.018994856
A18: Debt/Equity | B18: =B14/(B15+B16) -> 1.1179938 | D18: =D14/(D15+D16) -> 1.2047912 | F18: =F14/(F15+F16) -> 1.4115839 | H18: =H14/(H15+H16) -> 1.786377 | J18: =J14/(J15+J16) -> 1.5255774 | N18: Factory Depreciation | Q18: 190596 | R18: =Q18/Q$8 -> 0.0044379846
A19: DIVIDENDS PAID | B19: =ACTIVE!B68 -> 0 | D19: =ACTIVE!C68 -> 0 | F19: =ACTIVE!D68 -> 0 | H19: =ACTIVE!E68 -> 0 | J19: =ACTIVE!F68 -> 0 | N19: Factory Sale Loss | Q19: 1083003.6 | R19: =Q19/Q$8 -> 0.025217493
N20: Inventory Write Down | Q20: 0 | R20: =Q20/Q$8 -> 0
F21: INCOME STATEMENT DATA | N21: Consultants | Q21: 3191000 | R21: =Q21/Q$8 -> 0.07430171
B22: Company 1 | C22: % | D22: Company 2 | E22: % | F22: Company 3 | G22: % | H22: Company 4 | I22: % | J22: Company 5 | K22: % | N22: Insurance | Q22: 160000 | R22: =Q22/Q$8 -> 0.0037255636
A23: Total Sales Revenue | B23: =ACTIVE!B69 -> 42718742 | D23: =ACTIVE!C69 -> 40004345 | F23: =ACTIVE!D69 -> 36246031 | H23: =ACTIVE!E69 -> 39253391 | J23: =ACTIVE!F69 -> 41113091 | N23: Admin and Misc Expenses | Q23: 169775.04 | R23: =Q23/Q$8 -> 0.0039531731
A24: Net Income | B24: =ACTIVE!B70 -> 1519262.8 | C24: =B24/B23 -> 0.035564316 | D24: =ACTIVE!C70 -> 1542141.5 | E24: =D24/D23 -> 0.03854935 | F24: =ACTIVE!D70 -> 2161438.7 | G24: =F24/F23 -> 0.059632424 | H24: =ACTIVE!E70 -> -343721.6 | I24: =H24/H23 -> -0.0087564815 | J24: =ACTIVE!F70 -> 2954323.4 | K24: =IF(J23=0,0,J24/J23) -> 0.07185846 | N24: Bad Debt Expenses | Q24: 268960 | R24: =Q24/Q$8 -> 0.0062626725
A25: Annualized ROE | B25: =4*B24/SUM(B15:B16) -> 0.30489789 | D25: =4*D24/SUM(D15:D16) -> 0.34975981 | F25: =4*F24/SUM(F15:F16) -> 0.52336868 | H25: =4*H24/SUM(H15:H16) -> -0.075190071 | J25: =IF(SUM(J23:J24)=0,0,4*J24/SUM(J15:J16)) -> 0.56123408 | N25: Import Tariffs | Q25: 2932778.5 | R25: =Q25/Q$8 -> 0.068289082
N26: TOTAL OPERATING EXP | Q26: 40644609 | R26: =Q26/Q$8 -> 0.94640048
A27: From -->>> | F27: TARIFF RATES
A28: To | B28: Japan | D28: Mexico | F28: China | H28: U.K. | J28: Germany | L28: U.S. | N28: PRETAX INCOME | Q28: {=ACTIVE!$B$232:$B$234} -> 2301912.8 | R28: =Q28/Q$8 -> 0.053599518
A29: Japan | B29: {=ACTIVE!$B$35:$B$40} -> 0 | D29: {=ACTIVE!$C$35:$C$40} -> 0.09 | F29: {=ACTIVE!$D$35:$D$40} -> 0.09 | H29: {=ACTIVE!$E$35:$E$40} -> 0.09 | J29: {=ACTIVE!$F$35:$F$40} -> 0.09 | L29: {=ACTIVE!$G$35:$G$40} -> 0.09 | N29: TAXES | Q29: 782650 | R29: =Q29/Q$8 -> 0.018223827
A30: Mexico | B30: 0.069 | D30: 0 | F30: 0.069 | H30: 0.069 | J30: 0.069 | L30: 0 | N30: NET INCOME | Q30: 1519262.8 | R30: =Q30/Q$8 -> 0.03537569
A31: China | B31: 0.092 | D31: 0.092 | F31: 0 | H31: 0.092 | J31: 0.092 | L31: 0.092
A32: U.K. | B32: 0.115 | D32: 0.115 | F32: 0.115 | H32: 0 | J32: 0 | L32: 0.115
A33: Germany | B33: 0.115 | D33: 0.115 | F33: 0.115 | H33: 0 | J33: 0 | L33: 0.115 | Q33: INSURANCE SUMMARY
A34: U.S. | B34: 0.0575 | D34: 0 | F34: 0.0575 | H34: 0.0575 | J34: 0.0575 | L34: 0 | N34: Rates are USD per 100,000 coverage per QTR.
Q35: Rate | R35: Coverage $ | S35: Premium $
A36: From -->>> | F36: TRANSPORT RATES | O36: Property / Casualty | Q36: =ACTIVE!B238 -> 400 | R36: =ACTIVE!B235 -> 6250000 | S36: =(R36/100000)*Q36 -> 25000
A37: To | B37: Japan | D37: Mexico | F37: China | H37: U.K. | J37: Germany | L37: U.S. | O37: Directors & Officers | Q37: =ACTIVE!B239 -> 300 | R37: =ACTIVE!B236 -> 11666667 | S37: =(R37/100000)*Q37 -> 35000
A38: Japan | B38: {=ACTIVE!$B$41:$B$46} -> 0.6 | D38: {=ACTIVE!$C$41:$C$46} -> 1.2 | F38: {=ACTIVE!$D$41:$D$46} -> 0.6 | H38: {=ACTIVE!$E$41:$E$46} -> 1.5 | J38: {=ACTIVE!$F$41:$F$46} -> 1.5 | L38: {=ACTIVE!$G$41:$G$46} -> 1.2 | O38: Product Liability | Q38: =ACTIVE!B240 -> 1000 | R38: =ACTIVE!B237 -> 10000000 | S38: =(R38/100000)*Q38 -> 100000
A39: Mexico | B39: 1.2 | D39: 0.6 | F39: 1.8 | H39: 1.2 | J39: 1.2 | L39: 0.6
A40: China | B40: 0.6 | D40: 1.8 | F40: 0.6 | H40: 1.2 | J40: 1.2 | L40: 1.2
A41: U.K. | B41: 1.5 | D41: 1.2 | F41: 1.2 | H41: 0.6 | J41: 0.6 | L41: 0.9 | Q41: NEXT PERIOD DATA
A42: Germany | B42: 1.5 | D42: 1.2 | F42: 1.2 | H42: 0.6 | J42: 0.6 | L42: 0.9
A43: U.S. | B43: 1.2 | D43: 0.6 | F43: 1.2 | H43: 0.9 | J43: 0.9 | L43: 0.6 | N43: Max Loan | P43: =ACTIVE!B243 -> 39862863 | Q43: Company Image - Product 1 | S43: =ACTIVE!B247 -> 6.9234566
N44: Max New Loan | P44: =ACTIVE!B244 -> 17579646 | Q44: Company Image - Product 2 | S44: =ACTIVE!B248 -> 7.2
F45: CURRENCY CONTRACTS | Q45: %/Qtr
B46: Last Period | D46: Last Period | F46: This Period | H46: This Period | I46: Buy or | J46: Contracts | K46: Gain or | L46: Settlement | N46: Borrowing Interest Rate | Q46: =ACTIVE!B242/100 -> 0.0247
A47: Local Currency per USD | B47: Spot Rate | D47: Forward Rate | F47: Spot Rate | H47: Forward Rate | I47: Sell | J47: Millions | K47: Loss | L47: US Dollars | N47: Rate Earned on Excess Cash | Q47: =ACTIVE!B241/100 -> 0.014
A48: YEN | B48: =ACTIVE!B47 -> 89 | D48: =ACTIVE!B48 -> 91 | F48: =ACTIVE!B49 -> 90 | H48: =ACTIVE!B50 -> 90 | I48: =IF(ACTIVE!B249=0,"",IF(ACTIVE!B249<0,"Sell","Buy")) | J48: =IF(ACTIVE!B249<0,-1*ACTIVE!B249,ACTIVE!B249) -> 0 | K48: =IF(ACTIVE!B254=0,"",IF(ACTIVE!B254<0,"Loss","Gain")) | L48: =ACTIVE!B254 -> 0
A49: PESO | B49: =ACTIVE!C47 -> 12.8 | D49: =ACTIVE!C48 -> 13 | F49: =ACTIVE!C49 -> 12.8 | H49: =ACTIVE!C50 -> 12.7 | I49: =IF(ACTIVE!B250=0,"",IF(ACTIVE!B250<0,"Sell","Buy")) | J49: =IF(ACTIVE!B250<0,-1*ACTIVE!B250,ACTIVE!B250) -> 0 | K49: =IF(ACTIVE!B255=0,"",IF(ACTIVE!B255<0,"Loss","Gain")) | L49: =ACTIVE!B255 -> 0
A50: YUAN | B50: =ACTIVE!D47 -> 6.4 | D50: =ACTIVE!D48 -> 6.5 | F50: =ACTIVE!D49 -> 6.5 | H50: =ACTIVE!D50 -> 6.1 | I50: =IF(ACTIVE!B251=0,"",IF(ACTIVE!B251<0,"Sell","Buy")) | J50: =IF(ACTIVE!B251<0,-1*ACTIVE!B251,ACTIVE!B251) -> 0 | K50: =IF(ACTIVE!B256=0,"",IF(ACTIVE!B256<0,"Loss","Gain")) | L50: =ACTIVE!B256 -> 0
A51: POUND | B51: =ACTIVE!E47 -> 0.66 | D51: =ACTIVE!E48 -> 0.67 | F51: =ACTIVE!E49 -> 0.65 | H51: =ACTIVE!E50 -> 0.66 | I51: =IF(ACTIVE!B252=0,"",IF(ACTIVE!B252<0,"Sell","Buy")) | J51: =IF(ACTIVE!B252<0,-1*ACTIVE!B252,ACTIVE!B252) -> 0 | K51: =IF(ACTIVE!B257=0,"",IF(ACTIVE!B257<0,"Loss","Gain")) | L51: =ACTIVE!B257 -> 0
A52: EURO | B52: =ACTIVE!F47 -> 0.78 | D52: =ACTIVE!F48 -> 0.8 | F52: =ACTIVE!F49 -> 0.77 | H52: =ACTIVE!F50 -> 0.79 | I52: =IF(ACTIVE!B253=0,"",IF(ACTIVE!B253<0,"Sell","Buy")) | J52: =IF(ACTIVE!B253<0,-1*ACTIVE!B253,ACTIVE!B253) -> 0 | K52: =IF(ACTIVE!B258=0,"",IF(ACTIVE!B258<0,"Loss","Gain")) | L52: =ACTIVE!B258 -> 0

Sheet Cash Flow
A1: Select Period to View Period Currently Displayed | B1: =ACTIVE!A2 -> 62 | C1: CASH FLOW
A2: Company Number | B2: =ACTIVE!B78 -> 1 | C2: Report
H3: How Well Are You Managing Your Capital And Your Assets?
A4: CASH FLOWS FROM OPERATING ACTIVITIES | F4: Period 1 | G4: Period 2 | H4: Period 3 | I4: Period 4 | J4: Period 5 | K4: Period 6 | L4: Period 7 | M4: Period 8 | N4: Period 9 | O4: Period 10 | P4: Period 11 | Q4: Period 12 | R4: Period 13 | S4: Period 14 | T4: Period 15 | U4: Period 16 | V4: Period 17 | W4: Period 18 | X4: Period 19 | Y4: Period 20 | Z4: Period 21 | AA4: Period 22 | AB4: Period 23 | AC4: Period 24 | AD4: Period 25 | AE4: Period 26 | AF4: Period 27 | AG4: Period 28 | AH4: Period 29 | AI4: Period 30 | AJ4: Period 31 | AK4: Period 32 | AL4: Period 33 | AM4: Period 34 | AN4: Period 35 | AO4: Period 36 | AP4: Period 37 | AQ4: Period 38 | AR4: Period 39 | AS4: Period 40 | AT4: Period 41 | AU4: Period 42 | AV4: Period 43 | AW4: Period 44 | AX4: Period 45 | AY4: Period 46 | AZ4: Period 47 | BA4: Period 48 | BB4: Period 49 | BC4: Period 50 | BD4: Period 51 | BE4: Period 52 | BF4: Period 53 | BG4: Period 54 | BH4: Period 55 | BI4: Period 56 | BJ4: Period 57 | BK4: Period 58 | BL4: Period 59 | BM4: Period 60 | BN4: Period 61 | BO4: Period 62 | BP4: Period 63 | BQ4: Period 64 | BR4: Period 65 | BS4: Period 66 | BT4: Period 67 | BU4: Period 68 | BV4: Period 69 | BW4: Period 70 | BX4: Period 71 | BY4: Period 72 | BZ4: Period 73 | CA4: Period 74 | CB4: Period 75
A5: Net profits | C5: =ACTIVE!B70 -> 1519262.8 | E5: Net Operating Profit After Tax | F5: ='P1'!$B277 -> 4228837.3 | G5: ='P2'!$B277 -> 3384229 | H5: ='P3'!$B277 -> 2912688.1 | I5: ='P4'!$B277 -> 3877406.6 | J5: ='P5'!$B277 -> 4054908.5 | K5: ='P6'!$B277 -> 1546967.6 | L5: ='P7'!$B277 -> 661402.46 | M5: ='P8'!$B277 -> 3284959.9 | N5: ='P9'!$B277 -> 1739084.6 | O5: ='P10'!$B277 -> 2697048.1 | P5: ='P11'!$B277 -> 1100013.8 | Q5: ='P12'!$B277 -> 1347907.5 | R5: ='P13'!$B277 -> 3731054.9 | S5: ='P14'!$B277 -> 3795013.3 | T5: ='P15'!$B277 -> 1383625 | U5: ='P16'!$B277 -> 701096.28 | V5: ='P17'!$B277 -> 1270537.3 | W5: ='P18'!$B277 -> 2233533.8 | X5: ='P19'!$B277 -> 2813762.4 | Y5: ='P20'!$B277 -> 3324607.3 | Z5: ='P21'!B277 -> 3412631.1 | AA5: ='P22'!B277 -> 3502786.3 | AB5: ='P23'!B277 -> 5875234.7 | AC5: ='P24'!B277 -> 4898099.3 | AD5: ='P25'!B277 -> 4526014.8 | AE5: ='P26'!B277 -> 4651543.6 | AF5: ='P27'!B277 -> 3269427.8 | AG5: ='P28'!B277 -> 1546151.7 | AH5: ='P29'!B277 -> -2452371.4 | AI5: ='P30'!B277 -> -350869.11 | AJ5: ='P31'!B277 -> 1010287.2 | AK5: ='P32'!$B277 -> 1121033 | AL5: ='P33'!$B277 -> -978698.69 | AM5: ='P34'!$B277 -> 1297904.4 | AN5: ='P35'!$B277 -> 696793.33 | AO5: ='P36'!$B277 -> 1099085.1 | AP5: ='P37'!$B277 -> 2773467.4 | AQ5: ='P38'!$B277 -> 3112031.7 | AR5: ='P39'!$B277 -> 3352244.6 | AS5: ='P40'!$B277 -> 3449804.6 | AT5: ='P41'!$B277 -> 3810124 | AU5: ='P42'!$B277 -> 3952447.2 | AV5: ='P43'!$B277 -> 4306082.8 | AW5: ='P44'!$B277 -> 4664647 | AX5: ='P45'!$B277 -> 4429175.9 | AY5: ='P46'!$B277 -> 4452192.9 | AZ5: ='P47'!$B277 -> 5232546.9 | BA5: ='P48'!$B277 -> 5061030.7 | BB5: ='P49'!$B277 -> 4292259.1 | BC5: ='P50'!$B277 -> 3793014.5 | BD5: ='P51'!$B277 -> 3155181 | BE5: ='P52'!$B277 -> 4761233.1 | BF5: ='P53'!$B277 -> 3437087.1 | BG5: ='P54'!$B277 -> 3728824.1 | BH5: ='P55'!$B277 -> 3963170.5 | BI5: ='P56'!$B277 -> 4113013.3 | BJ5: ='P57'!$B277 -> 4353060.3 | BK5: ='P58'!$B277 -> 4365110.3 | BL5: ='P59'!$B277 -> 4365357.9 | BM5: ='P60'!$B277 -> 4337658.4 | BN5: ='P61'!$B277 -> 3708282.7 | BO5: ='P62'!$B277 -> 3551343.4 | BP5: ='P63'!$B277 -> 0 | BQ5: ='P64'!$B277 -> 0 | BR5: ='P65'!$B277 -> 0 | BS5: ='P66'!$B277 -> 0 | BT5: ='P67'!$B277 -> 0 | BU5: ='P68'!$B277 -> 0 | BV5: ='P69'!$B277 -> 0 | BW5: ='P70'!$B277 -> 0 | BX5: ='P71'!$B277 -> 0 | BY5: ='P72'!$B277 -> 0 | BZ5: ='P73'!$B277 -> 0 | CA5: ='P74'!$B277 -> 0 | CB5: ='P75'!$B277 -> 0
A6: Add back non-cash expenses | E6: Debt/Equity Ratio | F6: ='P1'!B278 -> 0.28523738 | G6: ='P2'!$B278 -> 0.25769477 | H6: ='P3'!$B278 -> 0.23912567 | I6: ='P4'!$B278 -> 0.30500633 | J6: ='P5'!$B278 -> 0.26965442 | K6: ='P6'!$B278 -> 0.29056062 | L6: ='P7'!$B278 -> 0.73072479 | M6: ='P8'!$B278 -> 0.7507871 | N6: ='P9'!$B278 -> 0.78594769 | O6: ='P10'!$B278 -> 0.79153046 | P6: ='P11'!$B278 -> 0.86317616 | Q6: ='P12'!$B278 -> 0.93671189 | R6: ='P13'!$B278 -> 0.89510392 | S6: ='P14'!$B278 -> 0.77940219 | T6: ='P15'!$B278 -> 0.76020079 | U6: ='P16'!$B278 -> 0.76436085 | V6: ='P17'!$B278 -> 0.753345 | W6: ='P18'!$B278 -> 0.71719797 | X6: ='P19'!$B278 -> 0.74822674 | Y6: ='P20'!$B278 -> 0.76714946 | Z6: ='P21'!B278 -> 0.78362297 | AA6: ='P22'!B278 -> 0.79867043 | AB6: ='P23'!B278 -> 0.74712746 | AC6: ='P24'!B278 -> 0.72633268 | AD6: ='P25'!B278 -> 0.71515716 | AE6: ='P26'!B278 -> 0.70324352 | AF6: ='P27'!B278 -> 0.72197109 | AG6: ='P28'!B278 -> 0.71312994 | AH6: ='P29'!B278 -> 0.77050169 | AI6: ='P30'!B278 -> 0.79969996 | AJ6: ='P31'!B278 -> 0.80226053 | AK6: ='P32'!B278 -> 0.80494791 | AL6: ='P33'!$B278 -> 1.5812271 | AM6: ='P34'!$B278 -> 1.5741336 | AN6: ='P35'!$B278 -> 1.6215352 | AO6: ='P36'!$B278 -> 1.6859546 | AP6: ='P37'!$B278 -> 1.6073071 | AQ6: ='P38'!$B278 -> 1.6630499 | AR6: ='P39'!$B278 -> 1.564016 | AS6: ='P40'!$B278 -> 1.6468 | AT6: ='P41'!$B278 -> 1.6013117 | AU6: ='P42'!$B278 -> 1.6175234 | AV6: ='P43'!$B278 -> 1.6095794 | AW6: ='P44'!$B278 -> 1.5823867 | AX6: ='P45'!$B278 -> 1.5312649 | AY6: ='P46'!$B278 -> 1.4866414 | AZ6: ='P47'!$B278 -> 1.4059626 | BA6: ='P48'!$B278 -> 1.1748519 | BB6: ='P49'!$B278 -> 1.2440895 | BC6: ='P50'!$B278 -> 1.2398398 | BD6: ='P51'!$B278 -> 1.2623033 | BE6: ='P52'!$B278 -> 1.4701597 | BF6: ='P53'!$B278 -> 1.5394597 | BG6: ='P54'!$B278 -> 1.5967007 | BH6: ='P55'!$B278 -> 1.6403514 | BI6: ='P56'!$B278 -> 1.862077 | BJ6: ='P57'!$B278 -> 1.744002 | BK6: ='P58'!$B278 -> 1.8055285 | BL6: ='P59'!$B278 -> 1.816945 | BM6: ='P60'!$B278 -> 1.882829 | BN6: ='P61'!$B278 -> 1.7090574 | BO6: ='P62'!$B278 -> 1.1179938 | BP6: ='P63'!$B278 -> 0 | BQ6: ='P64'!$B278 -> 0 | BR6: ='P65'!$B278 -> 0 | BS6: ='P66'!$B278 -> 0 | BT6: ='P67'!$B278 -> 0 | BU6: ='P68'!$B278 -> 0 | BV6: ='P69'!$B278 -> 0 | BW6: ='P70'!$B278 -> 0 | BX6: ='P71'!$B278 -> 0 | BY6: ='P72'!$B278 -> 0 | BZ6: ='P73'!$B278 -> 0 | CA6: ='P74'!$B278 -> 0 | CB6: ='P75'!$B278 -> 0
A7: Depreciation part of transportation expense | C7: =ACTIVE!B207 -> 170498 | E7: Debt /(Debt + Equity) | F7: ='P1'!B279 -> 0.22193362 | G7: ='P2'!$B279 -> 0.20489452 | H7: ='P3'!$B279 -> 0.19297935 | I7: ='P4'!$B279 -> 0.23372019 | J7: ='P5'!$B279 -> 0.2123841 | K7: ='P6'!$B279 -> 0.22514295 | L7: ='P7'!$B279 -> 0.42220739 | M7: ='P8'!$B279 -> 0.42882832 | N7: ='P9'!$B279 -> 0.44007319 | O7: ='P10'!$B279 -> 0.44181803 | P7: ='P11'!$B279 -> 0.4632821 | Q7: ='P12'!$B279 -> 0.48366094 | R7: ='P13'!$B279 -> 0.47232445 | S7: ='P14'!$B279 -> 0.43801351 | T7: ='P15'!$B279 -> 0.431883 | U7: ='P16'!$B279 -> 0.43322252 | V7: ='P17'!$B279 -> 0.42966159 | W7: ='P18'!$B279 -> 0.41765596 | X7: ='P19'!$B279 -> 0.42799182 | Y7: ='P20'!$B279 -> 0.43411691 | Z7: ='P21'!B279 -> 0.43934339 | AA7: ='P22'!B279 -> 0.44403378 | AB7: ='P23'!B279 -> 0.42763192 | AC7: ='P24'!B279 -> 0.42073738 | AD7: ='P25'!B279 -> 0.41696305 | AE7: ='P26'!B279 -> 0.41288489 | AF7: ='P27'!B279 -> 0.41927016 | AG7: ='P28'!B279 -> 0.41627312 | AH7: ='P29'!B279 -> 0.43518834 | AI7: ='P30'!B279 -> 0.44435182 | AJ7: ='P31'!B279 -> 0.44514126 | AK7: ='P32'!B279 -> 0.44596739 | AL7: ='P33'!$B279 -> 0.61258736 | AM7: ='P34'!$B279 -> 0.61151978 | AN7: ='P35'!$B279 -> 0.61854413 | AO7: ='P36'!$B279 -> 0.62769289 | AP7: ='P37'!$B279 -> 0.61646251 | AQ7: ='P38'!$B279 -> 0.6244907 | AR7: ='P39'!$B279 -> 0.60998684 | AS7: ='P40'!$B279 -> 0.62218528 | AT7: ='P41'!$B279 -> 0.61557856 | AU7: ='P42'!$B279 -> 0.61795949 | AV7: ='P43'!$B279 -> 0.61679648 | AW7: ='P44'!$B279 -> 0.61276132 | AX7: ='P45'!$B279 -> 0.6049406 | AY7: ='P46'!$B279 -> 0.59785115 | AZ7: ='P47'!$B279 -> 0.58436594 | BA7: ='P48'!$B279 -> 0.54019857 | BB7: ='P49'!$B279 -> 0.55438498 | BC7: ='P50'!$B279 -> 0.5535395 | BD7: ='P51'!$B279 -> 0.55797262 | BE7: ='P52'!$B279 -> 0.59516787 | BF7: ='P53'!$B279 -> 0.60621544 | BG7: ='P54'!$B279 -> 0.61489593 | BH7: ='P55'!$B279 -> 0.62126253 | BI7: ='P56'!$B279 -> 0.65060339 | BJ7: ='P57'!$B279 -> 0.63556878 | BK7: ='P58'!$B279 -> 0.64356092 | BL7: ='P59'!$B279 -> 0.64500549 | BM7: ='P60'!$B279 -> 0.65311852 | BN7: ='P61'!$B279 -> 0.63086792 | BO7: ='P62'!$B279 -> 0.52785509 | BP7: ='P63'!$B279 -> 0 | BQ7: ='P64'!$B279 -> 0 | BR7: ='P65'!$B279 -> 0 | BS7: ='P66'!$B279 -> 0 | BT7: ='P67'!$B279 -> 0 | BU7: ='P68'!$B279 -> 0 | BV7: ='P69'!$B279 -> 0 | BW7: ='P70'!$B279 -> 0 | BX7: ='P71'!$B279 -> 0 | BY7: ='P72'!$B279 -> 0 | BZ7: ='P73'!$B279 -> 0 | CA7: ='P74'!$B279 -> 0 | CB7: ='P75'!$B279 -> 0
A8: Interest expense | C8: =ACTIVE!B222 -> 815763 | E8: Equity/(Debt+Equity) | F8: ='P1'!B280 -> 0.77806638 | G8: ='P2'!$B280 -> 0.79510548 | H8: ='P3'!$B280 -> 0.80702065 | I8: ='P4'!$B280 -> 0.76627981 | J8: ='P5'!$B280 -> 0.7876159 | K8: ='P6'!$B280 -> 0.77485705 | L8: ='P7'!$B280 -> 0.57779261 | M8: ='P8'!$B280 -> 0.57117168 | N8: ='P9'!$B280 -> 0.55992681 | O8: ='P10'!$B280 -> 0.55818197 | P8: ='P11'!$B280 -> 0.5367179 | Q8: ='P12'!$B280 -> 0.51633906 | R8: ='P13'!$B280 -> 0.52767555 | S8: ='P14'!$B280 -> 0.56198649 | T8: ='P15'!$B280 -> 0.568117 | U8: ='P16'!$B280 -> 0.56677748 | V8: ='P17'!$B280 -> 0.57033841 | W8: ='P18'!$B280 -> 0.58234404 | X8: ='P19'!$B280 -> 0.57200818 | Y8: ='P20'!$B280 -> 0.56588309 | Z8: ='P21'!B280 -> 0.56065661 | AA8: ='P22'!B280 -> 0.55596622 | AB8: ='P23'!B280 -> 0.57236808 | AC8: ='P24'!B280 -> 0.57926262 | AD8: ='P25'!B280 -> 0.58303695 | AE8: ='P26'!B280 -> 0.58711511 | AF8: ='P27'!B280 -> 0.58072984 | AG8: ='P28'!B280 -> 0.58372688 | AH8: ='P29'!B280 -> 0.56481166 | AI8: ='P30'!B280 -> 0.55564818 | AJ8: ='P31'!B280 -> 0.55485874 | AK8: ='P32'!B280 -> 0.55403261 | AL8: ='P33'!$B280 -> 0.38741264 | AM8: ='P34'!$B280 -> 0.38848022 | AN8: ='P35'!$B280 -> 0.38145587 | AO8: ='P36'!$B280 -> 0.37230711 | AP8: ='P37'!$B280 -> 0.38353749 | AQ8: ='P38'!$B280 -> 0.3755093 | AR8: ='P39'!$B280 -> 0.39001316 | AS8: ='P40'!$B280 -> 0.37781472 | AT8: ='P41'!$B280 -> 0.38442144 | AU8: ='P42'!$B280 -> 0.38204051 | AV8: ='P43'!$B280 -> 0.38320352 | AW8: ='P44'!$B280 -> 0.38723868 | AX8: ='P45'!$B280 -> 0.3950594 | AY8: ='P46'!$B280 -> 0.40214885 | AZ8: ='P47'!$B280 -> 0.41563406 | BA8: ='P48'!$B280 -> 0.45980143 | BB8: ='P49'!$B280 -> 0.44561502 | BC8: ='P50'!$B280 -> 0.4464605 | BD8: ='P51'!$B280 -> 0.44202738 | BE8: ='P52'!$B280 -> 0.40483213 | BF8: ='P53'!$B280 -> 0.39378456 | BG8: ='P54'!$B280 -> 0.38510407 | BH8: ='P55'!$B280 -> 0.37873747 | BI8: ='P56'!$B280 -> 0.34939661 | BJ8: ='P57'!$B280 -> 0.36443122 | BK8: ='P58'!$B280 -> 0.35643908 | BL8: ='P59'!$B280 -> 0.35499451 | BM8: ='P60'!$B280 -> 0.34688148 | BN8: ='P61'!$B280 -> 0.36913208 | BO8: ='P62'!$B280 -> 0.47214491 | BP8: ='P63'!$B280 -> 0 | BQ8: ='P64'!$B280 -> 0 | BR8: ='P65'!$B280 -> 0 | BS8: ='P66'!$B280 -> 0 | BT8: ='P67'!$B280 -> 0 | BU8: ='P68'!$B280 -> 0 | BV8: ='P69'!$B280 -> 0 | BW8: ='P70'!$B280 -> 0 | BX8: ='P71'!$B280 -> 0 | BY8: ='P72'!$B280 -> 0 | BZ8: ='P73'!$B280 -> 0 | CA8: ='P74'!$B280 -> 0 | CB8: ='P75'!$B280 -> 0
A9: Factory Depreciation | C9: =ACTIVE!B223 -> 190596 | E9: Expected Return on Debt | F9: ='P1'!B281 -> 0.05016 | G9: ='P2'!$B281 -> 0.05016 | H9: ='P3'!$B281 -> 0.05016 | I9: ='P4'!$B281 -> 0.05016 | J9: ='P5'!$B281 -> 0.05016 | K9: ='P6'!$B281 -> 0.05016 | L9: ='P7'!$B281 -> 0.060192 | M9: ='P8'!$B281 -> 0.060192 | N9: ='P9'!$B281 -> 0.060192 | O9: ='P10'!$B281 -> 0.060192 | P9: ='P11'!$B281 -> 0.065208 | Q9: ='P12'!$B281 -> 0.065208 | R9: ='P13'!$B281 -> 0.065208 | S9: ='P14'!$B281 -> 0.060192 | T9: ='P15'!$B281 -> 0.060192 | U9: ='P16'!$B281 -> 0.060192 | V9: ='P17'!$B281 -> 0.060192 | W9: ='P18'!$B281 -> 0.060192 | X9: ='P19'!$B281 -> 0.060192 | Y9: ='P20'!$B281 -> 0.060192 | Z9: ='P21'!B281 -> 0.060192 | AA9: ='P22'!B281 -> 0.060192 | AB9: ='P23'!B281 -> 0.060192 | AC9: ='P24'!B281 -> 0.060192 | AD9: ='P25'!B281 -> 0.060192 | AE9: ='P26'!B281 -> 0.060192 | AF9: ='P27'!B281 -> 0.060192 | AG9: ='P28'!B281 -> 0.060192 | AH9: ='P29'!B281 -> 0.060192 | AI9: ='P30'!B281 -> 0.060192 | AJ9: ='P31'!B281 -> 0.065208 | AK9: ='P32'!B281 -> 0.065208 | AL9: ='P33'!$B281 -> 0.070224 | AM9: ='P34'!$B281 -> 0.070224 | AN9: ='P35'!$B281 -> 0.10032 | AO9: ='P36'!$B281 -> 0.10032 | AP9: ='P37'!$B281 -> 0.10032 | AQ9: ='P38'!$B281 -> 0.10032 | AR9: ='P39'!$B281 -> 0.070224 | AS9: ='P40'!$B281 -> 0.10032 | AT9: ='P41'!$B281 -> 0.10032 | AU9: ='P42'!$B281 -> 0.10032 | AV9: ='P43'!$B281 -> 0.10032 | AW9: ='P44'!$B281 -> 0.070224 | AX9: ='P45'!$B281 -> 0.070224 | AY9: ='P46'!$B281 -> 0.070224 | AZ9: ='P47'!$B281 -> 0.070224 | BA9: ='P48'!$B281 -> 0.065208 | BB9: ='P49'!$B281 -> 0.070224 | BC9: ='P50'!$B281 -> 0.070224 | BD9: ='P51'!$B281 -> 0.070224 | BE9: ='P52'!$B281 -> 0.070224 | BF9: ='P53'!$B281 -> 0.070224 | BG9: ='P54'!$B281 -> 0.070224 | BH9: ='P55'!$B281 -> 0.10032 | BI9: ='P56'!$B281 -> 0.10032 | BJ9: ='P57'!$B281 -> 0.10032 | BK9: ='P58'!$B281 -> 0.10032 | BL9: ='P59'!$B281 -> 0.10032 | BM9: ='P60'!$B281 -> 0.10032 | BN9: ='P61'!$B281 -> 0.10032 | BO9: ='P62'!$B281 -> 0.065208 | BP9: ='P63'!$B281 -> 0 | BQ9: ='P64'!$B281 -> 0 | BR9: ='P65'!$B281 -> 0 | BS9: ='P66'!$B281 -> 0 | BT9: ='P67'!$B281 -> 0 | BU9: ='P68'!$B281 -> 0 | BV9: ='P69'!$B281 -> 0 | BW9: ='P70'!$B281 -> 0 | BX9: ='P71'!$B281 -> 0 | BY9: ='P72'!$B281 -> 0 | BZ9: ='P73'!$B281 -> 0 | CA9: ='P74'!$B281 -> 0 | CB9: ='P75'!$B281 -> 0
A10: Plant Sale loss | C10: =ACTIVE!B224 -> 1083003.6 | E10: Expected Return on Equity | F10: ='P1'!B282 -> 0.10427856 | G10: ='P2'!$B282 -> 0.10386542 | H10: ='P3'!$B282 -> 0.10358689 | I10: ='P4'!$B282 -> 0.1045751 | J10: ='P5'!$B282 -> 0.10404482 | K10: ='P6'!$B282 -> 0.10435841 | L10: ='P7'!$B282 -> 0.11096087 | M10: ='P8'!$B282 -> 0.11126181 | N10: ='P9'!$B282 -> 0.11178922 | O10: ='P10'!$B282 -> 0.11187296 | P10: ='P11'!$B282 -> 0.11294764 | Q10: ='P12'!$B282 -> 0.11405068 | R10: ='P13'!$B282 -> 0.11342656 | S10: ='P14'!$B282 -> 0.11169103 | T10: ='P15'!$B282 -> 0.11140301 | U10: ='P16'!$B282 -> 0.11146541 | V10: ='P17'!$B282 -> 0.11130018 | W10: ='P18'!$B282 -> 0.11075797 | X10: ='P19'!$B282 -> 0.1112234 | Y10: ='P20'!$B282 -> 0.11150724 | Z10: ='P21'!B282 -> 0.11175434 | AA10: ='P22'!B282 -> 0.11198006 | AB10: ='P23'!B282 -> 0.11120691 | AC10: ='P24'!B282 -> 0.11089499 | AD10: ='P25'!B282 -> 0.11072736 | AE10: ='P26'!B282 -> 0.11054865 | AF10: ='P27'!B282 -> 0.11082957 | AG10: ='P28'!B282 -> 0.11069695 | AH10: ='P29'!B282 -> 0.11155753 | AI10: ='P30'!B282 -> 0.1119955 | AJ10: ='P31'!B282 -> 0.11203391 | AK10: ='P32'!B282 -> 0.11207422 | AL10: ='P33'!$B282 -> 0.12371841 | AM10: ='P34'!$B282 -> 0.123612 | AN10: ='P35'!$B282 -> 0.12432303 | AO10: ='P36'!$B282 -> 0.12528932 | AP10: ='P37'!$B282 -> 0.12410961 | AQ10: ='P38'!$B282 -> 0.12494575 | AR10: ='P39'!$B282 -> 0.12346024 | AS10: ='P40'!$B282 -> 0.124702 | AT10: ='P41'!$B282 -> 0.12401968 | AU10: ='P42'!$B282 -> 0.12426285 | AV10: ='P43'!$B282 -> 0.12414369 | AW10: ='P44'!$B282 -> 0.1237358 | AX10: ='P45'!$B282 -> 0.12296897 | AY10: ='P46'!$B282 -> 0.12229962 | AZ10: ='P47'!$B282 -> 0.12108944 | BA10: ='P48'!$B282 -> 0.11762278 | BB10: ='P49'!$B282 -> 0.11866134 | BC10: ='P50'!$B282 -> 0.1185976 | BD10: ='P51'!$B282 -> 0.11893455 | BE10: ='P52'!$B282 -> 0.12205239 | BF10: ='P53'!$B282 -> 0.12309189 | BG10: ='P54'!$B282 -> 0.12395051 | BH10: ='P55'!$B282 -> 0.12460527 | BI10: ='P56'!$B282 -> 0.12793116 | BJ10: ='P57'!$B282 -> 0.12616003 | BK10: ='P58'!$B282 -> 0.12708293 | BL10: ='P59'!$B282 -> 0.12725417 | BM10: ='P60'!$B282 -> 0.12824244 | BN10: ='P61'!$B282 -> 0.12563586 | BO10: ='P62'!$B282 -> 0.11676991 | BP10: ='P63'!$B282 -> 0 | BQ10: ='P64'!$B282 -> 0 | BR10: ='P65'!$B282 -> 0 | BS10: ='P66'!$B282 -> 0 | BT10: ='P67'!$B282 -> 0 | BU10: ='P68'!$B282 -> 0 | BV10: ='P69'!$B282 -> 0 | BW10: ='P70'!$B282 -> 0 | BX10: ='P71'!$B282 -> 0 | BY10: ='P72'!$B282 -> 0 | BZ10: ='P73'!$B282 -> 0 | CA10: ='P74'!$B282 -> 0 | CB10: ='P75'!$B282 -> 0
A11: Inventory writedowns | C11: =ACTIVE!B225 -> 0 | E11: Amount of debt | F11: ='P1'!B283 -> 7285276 | G11: ='P2'!$B283 -> 7423696 | H11: ='P3'!$B283 -> 7564746 | I11: ='P4'!$B283 -> 7708476 | J11: ='P5'!$B283 -> 7854937 | K11: ='P6'!$B283 -> 8004181 | L11: ='P7'!$B283 -> 15289260 | M11: ='P8'!$B283 -> 15637855 | N11: ='P9'!$B283 -> 15994398 | O11: ='P10'!$B283 -> 16359070 | P11: ='P11'!$B283 -> 16732057 | Q11: ='P12'!$B283 -> 17145339 | R11: ='P13'!$B283 -> 17568829 | S11: ='P14'!$B283 -> 18002779 | T11: ='P15'!$B283 -> 18413242 | U11: ='P16'!$B283 -> 18833064 | V11: ='P17'!$B283 -> 19262458 | W11: ='P18'!$B283 -> 19701642 | X11: ='P19'!$B283 -> 20150839 | Y11: ='P20'!$B283 -> 20610278 | Z11: ='P21'!B283 -> 21080192 | AA11: ='P22'!B283 -> 21560820 | AB11: ='P23'!B283 -> 22052407 | AC11: ='P24'!B283 -> 22555202 | AD11: ='P25'!B283 -> 23069461 | AE11: ='P26'!B283 -> 23595445 | AF11: ='P27'!B283 -> 24133421 | AG11: ='P28'!B283 -> 24683663 | AH11: ='P29'!B283 -> 25246451 | AI11: ='P30'!B283 -> 25822070 | AJ11: ='P31'!B283 -> 26410813 | AK11: ='P32'!B283 -> 27063160 | AL11: ='P33'!$B283 -> 27731620 | AM11: ='P34'!$B283 -> 28469281 | AN11: ='P35'!$B283 -> 29226564 | AO11: ='P36'!$B283 -> 30337173 | AP11: ='P37'!$B283 -> 31489986 | AQ11: ='P38'!$B283 -> 32686605 | AR11: ='P39'!$B283 -> 33928696 | AS11: ='P40'!$B283 -> 34831199 | AT11: ='P41'!$B283 -> 33040785 | AU11: ='P42'!$B283 -> 34296335 | AV11: ='P43'!$B283 -> 35599596 | AW11: ='P44'!$B283 -> 36952381 | AX11: ='P45'!$B283 -> 37935314 | AY11: ='P46'!$B283 -> 38944393 | AZ11: ='P47'!$B283 -> 39980314 | BA11: ='P48'!$B283 -> 35910790 | BB11: ='P49'!$B283 -> 36797787 | BC11: ='P50'!$B283 -> 37776608 | BD11: ='P51'!$B283 -> 38781466 | BE11: ='P52'!$B283 -> 39813053 | BF11: ='P53'!$B283 -> 40872080 | BG11: ='P54'!$B283 -> 41959277 | BH11: ='P55'!$B283 -> 43075394 | BI11: ='P56'!$B283 -> 31944859 | BJ11: ='P57'!$B283 -> 30044764 | BK11: ='P58'!$B283 -> 31186465 | BL11: ='P59'!$B283 -> 29205651 | BM11: ='P60'!$B283 -> 30315466 | BN11: ='P61'!$B283 -> 31467454 | BO11: ='P62'!$B283 -> 22283217 | BP11: ='P63'!$B283 -> 0 | BQ11: ='P64'!$B283 -> 0 | BR11: ='P65'!$B283 -> 0 | BS11: ='P66'!$B283 -> 0 | BT11: ='P67'!$B283 -> 0 | BU11: ='P68'!$B283 -> 0 | BV11: ='P69'!$B283 -> 0 | BW11: ='P70'!$B283 -> 0 | BX11: ='P71'!$B283 -> 0 | BY11: ='P72'!$B283 -> 0 | BZ11: ='P73'!$B283 -> 0 | CA11: ='P74'!$B283 -> 0 | CB11: ='P75'!$B283 -> 0
A12: Change in Accounts Receivables | C12: =-1*(ACTIVE!B53-'Active -1'!B53) -> 2452927 | E12: Amount of Equity | F12: ='P1'!B284 -> 25541098 | G12: ='P2'!$B284 -> 28808097 | H12: ='P3'!$B284 -> 31635022 | I12: ='P4'!$B284 -> 25273167 | J12: ='P5'!$B284 -> 29129644 | K12: ='P6'!$B284 -> 27547370 | L12: ='P7'!$B284 -> 20923418 | M12: ='P8'!$B284 -> 20828614 | N12: ='P9'!$B284 -> 20350461 | O12: ='P10'!$B284 -> 20667644 | P12: ='P11'!$B284 -> 19384290 | Q12: ='P12'!$B284 -> 18303749 | R12: ='P13'!$B284 -> 19627697 | S12: ='P14'!$B284 -> 23098189 | T12: ='P15'!$B284 -> 24221551 | U12: ='P16'!$B284 -> 24638970 | V12: ='P17'!$B284 -> 25569238 | W12: ='P18'!$B284 -> 27470298 | X12: ='P19'!$B284 -> 26931461 | Y12: ='P20'!$B284 -> 26866053 | Z12: ='P21'!B284 -> 26900937 | AA12: ='P22'!B284 -> 26995891 | AB12: ='P23'!B284 -> 29516258 | AC12: ='P24'!B284 -> 31053541 | AD12: ='P25'!B284 -> 32257890 | AE12: ='P26'!B284 -> 33552311 | AF12: ='P27'!B284 -> 33427130 | AG12: ='P28'!B284 -> 34613135 | AH12: ='P29'!B284 -> 32766250 | AI12: ='P30'!B284 -> 32289698 | AJ12: ='P31'!B284 -> 32920494 | AK12: ='P32'!B284 -> 33621008 | AL12: ='P33'!$B284 -> 17538037 | AM12: ='P34'!$B284 -> 18085683 | AN12: ='P35'!$B284 -> 18024008 | AO12: ='P36'!$B284 -> 17994063 | AP12: ='P37'!$B284 -> 19591767 | AQ12: ='P38'!$B284 -> 19654614 | AR12: ='P39'!$B284 -> 21693317 | AS12: ='P40'!$B284 -> 21150838 | AT12: ='P41'!$B284 -> 20633575 | AU12: ='P42'!$B284 -> 21202991 | AV12: ='P43'!$B284 -> 22117329 | AW12: ='P44'!$B284 -> 23352308 | AX12: ='P45'!$B284 -> 24773842 | AY12: ='P46'!$B284 -> 26196225 | AZ12: ='P47'!$B284 -> 28436258 | BA12: ='P48'!$B284 -> 30566228 | BB12: ='P49'!$B284 -> 29578085 | BC12: ='P50'!$B284 -> 30468943 | BD12: ='P51'!$B284 -> 30722780 | BE12: ='P52'!$B284 -> 27080768 | BF12: ='P53'!$B284 -> 26549627 | BG12: ='P54'!$B284 -> 26278736 | BH12: ='P55'!$B284 -> 26259858 | BI12: ='P56'!$B284 -> 17155498 | BJ12: ='P57'!$B284 -> 17227482 | BK12: ='P58'!$B284 -> 17272763 | BL12: ='P59'!$B284 -> 16074043 | BM12: ='P60'!$B284 -> 16101019 | BN12: ='P61'!$B284 -> 18412169 | BO12: ='P62'!$B284 -> 19931432 | BP12: ='P63'!$B284 -> 0 | BQ12: ='P64'!$B284 -> 0 | BR12: ='P65'!$B284 -> 0 | BS12: ='P66'!$B284 -> 0 | BT12: ='P67'!$B284 -> 0 | BU12: ='P68'!$B284 -> 0 | BV12: ='P69'!$B284 -> 0 | BW12: ='P70'!$B284 -> 0 | BX12: ='P71'!$B284 -> 0 | BY12: ='P72'!$B284 -> 0 | BZ12: ='P73'!$B284 -> 0 | CA12: ='P74'!$B284 -> 0 | CB12: ='P75'!$B284 -> 0
A13: Changes in Inventory net of any writedowns | C13: =-1*(ACTIVE!B56-'Active -1'!B56+ACTIVE!B225) -> 2381529 | E13: Capital Charge | F13: ='P1'!B285 -> 757204.6 | G13: ='P2'!$B285 -> 841134.44 | H13: ='P3'!$B285 -> 914105.27 | I13: ='P4'!$B285 -> 757400.25 | J13: ='P5'!$B285 -> 856198.01 | K13: ='P6'!$B285 -> 819072.36 | L13: ='P7'!$B285 -> 810492.95 | M13: ='P8'!$B285 -> 814675.76 | N13: ='P9'!$B285 -> 809424.22 | O13: ='P10'!$B285 -> 824208.9 | P13: ='P11'!$B285 -> 820118.46 | Q13: ='P12'!$B285 -> 801392.05 | R13: ='P13'!$B285 -> 842982.59 | S13: ='P14'!$B285 -> 915870.96 | T13: ='P15'!$B285 -> 951670.89 | U13: ='P16'!$B285 -> 969998.19 | V13: ='P17'!$B285 -> 1001326.6 | W13: ='P18'!$B285 -> 1057108.9 | X13: ='P19'!$B285 -> 1052082 | Y13: ='P20'!$B285 -> 1059083.3 | Z13: ='P21'!B285 -> 1068788.9 | AA13: ='P22'!B285 -> 1080197.6 | AB13: ='P23'!B285 -> 1152447.6 | AC13: ='P24'!B285 -> 1200331.2 | AD13: ='P25'!B285 -> 1240107 | AE13: ='P26'!B285 -> 1282354.9 | AF13: ='P27'!B285 -> 1289338.3 | AG13: ='P28'!B285 -> 1329331.9 | AH13: ='P29'!B285 -> 1293739 | AI13: ='P30'!B285 -> 1292645.7 | AJ13: ='P31'!B285 -> 1352602 | AK13: ='P32'!B285 -> 1383195.7 | AL13: ='P33'!$B285 -> 1029300.8 | AM13: ='P34'!$B285 -> 1058708.6 | AN13: ='P35'!$B285 -> 1293202 | AO13: ='P36'!$B285 -> 1324472.3 | AP13: ='P37'!$B285 -> 1397650.5 | AQ13: ='P38'!$B285 -> 1433720.2 | AR13: ='P39'!$B285 -> 1265217.7 | AS13: ='P40'!$B285 -> 1532954.4 | AT13: ='P41'!$B285 -> 1468405.2 | AU13: ='P42'!$B285 -> 1518838.1 | AV13: ='P43'!$B285 -> 1579269.6 | AW13: ='P44'!$B285 -> 1371115.1 | AX13: ='P45'!$B285 -> 1427595.8 | AY13: ='P46'!$B285 -> 1484654.9 | AZ13: ='P47'!$B285 -> 1562727 | BA13: ='P48'!$B285 -> 1484238.9 | BB13: ='P49'!$B285 -> 1523465.8 | BC13: ='P50'!$B285 -> 1566592 | BD13: ='P51'!$B285 -> 1594347.4 | BE13: ='P52'!$B285 -> 1525276.1 | BF13: ='P53'!$B285 -> 1534561.2 | BG13: ='P54'!$B285 -> 1550952.8 | BH13: ='P55'!$B285 -> 1898360.1 | BI13: ='P56'!$B285 -> 1349857.7 | BJ13: ='P57'!$B285 -> 1296877.6 | BK13: ='P58'!$B285 -> 1330924.9 | BL13: ='P59'!$B285 -> 1243850 | BM13: ='P60'!$B285 -> 1276520.4 | BN13: ='P61'!$B285 -> 1367510.9 | BO13: ='P62'!$B285 -> 945108.86 | BP13: ='P63'!$B285 -> 0 | BQ13: ='P64'!$B285 -> 0 | BR13: ='P65'!$B285 -> 0 | BS13: ='P66'!$B285 -> 0 | BT13: ='P67'!$B285 -> 0 | BU13: ='P68'!$B285 -> 0 | BV13: ='P69'!$B285 -> 0 | BW13: ='P70'!$B285 -> 0 | BX13: ='P71'!$B285 -> 0 | BY13: ='P72'!$B285 -> 0 | BZ13: ='P73'!$B285 -> 0 | CA13: ='P74'!$B285 -> 0 | CB13: ='P75'!$B285 -> 0
A14: Changes in Trade payables | C14: =ACTIVE!B62-'Active -1'!B62 -> -173068.01 | E14: Dividends | F14: ='P1'!B286 -> 200000 | G14: ='P2'!$B286 -> 0 | H14: ='P3'!$B286 -> 0 | I14: ='P4'!$B286 -> 10000000 | J14: ='P5'!$B286 -> 0 | K14: ='P6'!$B286 -> 3000000 | L14: ='P7'!$B286 -> 7000000 | M14: ='P8'!$B286 -> 3000000 | N14: ='P9'!$B286 -> 2000000 | O14: ='P10'!$B286 -> 2000000 | P14: ='P11'!$B286 -> 2000000 | Q14: ='P12'!$B286 -> 2000000 | R14: ='P13'!$B286 -> 2000000 | S14: ='P14'!$B286 -> 0 | T14: ='P15'!$B286 -> 0 | U14: ='P16'!$B286 -> 0 | V14: ='P17'!$B286 -> 0 | W14: ='P18'!$B286 -> 0 | X14: ='P19'!$B286 -> 3000000 | Y14: ='P20'!$B286 -> 3000000 | Z14: ='P21'!B286 -> 3000000 | AA14: ='P22'!B286 -> 3000000 | AB14: ='P23'!B286 -> 3000000 | AC14: ='P24'!B286 -> 3000000 | AD14: ='P25'!B286 -> 3000000 | AE14: ='P26'!B286 -> 3000000 | AF14: ='P27'!B286 -> 3000000 | AG14: ='P28'!B286 -> 0 | AH14: ='P29'!B286 -> 0 | AI14: ='P30'!B286 -> 0 | AJ14: ='P31'!B286 -> 0 | AK14: ='P32'!B286 -> 0 | AL14: ='P33'!$B286 -> 15000000 | AM14: ='P34'!$B286 -> 0 | AN14: ='P35'!$B286 -> 0 | AO14: ='P36'!$B286 -> 0 | AP14: ='P37'!$B286 -> 0 | AQ14: ='P38'!$B286 -> 0 | AR14: ='P39'!$B286 -> 0 | AS14: ='P40'!$B286 -> 3000000 | AT14: ='P41'!$B286 -> 3000000 | AU14: ='P42'!$B286 -> 2000000 | AV14: ='P43'!$B286 -> 2000000 | AW14: ='P44'!$B286 -> 2000000 | AX14: ='P45'!$B286 -> 2000000 | AY14: ='P46'!$B286 -> 2000000 | AZ14: ='P47'!$B286 -> 2000000 | BA14: ='P48'!$B286 -> 2000000 | BB14: ='P49'!$B286 -> 2000000 | BC14: ='P50'!$B286 -> 2000000 | BD14: ='P51'!$B286 -> 2000000 | BE14: ='P52'!$B286 -> 2000000 | BF14: ='P53'!$B286 -> 3000000 | BG14: ='P54'!$B286 -> 3000000 | BH14: ='P55'!$B286 -> 3000000 | BI14: ='P56'!$B286 -> 3000000 | BJ14: ='P57'!$B286 -> 3000000 | BK14: ='P58'!$B286 -> 3000000 | BL14: ='P59'!$B286 -> 3000000 | BM14: ='P60'!$B286 -> 3000000 | BN14: ='P61'!$B286 -> 0 | BO14: ='P62'!$B286 -> 0 | BP14: ='P63'!$B286 -> 0 | BQ14: ='P64'!$B286 -> 0 | BR14: ='P65'!$B286 -> 0 | BS14: ='P66'!$B286 -> 0 | BT14: ='P67'!$B286 -> 0 | BU14: ='P68'!$B286 -> 0 | BV14: ='P69'!$B286 -> 0 | BW14: ='P70'!$B286 -> 0 | BX14: ='P71'!$B286 -> 0 | BY14: ='P72'!$B286 -> 0 | BZ14: ='P73'!$B286 -> 0 | CA14: ='P74'!$B286 -> 0 | CB14: ='P75'!$B286 -> 0
A15: Changes in Taxes payable | C15: =ACTIVE!B63-'Active -1'!B63 -> -1967294 | E15: Stock purchases | F15: ='P1'!B287 -> 0 | G15: ='P2'!$B287 -> 0 | H15: ='P3'!$B287 -> 0 | I15: ='P4'!$B287 -> 0 | J15: ='P5'!$B287 -> 0 | K15: ='P6'!$B287 -> 0 | L15: ='P7'!$B287 -> 0 | M15: ='P8'!$B287 -> 0 | N15: ='P9'!$B287 -> 0 | O15: ='P10'!$B287 -> 0 | P15: ='P11'!$B287 -> 0 | Q15: ='P12'!$B287 -> 0 | R15: ='P13'!$B287 -> 0 | S15: ='P14'!$B287 -> 0 | T15: ='P15'!$B287 -> 0 | U15: ='P16'!$B287 -> 0 | V15: ='P17'!$B287 -> 0 | W15: ='P18'!$B287 -> 0 | X15: ='P19'!$B287 -> 0 | Y15: ='P20'!$B287 -> 0 | Z15: ='P21'!B287 -> 0 | AA15: ='P22'!B287 -> 0 | AB15: ='P23'!B287 -> 0 | AC15: ='P24'!B287 -> 0 | AD15: ='P25'!B287 -> 0 | AE15: ='P26'!B287 -> 0 | AF15: ='P27'!B287 -> 0 | AG15: ='P28'!B287 -> 0 | AH15: ='P29'!B287 -> 0 | AI15: ='P30'!B287 -> 0 | AJ15: ='P31'!B287 -> 0 | AK15: ='P32'!B287 -> 0 | AL15: ='P33'!$B287 -> 0 | AM15: ='P34'!$B287 -> 0 | AN15: ='P35'!$B287 -> 0 | AO15: ='P36'!$B287 -> 0 | AP15: ='P37'!$B287 -> 0 | AQ15: ='P38'!$B287 -> 0 | AR15: ='P39'!$B287 -> 0 | AS15: ='P40'!$B287 -> 0 | AT15: ='P41'!$B287 -> 0 | AU15: ='P42'!$B287 -> 0 | AV15: ='P43'!$B287 -> 0 | AW15: ='P44'!$B287 -> 0 | AX15: ='P45'!$B287 -> 0 | AY15: ='P46'!$B287 -> 0 | AZ15: ='P47'!$B287 -> 0 | BA15: ='P48'!$B287 -> 0 | BB15: ='P49'!$B287 -> 0 | BC15: ='P50'!$B287 -> 0 | BD15: ='P51'!$B287 -> 0 | BE15: ='P52'!$B287 -> 5500000 | BF15: ='P53'!$B287 -> 0 | BG15: ='P54'!$B287 -> 0 | BH15: ='P55'!$B287 -> 0 | BI15: ='P56'!$B287 -> 9000000 | BJ15: ='P57'!$B287 -> 0 | BK15: ='P58'!$B287 -> 0 | BL15: ='P59'!$B287 -> 1320000 | BM15: ='P60'!$B287 -> 0 | BN15: ='P61'!$B287 -> 0 | BO15: ='P62'!$B287 -> 0 | BP15: ='P63'!$B287 -> 0 | BQ15: ='P64'!$B287 -> 0 | BR15: ='P65'!$B287 -> 0 | BS15: ='P66'!$B287 -> 0 | BT15: ='P67'!$B287 -> 0 | BU15: ='P68'!$B287 -> 0 | BV15: ='P69'!$B287 -> 0 | BW15: ='P70'!$B287 -> 0 | BX15: ='P71'!$B287 -> 0 | BY15: ='P72'!$B287 -> 0 | BZ15: ='P73'!$B287 -> 0 | CA15: ='P74'!$B287 -> 0 | CB15: ='P75'!$B287 -> 0
E16: Stock Sales | F16: ='P1'!B288 -> 0 | G16: ='P2'!$B288 -> 0 | H16: ='P3'!$B288 -> 0 | I16: ='P4'!$B288 -> 0 | J16: ='P5'!$B288 -> 0 | K16: ='P6'!$B288 -> 0 | L16: ='P7'!$B288 -> 0 | M16: ='P8'!$B288 -> 0 | N16: ='P9'!$B288 -> 0 | O16: ='P10'!$B288 -> 0 | P16: ='P11'!$B288 -> 0 | Q16: ='P12'!$B288 -> 0 | R16: ='P13'!$B288 -> 0 | S16: ='P14'!$B288 -> 0 | T16: ='P15'!$B288 -> 0 | U16: ='P16'!$B288 -> 0 | V16: ='P17'!$B288 -> 0 | W16: ='P18'!$B288 -> 0 | X16: ='P19'!$B288 -> 0 | Y16: ='P20'!$B288 -> 0 | Z16: ='P21'!B288 -> 0 | AA16: ='P22'!B288 -> 0 | AB16: ='P23'!B288 -> 0 | AC16: ='P24'!B288 -> 0 | AD16: ='P25'!B288 -> 0 | AE16: ='P26'!B288 -> 0 | AF16: ='P27'!B288 -> 0 | AG16: ='P28'!B288 -> 0 | AH16: ='P29'!B288 -> 0 | AI16: ='P30'!B288 -> 0 | AJ16: ='P31'!B288 -> 0 | AK16: ='P32'!B288 -> 0 | AL16: ='P33'!$B288 -> 0 | AM16: ='P34'!$B288 -> 0 | AN16: ='P35'!$B288 -> 0 | AO16: ='P36'!$B288 -> 0 | AP16: ='P37'!$B288 -> 0 | AQ16: ='P38'!$B288 -> 0 | AR16: ='P39'!$B288 -> 0 | AS16: ='P40'!$B288 -> 0 | AT16: ='P41'!$B288 -> 0 | AU16: ='P42'!$B288 -> 0 | AV16: ='P43'!$B288 -> 0 | AW16: ='P44'!$B288 -> 0 | AX16: ='P45'!$B288 -> 0 | AY16: ='P46'!$B288 -> 0 | AZ16: ='P47'!$B288 -> 0 | BA16: ='P48'!$B288 -> 0 | BB16: ='P49'!$B288 -> 0 | BC16: ='P50'!$B288 -> 0 | BD16: ='P51'!$B288 -> 0 | BE16: ='P52'!$B288 -> 0 | BF16: ='P53'!$B288 -> 0 | BG16: ='P54'!$B288 -> 0 | BH16: ='P55'!$B288 -> 0 | BI16: ='P56'!$B288 -> 0 | BJ16: ='P57'!$B288 -> 0 | BK16: ='P58'!$B288 -> 0 | BL16: ='P59'!$B288 -> 0 | BM16: ='P60'!$B288 -> 0 | BN16: ='P61'!$B288 -> 0 | BO16: ='P62'!$B288 -> 0 | BP16: ='P63'!$B288 -> 0 | BQ16: ='P64'!$B288 -> 0 | BR16: ='P65'!$B288 -> 0 | BS16: ='P66'!$B288 -> 0 | BT16: ='P67'!$B288 -> 0 | BU16: ='P68'!$B288 -> 0 | BV16: ='P69'!$B288 -> 0 | BW16: ='P70'!$B288 -> 0 | BX16: ='P71'!$B288 -> 0 | BY16: ='P72'!$B288 -> 0 | BZ16: ='P73'!$B288 -> 0 | CA16: ='P74'!$B288 -> 0 | CB16: ='P75'!$B288 -> 0
A17: Net cash from operations | C17: =C5+SUM(C7:C11)+C12+C13+C14+C15 -> 6473217.4 | E17: Economic Profit | F17: ='P1'!B289 -> 3471632.7 | G17: ='P2'!$B289 -> 2543094.5 | H17: ='P3'!$B289 -> 1998582.8 | I17: ='P4'!$B289 -> 3120006.3 | J17: ='P5'!$B289 -> 3198710.5 | K17: ='P6'!$B289 -> 727895.29 | L17: ='P7'!$B289 -> -149090.49 | M17: ='P8'!$B289 -> 2470284.1 | N17: ='P9'!$B289 -> 929660.41 | O17: ='P10'!$B289 -> 1872839.2 | P17: ='P11'!$B289 -> 279895.38 | Q17: ='P12'!$B289 -> 546515.5 | R17: ='P13'!$B289 -> 2888072.3 | S17: ='P14'!$B289 -> 2879142.4 | T17: ='P15'!$B289 -> 431954.13 | U17: ='P16'!$B289 -> -268901.9 | V17: ='P17'!$B289 -> 269210.7 | W17: ='P18'!$B289 -> 1176424.9 | X17: ='P19'!$B289 -> 1761680.4 | Y17: ='P20'!$B289 -> 2265523.9 | Z17: ='P21'!B289 -> 2343842.2 | AA17: ='P22'!B289 -> 2422588.8 | AB17: ='P23'!B289 -> 4722787.1 | AC17: ='P24'!B289 -> 3697768.1 | AD17: ='P25'!B289 -> 3285907.8 | AE17: ='P26'!B289 -> 3369188.6 | AF17: ='P27'!B289 -> 1980089.5 | AG17: ='P28'!B289 -> 216819.86 | AH17: ='P29'!B289 -> -3746110.4 | AI17: ='P30'!B289 -> -1643514.8 | AJ17: ='P31'!B289 -> -342314.8 | AK17: ='P32'!B289 -> -262162.7 | AL17: ='P33'!$B289 -> -2007999.5 | AM17: ='P34'!$B289 -> 239195.79 | AN17: ='P35'!$B289 -> -596408.7 | AO17: ='P36'!$B289 -> -225387.16 | AP17: ='P37'!$B289 -> 1375816.9 | AQ17: ='P38'!$B289 -> 1678311.5 | AR17: ='P39'!$B289 -> 2087026.9 | AS17: ='P40'!$B289 -> 1916850.2 | AT17: ='P41'!$B289 -> 2341718.8 | AU17: ='P42'!$B289 -> 2433609.1 | AV17: ='P43'!$B289 -> 2726813.2 | AW17: ='P44'!$B289 -> 3293531.9 | AX17: ='P45'!$B289 -> 3001580.1 | AY17: ='P46'!$B289 -> 2967538.1 | AZ17: ='P47'!$B289 -> 3669819.9 | BA17: ='P48'!$B289 -> 3576791.9 | BB17: ='P49'!$B289 -> 2768793.4 | BC17: ='P50'!$B289 -> 2226422.6 | BD17: ='P51'!$B289 -> 1560833.6 | BE17: ='P52'!$B289 -> 3235957 | BF17: ='P53'!$B289 -> 1902525.9 | BG17: ='P54'!$B289 -> 2177871.4 | BH17: ='P55'!$B289 -> 2064810.5 | BI17: ='P56'!$B289 -> 2763155.6 | BJ17: ='P57'!$B289 -> 3056182.7 | BK17: ='P58'!$B289 -> 3034185.4 | BL17: ='P59'!$B289 -> 3121508 | BM17: ='P60'!$B289 -> 3061138 | BN17: ='P61'!$B289 -> 2340771.8 | BO17: ='P62'!$B289 -> 2606234.6 | BP17: ='P63'!$B289 -> 0 | BQ17: ='P64'!$B289 -> 0 | BR17: ='P65'!$B289 -> 0 | BS17: ='P66'!$B289 -> 0 | BT17: ='P67'!$B289 -> 0 | BU17: ='P68'!$B289 -> 0 | BV17: ='P69'!$B289 -> 0 | BW17: ='P70'!$B289 -> 0 | BX17: ='P71'!$B289 -> 0 | BY17: ='P72'!$B289 -> 0 | BZ17: ='P73'!$B289 -> 0 | CA17: ='P74'!$B289 -> 0 | CB17: ='P75'!$B289 -> 0
A18: (Note: Changes in assets are subtracted while changes in liabilities are added) | E18: WACC | F18: ='P1'!B290 -> 0.092267833 | G18: ='P2'!$B290 -> 0.092861475 | H18: ='P3'!$B290 -> 0.093276599 | I18: ='P4'!$B290 -> 0.091857188 | J18: ='P5'!$B290 -> 0.092600538 | K18: ='P6'!$B290 -> 0.09215602 | L18: ='P7'!$B290 -> 0.089525879 | M18: ='P8'!$B290 -> 0.089361627 | N18: ='P9'!$B290 -> 0.089082664 | O18: ='P10'!$B290 -> 0.089039378 | P18: ='P11'!$B290 -> 0.090830721 | Q18: ='P12'!$B290 -> 0.090427383 | R18: ='P13'!$B290 -> 0.090651754 | S18: ='P14'!$B290 -> 0.089133761 | T18: ='P15'!$B290 -> 0.089285847 | U18: ='P16'!$B290 -> 0.089252616 | V18: ='P17'!$B290 -> 0.089340955 | W18: ='P18'!$B290 -> 0.089638791 | X18: ='P19'!$B290 -> 0.089382379 | Y18: ='P20'!$B290 -> 0.089230428 | Z18: ='P21'!B290 -> 0.089100769 | AA18: ='P22'!B290 -> 0.08898441 | AB18: ='P23'!B290 -> 0.089391307 | AC18: ='P24'!B290 -> 0.089562347 | AD18: ='P25'!B290 -> 0.089655981 | AE18: ='P26'!B290 -> 0.089757152 | AF18: ='P27'!B290 -> 0.089598746 | AG18: ='P28'!B290 -> 0.089673097 | AH18: ='P29'!B290 -> 0.089203848 | AI18: ='P30'!B290 -> 0.08897652 | AJ18: ='P31'!B290 -> 0.091189764 | AK18: ='P32'!B290 -> 0.091173413 | AL18: ='P33'!$B290 -> 0.090948409 | AM18: ='P34'!$B290 -> 0.090964184 | AN18: ='P35'!$B290 -> 0.1094761 | AO18: ='P36'!$B290 -> 0.10961626 | AP18: ='P37'!$B290 -> 0.10944421 | AQ18: ='P38'!$B290 -> 0.1095672 | AR18: ='P39'!$B290 -> 0.090986834 | AS18: ='P40'!$B290 -> 0.10953188 | AT18: ='P41'!$B290 -> 0.10943066 | AU18: ='P42'!$B290 -> 0.10946714 | AV18: ='P43'!$B290 -> 0.10944932 | AW18: ='P44'!$B290 -> 0.090945839 | AX18: ='P45'!$B290 -> 0.091061398 | AY18: ='P46'!$B290 -> 0.091166151 | AZ18: ='P47'!$B290 -> 0.091365409 | BA18: ='P48'!$B290 -> 0.08930839 | BB18: ='P49'!$B290 -> 0.091808407 | BC18: ='P50'!$B290 -> 0.0918209 | BD18: ='P51'!$B290 -> 0.091755397 | BE18: ='P52'!$B290 -> 0.0912058 | BF18: ='P53'!$B290 -> 0.091042561 | BG18: ='P54'!$B290 -> 0.090914298 | BH18: ='P55'!$B290 -> 0.10951774 | BI18: ='P56'!$B290 -> 0.10996724 | BJ18: ='P57'!$B290 -> 0.10973691 | BK18: ='P58'!$B290 -> 0.10985935 | BL18: ='P59'!$B290 -> 0.10988148 | BM18: ='P60'!$B290 -> 0.11000578 | BN18: ='P61'!$B290 -> 0.1096649 | BO18: ='P62'!$B290 -> 0.089552692 | BP18: ='P63'!$B290 -> 0 | BQ18: ='P64'!$B290 -> 0 | BR18: ='P65'!$B290 -> 0 | BS18: ='P66'!$B290 -> 0 | BT18: ='P67'!$B290 -> 0 | BU18: ='P68'!$B290 -> 0 | BV18: ='P69'!$B290 -> 0 | BW18: ='P70'!$B290 -> 0 | BX18: ='P71'!$B290 -> 0 | BY18: ='P72'!$B290 -> 0 | BZ18: ='P73'!$B290 -> 0 | CA18: ='P74'!$B290 -> 0 | CB18: ='P75'!$B290 -> 0
E19: Return on Invested Capital | F19: ='P1'!B291 -> 0.51529752 | G19: ='P2'!$B291 -> 0.37361981 | H19: ='P3'!$B291 -> 0.29721483 | I19: ='P4'!$B291 -> 0.47025026 | J19: ='P5'!$B291 -> 0.43855125 | K19: ='P6'!$B291 -> 0.17405346 | L19: ='P7'!$B291 -> 0.073057559 | M19: ='P8'!$B291 -> 0.36032662 | N19: ='P9'!$B291 -> 0.19139814 | O19: ='P10'!$B291 -> 0.2913624 | P19: ='P11'!$B291 -> 0.12183002 | Q19: ='P12'!$B291 -> 0.15209503 | R19: ='P13'!$B291 -> 0.40122616 | S19: ='P14'!$B291 -> 0.36933567 | T19: ='P15'!$B291 -> 0.12981182 | U19: ='P16'!$B291 -> 0.064510097 | V19: ='P17'!$B291 -> 0.11336063 | W19: ='P18'!$B291 -> 0.18939512 | X19: ='P19'!$B291 -> 0.23905055 | Y19: ='P20'!$B291 -> 0.2801065 | Z19: ='P21'!B291 -> 0.28449777 | AA19: ='P22'!B291 -> 0.28855219 | AB19: ='P23'!B291 -> 0.4557213 | AC19: ='P24'!B291 -> 0.36547018 | AD19: ='P25'!B291 -> 0.32721717 | AE19: ='P26'!B291 -> 0.32558014 | AF19: ='P27'!B291 -> 0.2271992 | AG19: ='P28'!B291 -> 0.10429917 | AH19: ='P29'!B291 -> -0.16909203 | AI19: ='P30'!B291 -> -0.024151329 | AJ19: ='P31'!B291 -> 0.068111574 | AK19: ='P32'!B291 -> 0.073892946 | AL19: ='P33'!$B291 -> -0.086477234 | AM19: ='P34'!$B291 -> 0.11151587 | AN19: ='P35'!$B291 -> 0.058987082 | AO19: ='P36'!$B291 -> 0.090962715 | AP19: ='P37'!$B291 -> 0.21717872 | AQ19: ='P38'!$B291 -> 0.23782645 | AR19: ='P39'!$B291 -> 0.24107323 | AS19: ='P40'!$B291 -> 0.24649369 | AT19: ='P41'!$B291 -> 0.2839437 | AU19: ='P42'!$B291 -> 0.28486452 | AV19: ='P43'!$B291 -> 0.29842773 | AW19: ='P44'!$B291 -> 0.30940526 | AX19: ='P45'!$B291 -> 0.2825218 | AY19: ='P46'!$B291 -> 0.27338967 | AZ19: ='P47'!$B291 -> 0.30592278 | BA19: ='P48'!$B291 -> 0.30452814 | BB19: ='P49'!$B291 -> 0.25866382 | BC19: ='P50'!$B291 -> 0.22231571 | BD19: ='P51'!$B291 -> 0.18158206 | BE19: ='P52'!$B291 -> 0.28470391 | BF19: ='P53'!$B291 -> 0.20391576 | BG19: ='P54'!$B291 -> 0.21857753 | BH19: ='P55'!$B291 -> 0.22863813 | BI19: ='P56'!$B291 -> 0.33506993 | BJ19: ='P57'!$B291 -> 0.36833961 | BK19: ='P58'!$B291 -> 0.360312 | BL19: ='P59'!$B291 -> 0.38563494 | BM19: ='P60'!$B291 -> 0.37380326 | BN19: ='P61'!$B291 -> 0.29737857 | BO19: ='P62'!$B291 -> 0.33650342 | BP19: ='P63'!$B291 -> 0 | BQ19: ='P64'!$B291 -> 0 | BR19: ='P65'!$B291 -> 0 | BS19: ='P66'!$B291 -> 0 | BT19: ='P67'!$B291 -> 0 | BU19: ='P68'!$B291 -> 0 | BV19: ='P69'!$B291 -> 0 | BW19: ='P70'!$B291 -> 0 | BX19: ='P71'!$B291 -> 0 | BY19: ='P72'!$B291 -> 0 | BZ19: ='P73'!$B291 -> 0 | CA19: ='P74'!$B291 -> 0 | CB19: ='P75'!$B291 -> 0
A20: CASH FLOW FROM INVESTING ACTIVITIES
A22: Cash Flow From Purchases of Shipping Containers | C22: =(ACTIVE!B57-'Active -1'!B57+ACTIVE!B207)*-1 -> 1
A23: Net Cash Flow From Changes In Plant and Equipment | C23: =(ACTIVE!B60-'Active -1'!B60+C10+C9)*-1 -> -3170939.6
A25: Net cash flow from investing activities | C25: =SUM(C22:C23) -> -3170938.6
A28: CASH FLOW FROM FINANCING ACTIVITIES
A30: Debt Payments (negative), or New Borrowing (positive) | C30: =(ACTIVE!B64-'Active -1'!B64)-ACTIVE!B222 -> -10000000
A31: Commons Stock Purchases(negative) or Sales (positive) | C31: =ACTIVE!B66-'Active -1'!B66-ACTIVE!B70+ACTIVE!B68 -> 0
A33: Dividend payment | C33: =ACTIVE!B68*-1 -> 0
A35: Net Cash from Financing Activities | C35: =SUM(C30:C33) -> -10000000
A37: NET CHANGE IN CASH | C37: =C35+C25+C17 -> -6697721.2
A38: BEGINNING CASH BALANCE | C38: ='Active -1'!B52 -> 23756031
A39: ENDING CASH BALANCE | C39: =ACTIVE!B52 -> 17058310
A40: Cross check | C40: =C38+C37-C39 -> 0
F100: Period 1 | G100: Period 2 | H100: Period 3 | I100: Period 4 | J100: Period 5 | K100: Period 6 | L100: Period 7 | M100: Period 8 | N100: Period 9 | O100: Period 10 | P100: Period 11 | Q100: Period 12 | R100: Period 13 | S100: Period 14 | T100: Period 15 | U100: Period 16 | V100: Period 17 | W100: Period 18 | X100: Period 19 | Y100: Period 20 | Z100: Period 21 | AA100: Period 22 | AB100: Period 23 | AC100: Period 24 | AD100: Period 25 | AE100: Period 26 | AF100: Period 27 | AG100: Period 28 | AH100: Period 29 | AI100: Period 30 | AJ100: Period 31 | AK100: Period 32 | AL100: Period 33 | AM100: Period 34 | AN100: Period 35 | AO100: Period 36 | AP100: Period 37 | AQ100: Period 38 | AR100: Period 39 | AS100: Period 40 | AT100: Period 41 | AU100: Period 42 | AV100: Period 43 | AW100: Period 44 | AX100: Period 45 | AY100: Period 46 | AZ100: Period 47 | BA100: Period 48 | BB100: Period 49 | BC100: Period 50 | BD100: Period 51 | BE100: Period 52 | BF100: Period 53 | BG100: Period 54 | BH100: Period 55 | BI100: Period 56 | BJ100: Period 57 | BK100: Period 58 | BL100: Period 59 | BM100: Period 60 | BN100: Period 61 | BO100: Period 62 | BP100: Period 63 | BQ100: Period 64 | BR100: Period 65 | BS100: Period 66 | BT100: Period 67 | BU100: Period 68 | BV100: Period 69 | BW100: Period 70 | BX100: Period 71 | BY100: Period 72 | BZ100: Period 73 | CA100: Period 74 | CB100: Period 75
E101: Assets to DO NOT produce cash flow | F101: =SUM('P1'!$B52:$B55) -> 30722642 | G101: =SUM('P2'!$B52:$B55) -> 32303673 | H101: =SUM('P3'!$B52:$B55) -> 36062922 | I101: =SUM('P4'!$B52:$B55) -> 29619088 | J101: =SUM('P5'!$B52:$B55) -> 34857904 | K101: =SUM('P6'!$B52:$B55) -> 29133783 | L101: =SUM('P7'!$B52:$B55) -> 31121466 | M101: =SUM('P8'!$B52:$B55) -> 30638275 | N101: =SUM('P9'!$B52:$B55) -> 32440200 | O101: =SUM('P10'!$B52:$B55) -> 32579972 | P101: =SUM('P11'!$B52:$B55) -> 31528807 | Q101: =SUM('P12'!$B52:$B55) -> 30355773 | R101: =SUM('P13'!$B52:$B55) -> 33919807 | S101: =SUM('P14'!$B52:$B55) -> 36785552 | T101: =SUM('P15'!$B52:$B55) -> 39485985 | U101: =SUM('P16'!$B52:$B55) -> 35867336 | V101: =SUM('P17'!$B52:$B55) -> 39600283 | W101: =SUM('P18'!$B52:$B55) -> 42903851 | X101: =SUM('P19'!$B52:$B55) -> 43735934 | Y101: =SUM('P20'!$B52:$B55) -> 43189719 | Z101: =SUM('P21'!B52:B55) -> 45642895 | AA101: =SUM('P22'!B52:B55) -> 44661767 | AB101: =SUM('P23'!B52:B55) -> 50477144 | AC101: =SUM('P24'!B52:B55) -> 49774638 | AD101: =SUM('P25'!B52:B55) -> 53953033 | AE101: =SUM('P26'!B52:B55) -> 52593767 | AF101: =SUM('P27'!B52:B55) -> 54479286 | AG101: =SUM('P28'!B52:B55) -> 53257684 | AH101: =SUM('P29'!B52:B55) -> 48757300 | AI101: =SUM('P30'!B52:B55) -> 50701225 | AJ101: =SUM('P31'!B52:B55) -> 52324497 | AK101: =SUM('P32'!$B52:$B55) -> 54137863 | AL101: =SUM('P33'!$B52:$B55) -> 37595583 | AM101: =SUM('P34'!$B52:$B55) -> 38737393 | AN101: =SUM('P35'!$B52:$B55) -> 38891878 | AO101: =SUM('P36'!$B52:$B55) -> 40230515 | AP101: =SUM('P37'!$B52:$B55) -> 43855322 | AQ101: =SUM('P38'!$B52:$B55) -> 40929553 | AR101: =SUM('P39'!$B52:$B55) -> 43643726 | AS101: =SUM('P40'!$B52:$B55) -> 45102257 | AT101: =SUM('P41'!$B52:$B55) -> 44061480 | AU101: =SUM('P42'!$B52:$B55) -> 43644873 | AV101: =SUM('P43'!$B52:$B55) -> 48003714 | AW101: =SUM('P44'!$B52:$B55) -> 49412430 | AX101: =SUM('P45'!$B52:$B55) -> 53652204 | AY101: =SUM('P46'!$B52:$B55) -> 54613803 | AZ101: =SUM('P47'!$B52:$B55) -> 60070719 | BA101: =SUM('P48'!$B52:$B55) -> 56318432 | BB101: =SUM('P49'!$B52:$B55) -> 59697595 | BC101: =SUM('P50'!$B52:$B55) -> 60909195 | BD101: =SUM('P51'!$B52:$B55) -> 62165624 | BE101: =SUM('P52'!$B52:$B55) -> 59024050 | BF101: =SUM('P53'!$B52:$B55) -> 60955212 | BG101: =SUM('P54'!$B52:$B55) -> 60549256 | BH101: =SUM('P55'!$B52:$B55) -> 63240440 | BI101: =SUM('P56'!$B52:$B55) -> 40982388 | BJ101: =SUM('P57'!$B52:$B55) -> 41006941 | BK101: =SUM('P58'!$B52:$B55) -> 40273971 | BL101: =SUM('P59'!$B52:$B55) -> 39483771 | BM101: =SUM('P60'!$B52:$B55) -> 39354216 | BN101: =SUM('P61'!$B52:$B55) -> 44278008 | BO101: =SUM('P62'!$B52:$B55) -> 32745831 | BP101: =SUM('P63'!$B52:$B55) -> 0 | BQ101: =SUM('P64'!$B52:$B55) -> 0 | BR101: =SUM('P65'!$B52:$B55) -> 0 | BS101: =SUM('P66'!$B52:$B55) -> 0 | BT101: =SUM('P67'!$B52:$B55) -> 0 | BU101: =SUM('P68'!$B52:$B55) -> 0 | BV101: =SUM('P69'!$B52:$B55) -> 0 | BW101: =SUM('P70'!$B52:$B55) -> 0 | BX101: =SUM('P71'!$B52:$B55) -> 0 | BY101: =SUM('P72'!$B52:$B55) -> 0 | BZ101: =SUM('P73'!$B52:$B55) -> 0 | CA101: =SUM('P74'!$B52:$B55) -> 0 | CB101: =SUM('P75'!$B52:$B55) -> 0
E102: Assets to DO produce cash flow | F102: =SUM('P1'!$B57:$B59) -> 10276374 | G102: =SUM('P2'!$B57:$B59) -> 11560946 | H102: =SUM('P3'!$B57:$B59) -> 12691813 | I102: =SUM('P4'!$B57:$B59) -> 12464400 | J102: =SUM('P5'!$B57:$B59) -> 13131369 | K102: =SUM('P6'!$B57:$B59) -> 12898112 | L102: =SUM('P7'!$B57:$B59) -> 12765278 | M102: =SUM('P8'!$B57:$B59) -> 12824811 | N102: =SUM('P9'!$B57:$B59) -> 12685256 | O102: =SUM('P10'!$B57:$B59) -> 12547584 | P102: =SUM('P11'!$B57:$B59) -> 12696408 | Q102: =SUM('P12'!$B57:$B59) -> 12464801 | R102: =SUM('P13'!$B57:$B59) -> 12333784 | S102: =SUM('P14'!$B57:$B59) -> 12929188 | T102: =SUM('P15'!$B57:$B59) -> 12795768 | U102: =SUM('P16'!$B57:$B59) -> 12569732 | V102: =SUM('P17'!$B57:$B59) -> 11925676 | W102: =SUM('P18'!$B57:$B59) -> 11852406 | X102: =SUM('P19'!$B57:$B59) -> 12135543 | Y102: =SUM('P20'!$B57:$B59) -> 12512626 | Z102: =SUM('P21'!B57:B59) -> 12384732 | AA102: =SUM('P22'!B57:B59) -> 12258187 | AB102: =SUM('P23'!B57:B59) -> 12132986 | AC102: =SUM('P24'!B57:B59) -> 12809124 | AD102: =SUM('P25'!B57:B59) -> 12819097 | AE102: =SUM('P26'!B57:B59) -> 13323398 | AF102: =SUM('P27'!B57:B59) -> 13042124 | AG102: =SUM('P28'!B57:B59) -> 13433360 | AH102: =SUM('P29'!B57:B59) -> 13414950 | AI102: =SUM('P30'!B57:B59) -> 13392251 | AJ102: =SUM('P31'!B57:B59) -> 13365544 | AK102: =SUM('P32'!$B57:$B59) -> 13335092 | AL102: =SUM('P33'!$B57:$B59) -> 13936033 | AM102: =SUM('P34'!$B57:$B59) -> 14613078 | AN102: =SUM('P35'!$B57:$B59) -> 15482529 | AO102: =SUM('P36'!$B57:$B59) -> 15411242 | AP102: =SUM('P37'!$B57:$B59) -> 15337692 | AQ102: =SUM('P38'!$B57:$B59) -> 19014080 | AR102: =SUM('P39'!$B57:$B59) -> 20689648 | AS102: =SUM('P40'!$B57:$B59) -> 20541568 | AT102: =SUM('P41'!$B57:$B59) -> 20392766 | AU102: =SUM('P42'!$B57:$B59) -> 21343385 | AV102: =SUM('P43'!$B57:$B59) -> 21179801 | AW102: =SUM('P44'!$B57:$B59) -> 21016058 | AX102: =SUM('P45'!$B57:$B59) -> 20852270 | AY102: =SUM('P46'!$B57:$B59) -> 20688538 | AZ102: =SUM('P47'!$B57:$B59) -> 20524964 | BA102: =SUM('P48'!$B57:$B59) -> 20361641 | BB102: =SUM('P49'!$B57:$B59) -> 17752803 | BC102: =SUM('P50'!$B57:$B59) -> 17620806 | BD102: =SUM('P51'!$B57:$B59) -> 17488919 | BE102: =SUM('P52'!$B57:$B59) -> 17357220 | BF102: =SUM('P53'!$B57:$B59) -> 17225780 | BG102: =SUM('P54'!$B57:$B59) -> 17094661 | BH102: =SUM('P55'!$B57:$B59) -> 16963929 | BI102: =SUM('P56'!$B57:$B59) -> 17633641 | BJ102: =SUM('P57'!$B57:$B59) -> 17493850 | BK102: =SUM('P58'!$B57:$B59) -> 17818182 | BL102: =SUM('P59'!$B57:$B59) -> 17446311 | BM102: =SUM('P60'!$B57:$B59) -> 17086543 | BN102: =SUM('P61'!$B57:$B59) -> 16738359 | BO102: =SUM('P62'!$B57:$B59) -> 18465200 | BP102: =SUM('P63'!$B57:$B59) -> 0 | BQ102: =SUM('P64'!$B57:$B59) -> 0 | BR102: =SUM('P65'!$B57:$B59) -> 0 | BS102: =SUM('P66'!$B57:$B59) -> 0 | BT102: =SUM('P67'!$B57:$B59) -> 0 | BU102: =SUM('P68'!$B57:$B59) -> 0 | BV102: =SUM('P69'!$B57:$B59) -> 0 | BW102: =SUM('P70'!$B57:$B59) -> 0 | BX102: =SUM('P71'!$B57:$B59) -> 0 | BY102: =SUM('P72'!$B57:$B59) -> 0 | BZ102: =SUM('P73'!$B57:$B59) -> 0 | CA102: =SUM('P74'!$B57:$B59) -> 0 | CB102: =SUM('P75'!$B57:$B59) -> 0
E106: Assets that DO NOT produce cash flow | F106: =IF(B$1<30,CHOOSE(B$1,F101,G101,H101,I101,J101,K101,L101,M101,N101,O101,P101,Q101,R101,S101,T101,U101,V101,W101,X101,Y101,Z101,AA101,AB101,AC101,AD101,AE101,AF101,AG101,AH101),IF(B$1<59,CHOOSE(B$1-29,AI101,AJ101,AK101,AL101,AM101,AN101,AO101,AP101,AQ101,AR101,AS101,AT101,AU101,AV101,AW101,AX101,AY101,AZ101,BA101,BB101,BC101,BD101,BE101,BF101,BG101,BH101,BI101,BJ101,BK101),CHOOSE(B$1-58,BL101,BM101,BN101,BO101,BP101,BQ101,BR101,BS101,BT101,BU101,BV101,BW101,BX101,BY101,BZ101,CA101,CB101))) -> 32745831
E107: Assets that DO produce cash flow | F107: =IF(B$1<30,CHOOSE(B$1,F102,G102,H102,I102,J102,K102,L102,M102,N102,O102,P102,Q102,R102,S102,T102,U102,V102,W102,X102,Y102,Z102,AA102,AB102,AC102,AD102,AE102,AF102,AG102,AH102),IF(B$1<59,CHOOSE(B$1-29,AI102,AJ102,AK102,AL102,AM102,AN102,AO102,AP102,AQ102,AR102,AS102,AT102,AU102,AV102,AW102,AX102,AY102,AZ102,BA102,BB102,BC102,BD102,BE102,BF102,BG102,BH102,BI102,BJ102,BK102),CHOOSE(B$1-58,BL102,BM102,BN102,BO102,BP102,BQ102,BR102,BS102,BT102,BU102,BV102,BW102,BX102,BY102,BZ102,CA102,CB102))) -> 18465200
E109: DEBT | F109: =IF(B$1<30,CHOOSE(B$1,F7,G7,H7,I7,J7,K7,L7,M7,N7,O7,P7,Q7,R7,S7,T7,U7,V7,W7,X7,Y7,Z7,AA7,AB7,AC7,AD7,AE7,AF7,AG7,AH7),IF(B$1<59,CHOOSE(B$1-29,AI7,AJ7,AK7,AL7,AM7,AN7,AO7,AP7,AQ7,AR7,AS7,AT7,AU7,AV7,AW7,AX7,AY7,AZ7,BA7,BB7,BC7,BD7,BE7,BF7,BG7,BH7,BI7,BJ7,BK7),CHOOSE(B$1-58,BL7,BM7,BN7,BO7,BP7,BQ7,BR7,BS7,BT7,BU7,BV7,BW7,BX7,BY7,BZ7,CA7,CB7))) -> 0.52785509
E110: EQUITY | F110: =IF(B$1<30,CHOOSE(B$1,F8,G8,H8,I8,J8,K8,L8,M8,N8,O8,P8,Q8,R8,S8,T8,U8,V8,W8,X8,Y8,Z8,AA8,AB8,AC8,AD8,AE8,AF8,AG8,AH8),IF(B$1<59,CHOOSE(B$1-29,AI8,AJ8,AK8,AL8,AM8,AN8,AO8,AP8,AQ8,AR8,AS8,AT8,AU8,AV8,AW8,AX8,AY8,AZ8,BA8,BB8,BC8,BD8,BE8,BF8,BG8,BH8,BI8,BJ8,BK8),CHOOSE(B$1-58,BL8,BM8,BN8,BO8,BP8,BQ8,BR8,BS8,BT8,BU8,BV8,BW8,BX8,BY8,BZ8,CA8,CB8))) -> 0.47214491

Sheet IM Variance
A1: =ACTIVE!A2 -> 62 | F1: Marketing Input
A4: Forecast | E4: Actual | I4: Variance
B5: Sales (Units) | C5: Product 1 | D5: Product 2 | F5: Sales (Units) | G5: Product 1 | H5: Product 2 | J5: Sales (Units) | K5: Product 1 | L5: Product 2
B6: Japan | C6: 32392 | D6: 29820 | F6: Japan | G6: =ACTIVE!B91 -> 73793 | H6: =ACTIVE!B133 -> 66044 | J6: Japan | K6: =(G6-C6)/C6 -> 1.2781242 | L6: =(H6-D6)/D6 -> 1.2147552
B7: Mexico | C7: 15300 | D7: 1120 | F7: Mexico | G7: =ACTIVE!B92 -> 30809 | H7: =ACTIVE!B134 -> 22257 | J7: Mexico | K7: =(G7-C7)/C7 -> 1.0136601 | L7: =(H7-D7)/D7 -> 18.872321 | N7: Currency | O7: To dollars
B8: China | C8: 11247 | D8: 1544 | F8: China | G8: =ACTIVE!B93 -> 21253 | H8: =ACTIVE!B135 -> 22786 | J8: China | K8: =(G8-C8)/C8 -> 0.88965946 | L8: =(H8-D8)/D8 -> 13.757772 | N8: YEN | O8: ='FIN-RPT'!F48 -> 90
B9: U.K. | C9: 43516 | D9: 36304 | F9: U.K. | G9: =ACTIVE!B94 -> 48634 | H9: =ACTIVE!B136 -> 56320 | J9: U.K. | K9: =(G9-C9)/C9 -> 0.11761191 | L9: =(H9-D9)/D9 -> 0.5513442 | N9: PESO | O9: ='FIN-RPT'!F49 -> 12.8
B10: Germany | C10: 66651 | D10: 64000 | F10: Germany | G10: =ACTIVE!B95 -> 51834 | H10: =ACTIVE!B137 -> 65387 | J10: Germany | K10: =(G10-C10)/C10 -> -0.22230724 | L10: =(H10-D10)/D10 -> 0.021671875 | N10: YUAN | O10: ='FIN-RPT'!F50 -> 6.5
B11: U.S. | C11: 112085 | D11: 78000 | F11: U.S. | G11: =ACTIVE!B96 -> 127968 | H11: =ACTIVE!B138 -> 156719 | J11: U.S. | K11: =(G11-C11)/C11 -> 0.14170496 | L11: =(H11-D11)/D11 -> 1.0092179 | N11: POUND | O11: ='FIN-RPT'!F51 -> 0.65
B12: New Contract | C12: 45000 | F12: New Contract | G12: =ACTIVE!B82 -> 180000 | J12: New Contract | K12: =(G12-C12)/C12 -> 3 | N12: MARK | O12: ='FIN-RPT'!F52 -> 0.77
B13: Other Contract | C13: 0 | F13: Other Contract | J13: Other Contract | N13: DOLLAR | O13: 1
C14: =SUM(C6:C12) -> 326191 | D14: =SUM(D6:D13) -> 210788 | G14: =SUM(G6:G13) -> 534291 | H14: =SUM(H6:H13) -> 389513
B15: Price | C15: Product 1 | D15: Product 2 | F15: Price | G15: Product 1 | H15: Product 2 | J15: Price | K15: Product 1 | L15: Product 2
B16: Japan | C16: 32.608696 | D16: 73.043478 | F16: Japan | G16: =ACTIVE!B16/O8 -> 44.444444 | H16: =ACTIVE!B26/O8 -> 67.777778 | J16: Japan | K16: =(G16-C16)/C16 -> 0.36296296 | L16: =(H16-D16)/D16 -> -0.072089947 | N16: Country | O16: Mexico | P16: U.S.
B17: Mexico | C17: 28.421053 | D17: 83.157895 | F17: Mexico | G17: =ACTIVE!C16/O9 -> 23.4375 | H17: =ACTIVE!C26/O9 -> 35.15625 | J17: Mexico | K17: =(G17-C17)/C17 -> -0.17534722 | L17: =(H17-D17)/D17 -> -0.57723497 | N17: Japan | O17: =HLOOKUP(O$16,'FIN-RPT'!$B$28:$L$34,2,FALSE) -> 0.09 | P17: =HLOOKUP(P$16,'FIN-RPT'!$B$28:$L$34,2,FALSE) -> 0.09
B18: China | C18: 29.444444 | D18: 95.555556 | F18: China | G18: =ACTIVE!D16/O10 -> 43.076923 | H18: =ACTIVE!D26/O10 -> 69.230769 | J18: China | K18: =(G18-C18)/C18 -> 0.46298984 | L18: =(H18-D18)/D18 -> -0.27549195 | N18: Mexico | O18: =HLOOKUP(O$16,'FIN-RPT'!$B$28:$L$34,3,FALSE) -> 0 | P18: =HLOOKUP(P$16,'FIN-RPT'!$B$28:$L$34,3,FALSE) -> 0
B19: U.K. | C19: 31.428571 | D19: 74.285714 | F19: U.K. | G19: =ACTIVE!E16/O11 -> 43.846154 | H19: =ACTIVE!E26/O11 -> 69.230769 | J19: U.K. | K19: =(G19-C19)/C19 -> 0.3951049 | L19: =(H19-D19)/D19 -> -0.068047337 | N19: China | O19: =HLOOKUP(O$16,'FIN-RPT'!$B$28:$L$34,4,FALSE) -> 0.092 | P19: =HLOOKUP(P$16,'FIN-RPT'!$B$28:$L$34,4,FALSE) -> 0.092
B20: Germany | C20: 24.285714 | D20: 60 | F20: Germany | G20: =ACTIVE!F16/O12 -> 57.987013 | H20: =ACTIVE!F26/O12 -> 71.428571 | J20: Germany | K20: =(G20-C20)/C20 -> 1.3877005 | L20: =(H20-D20)/D20 -> 0.19047619 | N20: U.K. | O20: =HLOOKUP(O$16,'FIN-RPT'!$B$28:$L$34,5,FALSE) -> 0.115 | P20: =HLOOKUP(P$16,'FIN-RPT'!$B$28:$L$34,5,FALSE) -> 0.115
B21: U.S. | C21: 30 | D21: 78 | F21: U.S. | G21: =ACTIVE!G16 -> 50 | H21: =ACTIVE!G26 -> 50 | J21: U.S. | K21: =(G21-C21)/C21 -> 0.66666667 | L21: =(H21-D21)/D21 -> -0.35897436 | N21: Germany | O21: =HLOOKUP(O$16,'FIN-RPT'!$B$28:$L$34,6,FALSE) -> 0.115 | P21: =HLOOKUP(P$16,'FIN-RPT'!$B$28:$L$34,6,FALSE) -> 0.115
N22: U.S. | O22: =HLOOKUP(O$16,'FIN-RPT'!$B$28:$L$34,7,FALSE) -> 0 | P22: =HLOOKUP(P$16,'FIN-RPT'!$B$28:$L$34,7,FALSE) -> 0
B23: Revenue | C23: Product 1 | D23: Product 2 | F23: Revenue | G23: Product 1 | H23: Product 2 | J23: Revenue | K23: Product 1 | L23: Product 2
B24: Japan | C24: 1056260.9 | D24: 2178156.5 | F24: Japan | G24: =G6*G16 -> 3279688.9 | H24: =H6*H16 -> 4476315.6 | J24: Japan | K24: =(G24-C24)/C24 -> 2.1049989 | L24: =(H24-D24)/D24 -> 1.0550936
B25: Mexico | C25: 434842.11 | D25: 93136.842 | F25: Mexico | G25: =G7*G17 -> 722085.94 | H25: =H7*H17 -> 782472.66 | J25: Mexico | K25: =(G25-C25)/C25 -> 0.66057042 | L25: =(H25-D25)/D25 -> 7.4013226
B26: China | C26: 331161.67 | D26: 147537.78 | F26: China | G26: =G8*G18 -> 915513.85 | H26: =H8*H18 -> 1577492.3 | J26: China | K26: =(G26-C26)/C26 -> 1.7645526 | L26: =(H26-D26)/D26 -> 9.6921246
B27: U.K. | C27: 1367645.7 | D27: 2696868.6 | F27: U.K. | G27: =G9*G19 -> 2132413.8 | H27: =H9*H19 -> 3899076.9 | J27: U.K. | K27: =(G27-C27)/C27 -> 0.55918585 | L27: =(H27-D27)/D27 -> 0.44577936
B28: Germany | C28: 1618667.1 | D28: 3840000 | F28: Germany | G28: =G10*G20 -> 3005698.8 | H28: =H10*H20 -> 4670500 | J28: Germany | K28: =(G28-C28)/C28 -> 0.85689741 | L28: =(H28-D28)/D28 -> 0.21627604
B29: U.S. | C29: 3362550 | D29: 6084000 | F29: U.S. | G29: =G11*G21 -> 6398400 | H29: =H11*H21 -> 7835950 | J29: U.S. | K29: =(G29-C29)/C29 -> 0.90284159 | L29: =(H29-D29)/D29 -> 0.28796022
C30: 8171127.5 | D30: 15039700
B32: Marketing Expense | C32: Product 1 | D32: Product 2 | F32: Marketing Expense | G32: Product 1 | H32: Product 2 | J32: Marketing Expense | K32: Product 1 | L32: Product 2
B33: Japan | C33: 146086.96 | D33: 172000 | F33: Japan | G33: =ACTIVE!B115/O8 -> 155556 | H33: =ACTIVE!B157/O8 -> 188889 | J33: Japan | K33: =(G33-C33)/C33 -> 0.064817857 | L33: =(H33-D33)/D33 -> 0.09819186
B34: Mexico | C34: 50947.368 | D34: 2315.7895 | F34: Mexico | G34: =ACTIVE!B116/O9 -> 46875 | H34: =ACTIVE!B158/O9 -> 62500 | J34: Mexico | K34: =(G34-C34)/C34 -> -0.079932851 | L34: =(H34-D34)/D34 -> 25.988636
B35: China | C35: 7000 | D35: 8000 | F35: China | G35: =ACTIVE!B117/O10 -> 92308 | H35: =ACTIVE!B159/O10 -> 135385 | J35: China | K35: =(G35-C35)/C35 -> 12.186857 | L35: =(H35-D35)/D35 -> 15.923125
B36: U.K. | C36: 514285.71 | D36: 520000 | F36: U.K. | G36: =ACTIVE!B118/O11 -> 230769 | H36: =ACTIVE!B160/O11 -> 338462 | J36: U.K. | K36: =(G36-C36)/C36 -> -0.5512825 | L36: =(H36-D36)/D36 -> -0.34911154
B37: Germany | C37: 213986.19 | D37: 570000 | F37: Germany | G37: =ACTIVE!B119/O12 -> 324675 | H37: =ACTIVE!B161/O12 -> 454545 | J37: Germany | K37: =(G37-C37)/C37 -> 0.51727081 | L37: =(H37-D37)/D37 -> -0.20255263
B38: U.S. | C38: 768000 | D38: 1300000 | F38: U.S. | G38: =ACTIVE!B120/O13 -> 1000000 | H38: =ACTIVE!B162/O13 -> 1200000 | J38: U.S. | K38: =(G38-C38)/C38 -> 0.30208333 | L38: =(H38-D38)/D38 -> -0.076923077

Sheet Tabulate
A1: =ACTIVE!A2 -> 62 | B1: Do not edit
A2: =COUNTA(B3:GG3)+1 -> 1 | B2: Cells A1, A2
A4: Tabulate Tool | I4: See Instructions below
A5: Time Period
A6: Period 1 | I6: This tool is useful for extracting data over time for graphs or regressions
A7: Period 2 | I7: You can select any cell within any report and then quickly extract that data for all time periods. Here is how to do it.
A8: Period 3
A9: Period 4 | I9: 1. Select any cell within any of the reports, from the marketing report to the cash flow statement
A10: Period 5 | I10: 2. Press the copy button, then go to cell B3 within the "Tabulate" worksheet. (see Yellow above)
A11: Period 6 | I11: 3. From the high level menu, select "Edit", then select "Paste Special", then select "Paste Link"
A12: Period 7 | I12: 4. You can repeat this procedure and place additional variables into cells C3, D3, E3, F3, G3 as you wish
A13: Period 8 | I13: 5. Press the button called "Fill The Table"
A14: Period 9 | I14: 6. The table will fill with data from all time periods which contain information and then stop.
A15: Period 10 | I15: 7. You should assign some text label to each vector of data so that you remember what data you have extracted
A16: Period 11
A17: Period 12 | I17: When you have extracted the data that you want, you can copy it into regression software, attempt to
A18: Period 13 | I18: perform the regression within excel, or you can copy the data into some graph for presentation purposes
A19: Period 14
A20: Period 15 | I20: This tool can save you time whenever you wish to view data over time.
A21: Period 16
A22: Period 17 | I22: The button labeled "Copy Data" will simply highlight whatever data that you selected plus whatever
A23: Period 18 | I23: Text labels that you place in the Geeen area so that you can extract this information to other locations
A24: Period 19
A25: Period 20
A26: Period 21
A27: Period 22
A28: Period 23
A29: Period 24
A30: Period 25
A31: Period 26
A32: Period 27
A33: Period 28
A34: Period 29
A35: Period 30
... A105: Period 100

Sheet COMPETITORS
A1: QUARTERS COMPLETED | E1: SALES REVENUES | V1: 12 | AA1: SALES REVENUES | BY1: TOTAL
A2: COMPANIES PLAYING | E2: $(000) US DOLLARS | V2: 5 | AA2: $(000) US DOLLARS | BY2: SALES
B3: Q1 | C3: Q2 | D3: Q3 | E3: Q4 | F3: Q5 | G3: Q6 | H3: Q7 | I3: Q8 | J3: Q9 | K3: Q10 | L3: Q11 | M3: Q12 | N3: Q13 | O3: Q14 | P3: Q15 | Q3: Q16 | R3: Q17 | S3: Q18 | T3: Q19 | U3: Q20 | V3: Q21 | W3: Q22 | X3: Q23 | Y3: Q24 | Z3: Q25 | AA3: Q26 | AB3: Q27 | AC3: Q28 | AD3: Q29 | AE3: Q30 | AF3: Q31 | AG3: Q32 | AH3: Q33 | AI3: Q34 | AJ3: Q35 | AK3: Q36 | AL3: Q37 | AM3: Q38 | AN3: Q39 | AO3: Q40 | AP3: Q41 | AQ3: Q42 | AR3: Q43 | AS3: Q44 | AT3: Q45 | AU3: Q46 | AV3: Q47 | AW3: Q48 | AX3: Q49 | AY3: Q50 | AZ3: Q51 | BA3: Q52 | BB3: Q53 | BC3: Q54 | BD3: Q55 | BE3: Q56 | BF3: Q57 | BG3: Q58 | BH3: Q59 | BI3: Q60 | BJ3: Q61 | BK3: Q62 | BL3: Q63 | BM3: Q64 | BN3: Q65 | BO3: Q66 | BP3: Q67 | BQ3: Q68 | BR3: Q69 | BS3: Q70 | BT3: Q71 | BU3: Q72 | BV3: Q73 | BW3: Q74 | BX3: Q75 | BY3: $(000)
B4: - | C4: - | D4: - | E4: - | F4: - | G4: - | H4: - | I4: - | J4: - | K4: - | L4: - | M4: - | N4: - | O4: - | P4: - | Q4: - | R4: - | S4: - | T4: - | U4: - | V4: - | W4: - | X4: - | Y4: - | Z4: - | AA4: - | AB4: - | AC4: - | BY4: =
A5: Company 1 | B5: =Data!B37 -> 29324.169 | C5: =Data!C37 -> 24973.227 | D5: =Data!D37 -> 24674.709 | E5: =Data!E37 -> 30220.199 | F5: =Data!F37 -> 30946.722 | G5: =Data!G37 -> 23813.332 | H5: =Data!H37 -> 24927.112 | I5: =Data!I37 -> 32088.723 | ... BX5: =Data!BX37 -> 0 | BY5: =SUM(BJ5:BX5) -> 82843.728
A6: Company 2 | B6: =Data!B38 -> 29324.169 | C6: =Data!C38 -> 26986.417 | D6: =Data!D38 -> 24051.796 | E6: =Data!E38 -> 28515.345 | F6: =Data!F38 -> 29755.668 | G6: =Data!G38 -> 30562.181 | H6: =Data!H38 -> 23596.796 | I6: =Data!I38 -> 23092.145 | ... BX6: =Data!BX38 -> 0 | BY6: =SUM(BJ6:BX6) -> 78681.994
A7: Company 3 | B7: =Data!B39 -> 29324.169 | C7: =Data!C39 -> 24598.118 | D7: =Data!D39 -> 23000.985 | E7: =Data!E39 -> 21464.475 | F7: =Data!F39 -> 24126.104 | G7: =Data!G39 -> 29752.663 | H7: =Data!H39 -> 31806.554 | I7: =Data!I39 -> 22729.517 | ... BX7: =Data!BX39 -> 0 | BY7: =SUM(BJ7:BX7) -> 75221.017
A8: Company 4 | B8: =Data!B40 -> 29324.169 | C8: =Data!C40 -> 26861.889 | D8: =Data!D40 -> 28103.007 | E8: =Data!E40 -> 23018.475 | F8: =Data!F40 -> 22534.49 | G8: =Data!G40 -> 26576.966 | H8: =Data!H40 -> 32066.679 | I8: =Data!I40 -> 31317.094 | ... BX8: =Data!BX40 -> 0 | BY8: =SUM(BJ8:BX8) -> 78945.878
A9: Company 5 | B9: =Data!B41 -> 29324.169 | C9: =Data!C41 -> 24598.118 | D9: =Data!D41 -> 25785.54 | E9: =Data!E41 -> 23991.943 | F9: =Data!F41 -> 22202.836 | G9: =Data!G41 -> 21109.105 | H9: =Data!H41 -> 25919.265 | I9: =Data!I41 -> 28157.789 | ... BX9: =Data!BX41 -> 0 | BY9: =SUM(BJ9:BX9) -> 80149.17
B11: - | C11: - | D11: - | E11: - | F11: - | G11: - | H11: - | I11: - | J11: - | K11: - | L11: - | M11: - | N11: - | O11: - | P11: - | Q11: - | R11: - | S11: - | T11: - | U11: - | V11: - | W11: - | X11: - | Y11: - | Z11: - | AA11: - | AB11: - | AC11: - | BY11: =
A12: WORLD-WIDE MEAN | B12: =SUM(B5:B10)/$V$2 -> 29324.169 | C12: =SUM(C5:C10)/$V$2 -> 25603.554 | D12: =SUM(D5:D10)/$V$2 -> 25123.207 | E12: =SUM(E5:E10)/$V$2 -> 25442.088 | F12: =SUM(F5:F10)/$V$2 -> 25913.164 | G12: =SUM(G5:G10)/$V$2 -> 26362.849 | H12: =SUM(H5:H10)/$V$2 -> 27663.281 | I12: =SUM(I5:I10)/$V$2 -> 27477.054 | ... BY12: =SUM(BY5:BY10)/$V$2 -> 79168.357
E45: NET PROFITS | AA45: NET PROFITS | BY45: NET
E46: $(000) US DOLLARS | AA46: $(000) US DOLLARS | BY46: PROFITS
B47: Q1 | C47: Q2 | D47: Q3 | E47: Q4 | F47: Q5 | G47: Q6 | H47: Q7 | I47: Q8 | J47: Q9 | K47: Q10 | L47: Q11 | M47: Q12 | N47: Q13 | O47: Q14 | P47: Q15 | Q47: Q16 | R47: Q17 | S47: Q18 | T47: Q19 | U47: Q20 | V47: Q21 | W47: Q22 | X47: Q23 | Y47: Q24 | Z47: Q25 | AA47: Q26 | AB47: Q27 | AC47: Q28 | AD47: Q29 | AE47: Q30 | AF47: Q31 | AG47: Q32 | AH47: Q33 | AI47: Q34 | AJ47: Q35 | AK47: Q36 | AL47: Q37 | AM47: Q38 | AN47: Q39 | AO47: Q40 | AP47: Q41 | AQ47: Q42 | AR47: Q43 | AS47: Q44 | AT47: Q45 | AU47: Q46 | AV47: Q47 | AW47: Q48 | AX47: Q49 | AY47: Q50 | AZ47: Q51 | BA47: Q52 | BB47: Q53 | BC47: Q54 | BD47: Q55 | BE47: Q56 | BF47: Q57 | BG47: Q58 | BH47: Q59 | BI47: Q60 | BJ47: Q61 | BK47: Q62 | BL47: Q63 | BM47: Q64 | BN47: Q65 | BO47: Q66 | BP47: Q67 | BQ47: Q68 | BR47: Q69 | BS47: Q70 | BT47: Q71 | BU47: Q72 | BV47: Q73 | BW47: Q74 | BX47: Q75 | BY47: $(000)
B48: - | C48: - | D48: - | E48: - | F48: - | G48: - | H48: - | I48: - | J48: - | K48: - | L48: - | M48: - | N48: - | O48: - | P48: - | Q48: - | R48: - | S48: - | T48: - | U48: - | V48: - | W48: - | X48: - | Y48: - | Z48: - | AA48: - | AB48: - | AC48: - | BY48: =
A49: Company 1 | B49: =Data!B47 -> 4219.4043 | C49: =Data!C47 -> 3266.999 | D49: =Data!D47 -> 2826.9251 | E49: =Data!E47 -> 3638.1446 | F49: =Data!F47 -> 3856.4765 | G49: =Data!G47 -> 1417.7266 | H49: =Data!H47 -> 376.04746 | I49: =Data!I47 -> 2905.1969 | ... BX49: =Data!BX47 -> 0 | BY49: =SUM(BJ49:BX49) -> 3830.4126
A50: Company 2 | B50: =Data!B48 -> 4219.4043 | C50: =Data!C48 -> 3232.8966 | D50: =Data!D48 -> 3370.6268 | E50: =Data!E48 -> 3367.7019 | F50: =Data!F48 -> 3432.1803 | G50: =Data!G48 -> 4495.9303 | H50: =Data!H48 -> 1264.5736 | I50: =Data!I48 -> -451.61044 | ... BX50: =Data!BX48 -> 0 | BY50: =SUM(BJ50:BX50) -> 4561.0257
A51: Company 3 | B51: =Data!B49 -> 4219.4043 | C51: =Data!C49 -> 3352.9309 | D51: =Data!D49 -> 2626.6829 | E51: =Data!E49 -> 912.48583 | F51: =Data!F49 -> 600.77975 | G51: =Data!G49 -> 2363.1219 | H51: =Data!H49 -> 3211.2372 | I51: =Data!I49 -> 355.97288 | ... BX51: =Data!BX49 -> 0 | BY51: =SUM(BJ51:BX51) -> 5144.5229
A52: Company 4 | B52: =Data!B50 -> 4219.4043 | C52: =Data!C50 -> 3133.7771 | D52: =Data!D50 -> 4737.4462 | E52: =Data!E50 -> 2030.1222 | F52: =Data!F50 -> 939.57681 | G52: =Data!G50 -> 2089.6499 | H52: =Data!H50 -> 3149.1589 | I52: =Data!I50 -> 2776.0611 | ... BX52: =Data!BX50 -> 0 | BY52: =SUM(BJ52:BX52) -> 2212.191
A53: Company 5 | B53: =Data!B51 -> 4219.4043 | C53: =Data!C51 -> 3286.0069 | D53: =Data!D51 -> 3652.6566 | E53: =Data!E51 -> 2187.6504 | F53: =Data!F51 -> 516.09406 | G53: =Data!G51 -> 53.090371 | H53: =Data!H51 -> 968.63626 | I53: =Data!I51 -> 369.22919 | ... BX53: =Data!BX51 -> 0 | BY53: =SUM(BJ53:BX53) -> 4969.0054
B55: - | C55: - | D55: - | E55: - | F55: - | G55: - | H55: - | I55: - | J55: - | K55: - | L55: - | M55: - | N55: - | O55: - | P55: - | Q55: - | R55: - | S55: - | T55: - | U55: - | V55: - | W55: - | X55: - | Y55: - | Z55: - | AA55: - | AB55: - | AC55: - | AD55: - | AE55: - | AF55: - | AG55: - | AH55: - | AI55: - | AJ55: - | AK55: - | AL55: - | AM55: - | AN55: - | AO55: - | AP55: - | AQ55: - | AR55: - | AS55: - | AT55: - | AU55: - | AV55: - | AW55: - | AX55: - | AY55: - | AZ55: - | BA55: - | BB55: - | BC55: - | BD55: - | BE55: - | BF55: - | BG55: - | BH55: - | BI55: - | BJ55: - | BK55: - | BL55: - | BM55: - | BN55: - | BO55: - | BP55: - | BQ55: - | BR55: - | BS55: - | BT55: - | BU55: - | BV55: - | BW55: - | BX55: - | BY55: =
A56: WORLD-WIDE MEAN | B56: =SUM(B49:B54)/$V$2 -> 4219.4043 | C56: =SUM(C49:C54)/$V$2 -> 3254.5221 | D56: =SUM(D49:D54)/$V$2 -> 3442.8675 | E56: =SUM(E49:E54)/$V$2 -> 2427.221 | F56: =SUM(F49:F54)/$V$2 -> 1869.0215 | G56: =SUM(G49:G54)/$V$2 -> 2083.9038 | H56: =SUM(H49:H54)/$V$2 -> 1793.9307 | I56: =SUM(I49:I54)/$V$2 -> 1190.9699 | ... BY56: =SUM(BY49:BY54)/$V$2 -> 4143.4315
E86: TOTAL EQUITY | AA86: TOTAL EQUITY
E87: (000) US DOLLARS | AA87: (000) US DOLLARS
B89: Q1 | C89: Q2 | D89: Q3 | E89: Q4 | F89: Q5 | G89: Q6 | H89: Q7 | I89: Q8 | J89: Q9 | K89: Q10 | L89: Q11 | M89: Q12 | N89: Q13 | O89: Q14 | P89: Q15 | Q89: Q16 | R89: Q17 | S89: Q18 | T89: Q19 | U89: Q20 | V89: Q21 | W89: Q22 | X89: Q23 | Y89: Q24 | Z89: Q25 | AA89: Q26 | AB89: Q27 | AC89: Q28 | AD89: Q29 | AE89: Q30 | AF89: Q31 | AG89: Q32 | AH89: Q33 | AI89: Q34 | AJ89: Q35 | AK89: Q36 | AL89: Q37 | AM89: Q38 | AN89: Q39 | AO89: Q40 | AP89: Q41 | AQ89: Q42 | AR89: Q43 | AS89: Q44 | AT89: Q45 | AU89: Q46 | AV89: Q47 | AW89: Q48 | AX89: Q49 | AY89: Q50 | AZ89: Q51 | BA89: Q52 | BB89: Q53 | BC89: Q54 | BD89: Q55 | BE89: Q56 | BF89: Q57 | BG89: Q58 | BH89: Q59 | BI89: Q60 | BJ89: Q61 | BK89: Q62 | BL89: Q63 | BM89: Q64 | BN89: Q65 | BO89: Q66 | BP89: Q67 | BQ89: Q68 | BR89: Q69 | BS89: Q70 | BT89: Q71 | BU89: Q72 | BV89: Q73 | BW89: Q74 | BX89: Q75
B90: - | C90: - | D90: - | E90: - | F90: - | G90: - | H90: - | I90: - | J90: - | K90: - | L90: - | M90: - | N90: - | O90: - | P90: - | Q90: - | R90: - | S90: - | T90: - | U90: - | V90: - | W90: - | X90: - | Y90: - | Z90: - | AA90: - | AB90: - | AC90: -
A91: Company 1 | B91: =Data!B57 -> 25541.098 | C91: =Data!C57 -> 28808.097 | D91: =Data!D57 -> 31635.022 | E91: =Data!E57 -> 25273.167 | F91: =Data!F57 -> 29129.644 | G91: =Data!G57 -> 27547.37 | H91: =Data!H57 -> 20923.418 | I91: =Data!I57 -> 20828.614 | ... BX91: =Data!BX57 -> 0
A92: Company 2 | B92: =Data!B58 -> 25541.098 | C92: =Data!C58 -> 28773.995 | D92: =Data!D58 -> 32144.622 | E92: =Data!E58 -> 25512.324 | F92: =Data!F58 -> 28944.504 | G92: =Data!G58 -> 30440.434 | H92: =Data!H58 -> 24705.008 | I92: =Data!I58 -> 21253.397 | ... BX92: =Data!BX58 -> 0
A93: Company 3 | B93: =Data!B59 -> 25541.098 | C93: =Data!C59 -> 28894.029 | D93: =Data!D59 -> 31520.712 | E93: =Data!E59 -> 22433.198 | F93: =Data!F59 -> 23033.978 | G93: =Data!G59 -> 22397.1 | H93: =Data!H59 -> 18608.337 | I93: =Data!I59 -> 15964.31 | ... BX93: =Data!BX59 -> 0
A94: Company 4 | B94: =Data!B60 -> 25541.098 | C94: =Data!C60 -> 28674.875 | D94: =Data!D60 -> 33412.322 | E94: =Data!E60 -> 25442.444 | F94: =Data!F60 -> 26382.021 | G94: =Data!G60 -> 25471.67 | H94: =Data!H60 -> 21620.829 | I94: =Data!I60 -> 21396.89 | ... BX94: =Data!BX60 -> 0
A95: Company 5 | B95: =Data!B61 -> 25541.098 | C95: =Data!C61 -> 28827.105 | D95: =Data!D61 -> 32479.762 | E95: =Data!E61 -> 24667.412 | F95: =Data!F61 -> 25183.506 | G95: =Data!G61 -> 22236.597 | H95: =Data!H61 -> 16205.233 | I95: =Data!I61 -> 13574.462 | ... BX95: =Data!BX61 -> 0
B97: - | C97: - | D97: - | E97: - | F97: - | G97: - | H97: - | I97: - | J97: - | K97: - | L97: - | M97: - | N97: - | O97: - | P97: - | Q97: - | R97: - | S97: - | T97: - | U97: - | V97: - | W97: - | X97: - | Y97: - | Z97: - | AA97: - | AB97: - | AC97: - | AD97: - | AE97: - | AF97: - | AG97: - | AH97: - | AI97: - | AJ97: - | AK97: - | AL97: - | AM97: - | AN97: - | AO97: - | AP97: - | AQ97: - | AR97: - | AS97: - | AT97: - | AU97: - | AV97: - | AW97: - | AX97: - | AY97: - | AZ97: - | BA97: - | BB97: - | BC97: - | BD97: - | BE97: - | BF97: - | BG97: - | BH97: - | BI97: - | BJ97: - | BK97: - | BL97: - | BM97: - | BN97: - | BO97: - | BP97: - | BQ97: - | BR97: - | BS97: - | BT97: - | BU97: - | BV97: - | BW97: - | BX97: -
A98: WORLD-WIDE MEAN | B98: =SUM(B91:B96)/$V$2 -> 25541.098 | C98: =SUM(C91:C96)/$V$2 -> 28795.62 | D98: =SUM(D91:D96)/$V$2 -> 32238.488 | E98: =SUM(E91:E96)/$V$2 -> 24665.709 | F98: =SUM(F91:F96)/$V$2 -> 26534.73 | G98: =SUM(G91:G96)/$V$2 -> 25618.634 | H98: =SUM(H91:H96)/$V$2 -> 20412.565 | I98: =SUM(I91:I96)/$V$2 -> 18603.535 | ... BX98: =SUM(BX91:BX96)/$V$2 -> 0
D127: PRODUCT 1 | AA127: PRODUCT 1
D128: UNIT SALES | AA128: UNIT SALES
D129: JAPAN | AA129: JAPAN
BY130: TOTAL
B131: Q1 | C131: Q2 | D131: Q3 | E131: Q4 | F131: Q5 | G131: Q6 | H131: Q7 | I131: Q8 | J131: Q9 | K131: Q10 | L131: Q11 | M131: Q12 | N131: Q13 | O131: Q14 | P131: Q15 | Q131: Q16 | R131: Q17 | S131: Q18 | T131: Q19 | U131: Q20 | V131: Q21 | W131: Q22 | X131: Q23 | Y131: Q24 | Z131: Q25 | AA131: Q26 | AB131: Q27 | AC131: Q28 | AD131: Q29 | AE131: Q30 | AF131: Q31 | AG131: Q32 | AH131: Q33 | AI131: Q34 | AJ131: Q35 | AK131: Q36 | AL131: Q37 | AM131: Q38 | AN131: Q39 | AO131: Q40 | AP131: Q41 | AQ131: Q42 | AR131: Q43 | AS131: Q44 | AT131: Q45 | AU131: Q46 | AV131: Q47 | AW131: Q48 | AX131: Q49 | AY131: Q50 | AZ131: Q51 | BA131: Q52 | BB131: Q53 | BC131: Q54 | BD131: Q55 | BE131: Q56 | BF131: Q57 | BG131: Q58 | BH131: Q59 | BI131: Q60 | BJ131: Q61 | BK131: Q62 | BL131: Q63 | BM131: Q64 | BN131: Q65 | BO131: Q66 | BP131: Q67 | BQ131: Q68 | BR131: Q69 | BS131: Q70 | BT131: Q71 | BU131: Q72 | BV131: Q73 | BW131: Q74 | BX131: Q75 | BY131: SALES
B132: - | C132: - | D132: - | E132: - | F132: - | G132: - | H132: - | I132: - | J132: - | K132: - | L132: - | M132: - | N132: - | O132: - | P132: - | Q132: - | R132: - | S132: - | T132: - | U132: - | V132: - | W132: - | X132: - | Y132: - | Z132: - | AA132: - | AB132: - | AC132: - | BY132: =
A133: Company 1 | B133: =Data!B67 -> 48349 | C133: =Data!C67 -> 46345 | D133: =Data!D67 -> 43155 | E133: =Data!E67 -> 53140 | F133: =Data!F67 -> 52951 | G133: =Data!G67 -> 39420 | H133: =Data!H67 -> 39834 | I133: =Data!I67 -> 65978 | ... BX133: =Data!BX67 -> 0 | BY133: =SUM(BJ133:BX133) -> 144388
A134: Company 2 | B134: =Data!B68 -> 48349 | C134: =Data!C68 -> 43574 | D134: =Data!D68 -> 39078 | E134: =Data!E68 -> 48624 | F134: =Data!F68 -> 53290 | G134: =Data!G68 -> 53216 | H134: =Data!H68 -> 39749 | I134: =Data!I68 -> 37270 | ... BX134: =Data!BX68 -> 0 | BY134: =SUM(BJ134:BX134) -> 156034
A135: Company 3 | B135: =Data!B69 -> 48349 | C135: =Data!C69 -> 45882 | D135: =Data!D69 -> 39631 | E135: =Data!E69 -> 36152 | F135: =Data!F69 -> 39429 | G135: =Data!G69 -> 50411 | H135: =Data!H69 -> 51623 | I135: =Data!I69 -> 47172 | ... BX135: =Data!BX69 -> 0 | BY135: =SUM(BJ135:BX135) -> 135076
A136: Company 4 | B136: =Data!B70 -> 48349 | C136: =Data!C70 -> 43574 | D136: =Data!D70 -> 51356 | E136: =Data!E70 -> 47616 | F136: =Data!F70 -> 50190 | G136: =Data!G70 -> 57858 | H136: =Data!H70 -> 64183 | I136: =Data!I70 -> 50002 | ... BX136: =Data!BX70 -> 0 | BY136: =SUM(BJ136:BX136) -> 141358
A137: Company 5 | B137: =Data!B71 -> 48349 | C137: =Data!C71 -> 45882 | D137: =Data!D71 -> 45728 | E137: =Data!E71 -> 40573 | F137: =Data!F71 -> 36308 | G137: =Data!G71 -> 37260 | H137: =Data!H71 -> 45416 | I137: =Data!I71 -> 62830 | ... BX137: =Data!BX71 -> 0 | BY137: =SUM(BJ137:BX137) -> 150083
B139: - | C139: - | D139: - | E139: - | F139: - | G139: - | H139: - | I139: - | J139: - | K139: - | L139: - | M139: - | N139: - | O139: - | P139: - | Q139: - | R139: - | S139: - | T139: - | U139: - | V139: - | W139: - | X139: - | Y139: - | Z139: - | AA139: - | AB139: - | AC139: - | AD139: - | AE139: - | AF139: - | AG139: - | AH139: - | AI139: - | AJ139: - | AK139: - | AL139: - | AM139: - | AN139: - | AO139: - | AP139: - | AQ139: - | AR139: - | AS139: - | AT139: - | AU139: - | AV139: - | AW139: - | AX139: - | AY139: - | AZ139: - | BA139: - | BB139: - | BC139: - | BD139: - | BE139: - | BF139: - | BG139: - | BH139: - | BI139: - | BJ139: - | BK139: - | BL139: - | BM139: - | BN139: - | BO139: - | BP139: - | BQ139: - | BR139: - | BS139: - | BT139: - | BU139: - | BV139: - | BW139: - | BX139: - | BY139: =
A140: WORLD-WIDE TOTAL | B140: =SUM(B133:B138) -> 241745 | C140: =SUM(C133:C138) -> 225257 | D140: =SUM(D133:D138) -> 218948 | E140: =SUM(E133:E138) -> 226105 | F140: =SUM(F133:F138) -> 232168 | G140: =SUM(G133:G138) -> 238165 | H140: =SUM(H133:H138) -> 240805 | I140: =SUM(I133:I138) -> 263252 | ... BY140: =SUM(BY133:BY138) -> 726939
D169: PRODUCT 1 | AA169: PRODUCT 1
D170: UNIT SALES | AA170: UNIT SALES
D171: MEXICO | AA171: MEXICO
B173: Q1 | C173: Q2 | D173: Q3 | E173: Q4 | F173: Q5 | G173: Q6 | H173: Q7 | I173: Q8 | J173: Q9 | K173: Q10 | L173: Q11 | M173: Q12 | N173: Q13 | O173: Q14 | P173: Q15 | Q173: Q16 | R173: Q17 | S173: Q18 | T173: Q19 | U173: Q20 | V173: Q21 | W173: Q22 | X173: Q23 | Y173: Q24 | Z173: Q25 | AA173: Q26 | AB173: Q27 | AC173: Q28 | AD173: Q29 | AE173: Q30 | AF173: Q31 | AG173: Q32 | AH173: Q33 | AI173: Q34 | AJ173: Q35 | AK173: Q36 | AL173: Q37 | AM173: Q38 | AN173: Q39 | AO173: Q40 | AP173: Q41 | AQ173: Q42 | AR173: Q43 | AS173: Q44 | AT173: Q45 | AU173: Q46 | AV173: Q47 | AW173: Q48 | AX173: Q49 | AY173: Q50 | AZ173: Q51 | BA173: Q52 | BB173: Q53 | BC173: Q54 | BD173: Q55 | BE173: Q56 | BF173: Q57 | BG173: Q58 | BH173: Q59 | BI173: Q60 | BJ173: Q61 | BK173: Q62 | BL173: Q63 | BM173: Q64 | BN173: Q65 | BO173: Q66 | BP173: Q67 | BQ173: Q68 | BR173: Q69 | BS173: Q70 | BT173: Q71 | BU173: Q72 | BV173: Q73 | BW173: Q74 | BX173: Q75 | BY173: SALES
B174: - | C174: - | D174: - | E174: - | F174: - | G174: - | H174: - | I174: - | J174: - | K174: - | L174: - | M174: - | N174: - | O174: - | P174: - | Q174: - | R174: - | S174: - | T174: - | U174: - | V174: - | W174: - | X174: - | Y174: - | Z174: - | AA174: - | AB174: - | AC174: - | BY174: =
A175: Company 1 | B175: =Data!B77 -> 27240 | C175: =Data!C77 -> 26121 | D175: =Data!D77 -> 25137 | E175: =Data!E77 -> 26950 | F175: =Data!F77 -> 25409 | G175: =Data!G77 -> 19363 | H175: =Data!H77 -> 19944 | I175: =Data!I77 -> 26522 | ... BX175: =Data!BX77 -> 0 | BY175: =SUM(BJ175:BX175) -> 63329
A176: Company 2 | B176: =Data!B78 -> 27240 | C176: =Data!C78 -> 24258 | D176: =Data!D78 -> 19859 | E176: =Data!E78 -> 23960 | F176: =Data!F78 -> 26469 | G176: =Data!G78 -> 26724 | H176: =Data!H78 -> 19445 | I176: =Data!I78 -> 20122 | ... BX176: =Data!BX78 -> 0 | BY176: =SUM(BJ176:BX176) -> 70367
A177: Company 3 | B177: =Data!B79 -> 27240 | C177: =Data!C79 -> 25937 | D177: =Data!D79 -> 23122 | E177: =Data!E79 -> 18448 | F177: =Data!F79 -> 19083 | G177: =Data!G79 -> 24919 | H177: =Data!H79 -> 25972 | I177: =Data!I79 -> 19034 | ... BX177: =Data!BX79 -> 0 | BY177: =SUM(BJ177:BX177) -> 51778
A178: Company 4 | B178: =Data!B80 -> 27240 | C178: =Data!C80 -> 24258 | D178: =Data!D80 -> 27624 | E178: =Data!E80 -> 19679 | F178: =Data!F80 -> 23200 | G178: =Data!G80 -> 27027 | H178: =Data!H80 -> 31371 | I178: =Data!I80 -> 27023 | ... BX178: =Data!BX80 -> 0 | BY178: =SUM(BJ178:BX178) -> 77032
A179: Company 5 | B179: =Data!B81 -> 27240 | C179: =Data!C81 -> 25937 | D179: =Data!D81 -> 26679 | E179: =Data!E81 -> 20704 | F179: =Data!F81 -> 17572 | G179: =Data!G81 -> 18419 | H179: =Data!H81 -> 22459 | I179: =Data!I81 -> 25493 | ... BX179: =Data!BX81 -> 0 | BY179: =SUM(BJ179:BX179) -> 70319
B181: - | C181: - | D181: - | E181: - | F181: - | G181: - | H181: - | I181: - | J181: - | K181: - | L181: - | M181: - | N181: - | O181: - | P181: - | Q181: - | R181: - | S181: - | T181: - | U181: - | V181: - | W181: - | X181: - | Y181: - | Z181: - | AA181: - | AB181: - | AC181: - | AD181: - | AE181: - | AF181: - | AG181: - | AH181: - | AI181: - | AJ181: - | AK181: - | AL181: - | AM181: - | AN181: - | AO181: - | AP181: - | AQ181: - | AR181: - | AS181: - | AT181: - | AU181: - | AV181: - | AW181: - | AX181: - | AY181: - | AZ181: - | BA181: - | BB181: - | BC181: - | BD181: - | BE181: - | BF181: - | BG181: - | BH181: - | BI181: - | BJ181: - | BK181: - | BL181: - | BM181: - | BN181: - | BO181: - | BP181: - | BQ181: - | BR181: - | BS181: - | BT181: - | BU181: - | BV181: - | BW181: - | BX181: - | BY181: =
A182: WORLD-WIDE TOTAL | B182: =SUM(B175:B180) -> 136200 | C182: =SUM(C175:C180) -> 126511 | D182: =SUM(D175:D180) -> 122421 | E182: =SUM(E175:E180) -> 109741 | F182: =SUM(F175:F180) -> 111733 | G182: =SUM(G175:G180) -> 116452 | H182: =SUM(H175:H180) -> 119191 | I182: =SUM(I175:I180) -> 118194 | ... BY182: =SUM(BY175:BY180) -> 332825
D211: PRODUCT 1 | AA211: PRODUCT 1
D212: UNIT SALES | AA212: UNIT SALES
D213: CHINA | AA213: CHINA
B215: Q1 | C215: Q2 | D215: Q3 | E215: Q4 | F215: Q5 | G215: Q6 | H215: Q7 | I215: Q8 | J215: Q9 | K215: Q10 | L215: Q11 | M215: Q12 | N215: Q13 | O215: Q14 | P215: Q15 | Q215: Q16 | R215: Q17 | S215: Q18 | T215: Q19 | U215: Q20 | V215: Q21 | W215: Q22 | X215: Q23 | Y215: Q24 | Z215: Q25 | AA215: Q26 | AB215: Q27 | AC215: Q28 | AD215: Q29 | AE215: Q30 | AF215: Q31 | AG215: Q32 | AH215: Q33 | AI215: Q34 | AJ215: Q35 | AK215: Q36 | AL215: Q37 | AM215: Q38 | AN215: Q39 | AO215: Q40 | AP215: Q41 | AQ215: Q42 | AR215: Q43 | AS215: Q44 | AT215: Q45 | AU215: Q46 | AV215: Q47 | AW215: Q48 | AX215: Q49 | AY215: Q50 | AZ215: Q51 | BA215: Q52 | BB215: Q53 | BC215: Q54 | BD215: Q55 | BE215: Q56 | BF215: Q57 | BG215: Q58 | BH215: Q59 | BI215: Q60 | BJ215: Q61 | BK215: Q62 | BL215: Q63 | BM215: Q64 | BN215: Q65 | BO215: Q66 | BP215: Q67 | BQ215: Q68 | BR215: Q69 | BS215: Q70 | BT215: Q71 | BU215: Q72 | BV215: Q73 | BW215: Q74 | BX215: Q75 | BY215: SALES
B216: - | C216: - | D216: - | E216: - | F216: - | G216: - | H216: - | I216: - | J216: - | K216: - | L216: - | M216: - | N216: - | O216: - | P216: - | Q216: - | R216: - | S216: - | T216: - | U216: - | V216: - | W216: - | X216: - | Y216: - | Z216: - | AA216: - | AB216: - | AC216: - | BY216: =
A217: Company 1 | B217: =Data!B87 -> 16468 | C217: =Data!C87 -> 16000 | D217: =Data!D87 -> 16839 | E217: =Data!E87 -> 18573 | F217: =Data!F87 -> 17915 | G217: =Data!G87 -> 13535 | H217: =Data!H87 -> 13645 | I217: =Data!I87 -> 23436 | ... BX217: =Data!BX87 -> 0 | BY217: =SUM(BJ217:BX217) -> 42565
A218: Company 2 | B218: =Data!B88 -> 16468 | C218: =Data!C88 -> 15598 | D218: =Data!D88 -> 12666 | E218: =Data!E88 -> 15799 | F218: =Data!F88 -> 16128 | G218: =Data!G88 -> 15988 | H218: =Data!H88 -> 13122 | I218: =Data!I88 -> 11859 | ... BX218: =Data!BX88 -> 0 | BY218: =SUM(BJ218:BX218) -> 47406
A219: Company 3 | B219: =Data!B89 -> 16468 | C219: =Data!C89 -> 15845 | D219: =Data!D89 -> 15482 | E219: =Data!E89 -> 12699 | F219: =Data!F89 -> 13452 | G219: =Data!G89 -> 17418 | H219: =Data!H89 -> 17769 | I219: =Data!I89 -> 16819 | ... BX219: =Data!BX89 -> 0 | BY219: =SUM(BJ219:BX219) -> 39181
A220: Company 4 | B220: =Data!B90 -> 16468 | C220: =Data!C90 -> 15598 | D220: =Data!D90 -> 17868 | E220: =Data!E90 -> 11828 | F220: =Data!F90 -> 15002 | G220: =Data!G90 -> 17161 | H220: =Data!H90 -> 19426 | I220: =Data!I90 -> 15927 | ... BX220: =Data!BX90 -> 0 | BY220: =SUM(BJ220:BX220) -> 52589
A221: Company 5 | B221: =Data!B91 -> 16468 | C221: =Data!C91 -> 15845 | D221: =Data!D91 -> 17864 | E221: =Data!E91 -> 14252 | F221: =Data!F91 -> 12387 | G221: =Data!G91 -> 12874 | H221: =Data!H91 -> 15335 | I221: =Data!I91 -> 22517 | ... BX221: =Data!BX91 -> 0 | BY221: =SUM(BJ221:BX221) -> 41860
B223: - | C223: - | D223: - | E223: - | F223: - | G223: - | H223: - | I223: - | J223: - | K223: - | L223: - | M223: - | N223: - | O223: - | P223: - | Q223: - | R223: - | S223: - | T223: - | U223: - | V223: - | W223: - | X223: - | Y223: - | Z223: - | AA223: - | AB223: - | AC223: - | AD223: - | AE223: - | AF223: - | AG223: - | AH223: - | AI223: - | AJ223: - | AK223: - | AL223: - | AM223: - | AN223: - | AO223: - | AP223: - | AQ223: - | AR223: - | AS223: - | AT223: - | AU223: - | AV223: - | AW223: - | AX223: - | AY223: - | AZ223: - | BA223: - | BB223: - | BC223: - | BD223: - | BE223: - | BF223: - | BG223: - | BH223: - | BI223: - | BJ223: - | BK223: - | BL223: - | BM223: - | BN223: - | BO223: - | BP223: - | BQ223: - | BR223: - | BS223: - | BT223: - | BU223: - | BV223: - | BW223: - | BX223: - | BY223: =
A224: WORLD-WIDE TOTAL | B224: =SUM(B217:B222) -> 82340 | C224: =SUM(C217:C222) -> 78886 | D224: =SUM(D217:D222) -> 80719 | E224: =SUM(E217:E222) -> 73151 | F224: =SUM(F217:F222) -> 74884 | G224: =SUM(G217:G222) -> 76976 | H224: =SUM(H217:H222) -> 79297 | I224: =SUM(I217:I222) -> 90558 | ... BY224: =SUM(BY217:BY222) -> 223601
D253: PRODUCT 1 | AA253: PRODUCT 1
D254: UNIT SALES | AA254: UNIT SALES
D255: UNITED KINGDOM | AA255: UNITED KINGDOM
B257: Q1 | C257: Q2 | D257: Q3 | E257: Q4 | F257: Q5 | G257: Q6 | H257: Q7 | I257: Q8 | J257: Q9 | K257: Q10 | L257: Q11 | M257: Q12 | N257: Q13 | O257: Q14 | P257: Q15 | Q257: Q16 | R257: Q17 | S257: Q18 | T257: Q19 | U257: Q20 | V257: Q21 | W257: Q22 | X257: Q23 | Y257: Q24 | Z257: Q25 | AA257: Q26 | AB257: Q27 | AC257: Q28 | AD257: Q29 | AE257: Q30 | AF257: Q31 | AG257: Q32 | AH257: Q33 | AI257: Q34 | AJ257: Q35 | AK257: Q36 | AL257: Q37 | AM257: Q38 | AN257: Q39 | AO257: Q40 | AP257: Q41 | AQ257: Q42 | AR257: Q43 | AS257: Q44 | AT257: Q45 | AU257: Q46 | AV257: Q47 | AW257: Q48 | AX257: Q49 | AY257: Q50 | AZ257: Q51 | BA257: Q52 | BB257: Q53 | BC257: Q54 | BD257: Q55 | BE257: Q56 | BF257: Q57 | BG257: Q58 | BH257: Q59 | BI257: Q60 | BJ257: Q61 | BK257: Q62 | BL257: Q63 | BM257: Q64 | BN257: Q65 | BO257: Q66 | BP257: Q67 | BQ257: Q68 | BR257: Q69 | BS257: Q70 | BT257: Q71 | BU257: Q72 | BV257: Q73 | BW257: Q74 | BX257: Q75 | BY257: SALES
B258: - | C258: - | D258: - | E258: - | F258: - | G258: - | H258: - | I258: - | J258: - | K258: - | L258: - | M258: - | N258: - | O258: - | P258: - | Q258: - | R258: - | S258: - | T258: - | U258: - | V258: - | W258: - | X258: - | Y258: - | Z258: - | AA258: - | AB258: - | AC258: - | BY258: =
A259: Company 1 | B259: =Data!B97 -> 30636 | C259: =Data!C97 -> 28325 | D259: =Data!D97 -> 27134 | E259: =Data!E97 -> 34614 | F259: =Data!F97 -> 37378 | G259: =Data!G97 -> 27634 | H259: =Data!H97 -> 30782 | I259: =Data!I97 -> 36330 | ... BX259: =Data!BX97 -> 0 | BY259: =SUM(BJ259:BX259) -> 97831
A260: Company 2 | B260: =Data!B98 -> 30636 | C260: =Data!C98 -> 34873 | D260: =Data!D98 -> 34488 | E260: =Data!E98 -> 40055 | F260: =Data!F98 -> 43704 | G260: =Data!G98 -> 40701 | H260: =Data!H98 -> 28891 | I260: =Data!I98 -> 26049 | ... BX260: =Data!BX98 -> 0 | BY260: =SUM(BJ260:BX260) -> 104960
A261: Company 3 | B261: =Data!B99 -> 30636 | C261: =Data!C99 -> 27981 | D261: =Data!D99 -> 24909 | E261: =Data!E99 -> 23499 | F261: =Data!F99 -> 27905 | G261: =Data!G99 -> 35414 | H261: =Data!H99 -> 39960 | I261: =Data!I99 -> 26010 | ... BX261: =Data!BX99 -> 0 | BY261: =SUM(BJ261:BX261) -> 94227
A262: Company 4 | B262: =Data!B100 -> 30636 | C262: =Data!C100 -> 33784 | D262: =Data!D100 -> 34042 | E262: =Data!E100 -> 27899 | F262: =Data!F100 -> 26053 | G262: =Data!G100 -> 28084 | H262: =Data!H100 -> 31833 | I262: =Data!I100 -> 34957 | ... BX262: =Data!BX100 -> 0 | BY262: =SUM(BJ262:BX262) -> 103346
A263: Company 5 | B263: =Data!B101 -> 30636 | C263: =Data!C101 -> 27981 | D263: =Data!D101 -> 28741 | E263: =Data!E101 -> 26373 | F263: =Data!F101 -> 25696 | G263: =Data!G101 -> 26175 | H263: =Data!H101 -> 34337 | I263: =Data!I101 -> 35633 | ... BX263: =Data!BX101 -> 0 | BY263: =SUM(BJ263:BX263) -> 95042
B265: - | C265: - | D265: - | E265: - | F265: - | G265: - | H265: - | I265: - | J265: - | K265: - | L265: - | M265: - | N265: - | O265: - | P265: - | Q265: - | R265: - | S265: - | T265: - | U265: - | V265: - | W265: - | X265: - | Y265: - | Z265: - | AA265: - | AB265: - | AC265: - | AD265: - | AE265: - | AF265: - | AG265: - | AH265: - | AI265: - | AJ265: - | AK265: - | AL265: - | AM265: - | AN265: - | AO265: - | AP265: - | AQ265: - | AR265: - | AS265: - | AT265: - | AU265: - | AV265: - | AW265: - | AX265: - | AY265: - | AZ265: - | BA265: - | BB265: - | BC265: - | BD265: - | BE265: - | BF265: - | BG265: - | BH265: - | BI265: - | BJ265: - | BK265: - | BL265: - | BM265: - | BN265: - | BO265: - | BP265: - | BQ265: - | BR265: - | BS265: - | BT265: - | BU265: - | BV265: - | BW265: - | BX265: - | BY265: =
A266: WORLD-WIDE TOTAL | B266: =SUM(B259:B264) -> 153180 | C266: =SUM(C259:C264) -> 152944 | D266: =SUM(D259:D264) -> 149314 | E266: =SUM(E259:E264) -> 152440 | F266: =SUM(F259:F264) -> 160736 | G266: =SUM(G259:G264) -> 158008 | H266: =SUM(H259:H264) -> 165803 | I266: =SUM(I259:I264) -> 158979 | ... BY266: =SUM(BY259:BY264) -> 495406
D295: PRODUCT 1 | AA295: PRODUCT 1
D296: UNIT SALES | AA296: UNIT SALES
D297: GERMANY | AA297: GERMANY
B299: Q1 | C299: Q2 | D299: Q3 | E299: Q4 | F299: Q5 | G299: Q6 | H299: Q7 | I299: Q8 | J299: Q9 | K299: Q10 | L299: Q11 | M299: Q12 | N299: Q13 | O299: Q14 | P299: Q15 | Q299: Q16 | R299: Q17 | S299: Q18 | T299: Q19 | U299: Q20 | V299: Q21 | W299: Q22 | X299: Q23 | Y299: Q24 | Z299: Q25 | AA299: Q26 | AB299: Q27 | AC299: Q28 | AD299: Q29 | AE299: Q30 | AF299: Q31 | AG299: Q32 | AH299: Q33 | AI299: Q34 | AJ299: Q35 | AK299: Q36 | AL299: Q37 | AM299: Q38 | AN299: Q39 | AO299: Q40 | AP299: Q41 | AQ299: Q42 | AR299: Q43 | AS299: Q44 | AT299: Q45 | AU299: Q46 | AV299: Q47 | AW299: Q48 | AX299: Q49 | AY299: Q50 | AZ299: Q51 | BA299: Q52 | BB299: Q53 | BC299: Q54 | BD299: Q55 | BE299: Q56 | BF299: Q57 | BG299: Q58 | BH299: Q59 | BI299: Q60 | BJ299: Q61 | BK299: Q62 | BL299: Q63 | BM299: Q64 | BN299: Q65 | BO299: Q66 | BP299: Q67 | BQ299: Q68 | BR299: Q69 | BS299: Q70 | BT299: Q71 | BU299: Q72 | BV299: Q73 | BW299: Q74 | BX299: Q75 | BY299: SALES
B300: - | C300: - | D300: - | E300: - | F300: - | G300: - | H300: - | I300: - | J300: - | K300: - | L300: - | M300: - | N300: - | O300: - | P300: - | Q300: - | R300: - | S300: - | T300: - | U300: - | V300: - | W300: - | X300: - | Y300: - | Z300: - | AA300: - | AB300: - | AC300: - | BY300: =
A301: Company 1 | B301: =Data!B107 -> 38279 | C301: =Data!C107 -> 35903 | D301: =Data!D107 -> 35509 | E301: =Data!E107 -> 44243 | F301: =Data!F107 -> 45560 | G301: =Data!G107 -> 32868 | H301: =Data!H107 -> 34330 | I301: =Data!I107 -> 39768 | ... BX301: =Data!BX107 -> 0 | BY301: =SUM(BJ301:BX301) -> 106188
A302: Company 2 | B302: =Data!B108 -> 38279 | C302: =Data!C108 -> 46797 | D302: =Data!D108 -> 38533 | E302: =Data!E108 -> 48129 | F302: =Data!F108 -> 52353 | G302: =Data!G108 -> 49963 | H302: =Data!H108 -> 38913 | I302: =Data!I108 -> 30279 | ... BX302: =Data!BX108 -> 0 | BY302: =SUM(BJ302:BX302) -> 111237
A303: Company 3 | B303: =Data!B109 -> 38279 | C303: =Data!C109 -> 35355 | D303: =Data!D109 -> 32577 | E303: =Data!E109 -> 30033 | F303: =Data!F109 -> 33839 | G303: =Data!G109 -> 41957 | H303: =Data!H109 -> 44441 | I303: =Data!I109 -> 28421 | ... BX303: =Data!BX109 -> 0 | BY303: =SUM(BJ303:BX303) -> 103984
A304: Company 4 | B304: =Data!B110 -> 38279 | C304: =Data!C110 -> 46797 | D304: =Data!D110 -> 42320 | E304: =Data!E110 -> 37806 | F304: =Data!F110 -> 38062 | G304: =Data!G110 -> 41933 | H304: =Data!H110 -> 48111 | I304: =Data!I110 -> 40624 | ... BX304: =Data!BX110 -> 0 | BY304: =SUM(BJ304:BX304) -> 108080
A305: Company 5 | B305: =Data!B111 -> 38279 | C305: =Data!C111 -> 35355 | D305: =Data!D111 -> 37589 | E305: =Data!E111 -> 33706 | F305: =Data!F111 -> 31160 | G305: =Data!G111 -> 31011 | H305: =Data!H111 -> 40221 | I305: =Data!I111 -> 39605 | ... BX305: =Data!BX111 -> 0 | BY305: =SUM(BJ305:BX305) -> 112520
B307: - | C307: - | D307: - | E307: - | F307: - | G307: - | H307: - | I307: - | J307: - | K307: - | L307: - | M307: - | N307: - | O307: - | P307: - | Q307: - | R307: - | S307: - | T307: - | U307: - | V307: - | W307: - | X307: - | Y307: - | Z307: - | AA307: - | AB307: - | AC307: - | AD307: - | AE307: - | AF307: - | AG307: - | AH307: - | AI307: - | AJ307: - | AK307: - | AL307: - | AM307: - | AN307: - | AO307: - | AP307: - | AQ307: - | AR307: - | AS307: - | AT307: - | AU307: - | AV307: - | AW307: - | AX307: - | AY307: - | AZ307: - | BA307: - | BB307: - | BC307: - | BD307: - | BE307: - | BF307: - | BG307: - | BH307: - | BI307: - | BJ307: - | BK307: - | BL307: - | BM307: - | BN307: - | BO307: - | BP307: - | BQ307: - | BR307: - | BS307: - | BT307: - | BU307: - | BV307: - | BW307: - | BX307: - | BY307: =
A308: WORLD-WIDE TOTAL | B308: =SUM(B301:B306) -> 191395 | C308: =SUM(C301:C306) -> 200207 | D308: =SUM(D301:D306) -> 186528 | E308: =SUM(E301:E306) -> 193917 | F308: =SUM(F301:F306) -> 200974 | G308: =SUM(G301:G306) -> 197732 | H308: =SUM(H301:H306) -> 206016 | I308: =SUM(I301:I306) -> 178697 | ... BY308: =SUM(BY301:BY306) -> 542009
D336: PRODUCT 1
D337: UNIT SALES | AA337: PRODUCT 1
D338: UNITED STATES | AA338: UNIT SALES
AA339: UNITED STATES
B341: Q1 | C341: Q2 | D341: Q3 | E341: Q4 | F341: Q5 | G341: Q6 | H341: Q7 | I341: Q8 | J341: Q9 | K341: Q10 | L341: Q11 | M341: Q12 | N341: Q13 | O341: Q14 | P341: Q15 | Q341: Q16 | R341: Q17 | S341: Q18 | T341: Q19 | U341: Q20 | V341: Q21 | W341: Q22 | X341: Q23 | Y341: Q24 | Z341: Q25 | AA341: Q26 | AB341: Q27 | AC341: Q28 | AD341: Q29 | AE341: Q30 | AF341: Q31 | AG341: Q32 | AH341: Q33 | AI341: Q34 | AJ341: Q35 | AK341: Q36 | AL341: Q37 | AM341: Q38 | AN341: Q39 | AO341: Q40 | AP341: Q41 | AQ341: Q42 | AR341: Q43 | AS341: Q44 | AT341: Q45 | AU341: Q46 | AV341: Q47 | AW341: Q48 | AX341: Q49 | AY341: Q50 | AZ341: Q51 | BA341: Q52 | BB341: Q53 | BC341: Q54 | BD341: Q55 | BE341: Q56 | BF341: Q57 | BG341: Q58 | BH341: Q59 | BI341: Q60 | BJ341: Q61 | BK341: Q62 | BL341: Q63 | BM341: Q64 | BN341: Q65 | BO341: Q66 | BP341: Q67 | BQ341: Q68 | BR341: Q69 | BS341: Q70 | BT341: Q71 | BU341: Q72 | BV341: Q73 | BW341: Q74 | BX341: Q75 | BY341: SALES
B342: - | C342: - | D342: - | E342: - | F342: - | G342: - | H342: - | I342: - | J342: - | K342: - | L342: - | M342: - | N342: - | O342: - | P342: - | Q342: - | R342: - | S342: - | T342: - | U342: - | V342: - | W342: - | X342: - | Y342: - | Z342: - | AA342: - | AB342: - | AC342: - | BY342: =
...

Sheet InputHistory
A1: ='[3]TEAM 1'!A1 -> INPUT FOR - TEAM 1 | B1: ='[3]TEAM 1'!B1 -> Units | C1: ='[3]TEAM 1'!C1 -> Period 1 | D1: ='[3]TEAM 1'!D1 -> Period 2 | E1: ='[3]TEAM 1'!E1 -> Period 3 | F1: ='[3]TEAM 1'!F1 -> Period 4 | G1: ='[3]TEAM 1'!G1 -> Period 5 | H1: ='[3]TEAM 1'!H1 -> Period 6 | ... BY1: ='[3]TEAM 1'!BY1 -> Period 75
A2: ='[3]TEAM 1'!A2 -> Price in Japan, Product 1 | B2: ='[3]TEAM 1'!B2 -> Yen | C2: ='[3]TEAM 1'!C2 -> 4300 | D2: ='[3]TEAM 1'!D2 -> 4050 | E2: ='[3]TEAM 1'!E2 -> 4050 | F2: ='[3]TEAM 1'!F2 -> 3780 | G2: ='[3]TEAM 1'!G2 -> 3780 | H2: ='[3]TEAM 1'!H2 -> 3780 | ... BY2: ='[3]TEAM 1'!BY2 -> 0
A3: ='[3]TEAM 1'!A3 -> Price in Mexico, Product 1 | B3: ='[3]TEAM 1'!B3 -> Peso | C3: ='[3]TEAM 1'!C3 -> 450 | D3: ='[3]TEAM 1'!D3 -> 414 | E3: ='[3]TEAM 1'!E3 -> 382.5 | F3: ='[3]TEAM 1'!F3 -> 382.5 | G3: ='[3]TEAM 1'!G3 -> 382.5 | H3: ='[3]TEAM 1'!H3 -> 382.5 | ... BY3: ='[3]TEAM 1'!BY3 -> 0
A4: ='[3]TEAM 1'!A4 -> Price in China, Product 1 | B4: ='[3]TEAM 1'!B4 -> Yuan | C4: ='[3]TEAM 1'!C4 -> 400 | D4: ='[3]TEAM 1'!D4 -> 378 | E4: ='[3]TEAM 1'!E4 -> 360 | F4: ='[3]TEAM 1'!F4 -> 360 | G4: ='[3]TEAM 1'!G4 -> 360 | H4: ='[3]TEAM 1'!H4 -> 360 | ... BY4: ='[3]TEAM 1'!BY4 -> 0
A5: ='[3]TEAM 1'!A5 -> Price in U.K., Product 1 | B5: ='[3]TEAM 1'!B5 -> Pound | C5: ='[3]TEAM 1'!C5 -> 36 | D5: ='[3]TEAM 1'!D5 -> 32.4 | E5: ='[3]TEAM 1'!E5 -> 31.5 | F5: ='[3]TEAM 1'!F5 -> 28.8 | G5: ='[3]TEAM 1'!G5 -> 28.8 | H5: ='[3]TEAM 1'!H5 -> 28.8 | ... BY5: ='[3]TEAM 1'!BY5 -> 0
A6: ='[3]TEAM 1'!A6 -> Price in Germany, Product 1 | B6: ='[3]TEAM 1'!B6 -> Euro | C6: ='[3]TEAM 1'!C6 -> 49 | D6: ='[3]TEAM 1'!D6 -> 44.1 | E6: ='[3]TEAM 1'!E6 -> 42.3 | F6: ='[3]TEAM 1'!F6 -> 40.5 | G6: ='[3]TEAM 1'!G6 -> 40.5 | H6: ='[3]TEAM 1'!H6 -> 40.5 | ... BY6: ='[3]TEAM 1'!BY6 -> 0
A7: ='[3]TEAM 1'!A7 -> Price in U.S., Product 1 | B7: ='[3]TEAM 1'!B7 -> USD | C7: ='[3]TEAM 1'!C7 -> 50 | D7: ='[3]TEAM 1'!D7 -> 44.1 | E7: ='[3]TEAM 1'!E7 -> 43.2 | F7: ='[3]TEAM 1'!F7 -> 41.4 | G7: ='[3]TEAM 1'!G7 -> 41.4 | H7: ='[3]TEAM 1'!H7 -> 41.4 | ... BY7: ='[3]TEAM 1'!BY7 -> 0
A8: ='[3]TEAM 1'!A8 -> Price in Japan, Product 2 | B8: ='[3]TEAM 1'!B8 -> Yen | C8: ='[3]TEAM 1'!C8 -> 6200 | D8: ='[3]TEAM 1'!D8 -> 5850 | E8: ='[3]TEAM 1'!E8 -> 6300 | F8: ='[3]TEAM 1'!F8 -> 5850 | G8: ='[3]TEAM 1'!G8 -> 5850 | H8: ='[3]TEAM 1'!H8 -> 5850 | ... BY8: ='[3]TEAM 1'!BY8 -> 0
A9: ='[3]TEAM 1'!A9 -> Price in Mexico, Product 2 | B9: ='[3]TEAM 1'!B9 -> Peso | C9: ='[3]TEAM 1'!C9 -> 650 | D9: ='[3]TEAM 1'!D9 -> 540 | E9: ='[3]TEAM 1'!E9 -> 540 | F9: ='[3]TEAM 1'!F9 -> 495 | G9: ='[3]TEAM 1'!G9 -> 495 | H9: ='[3]TEAM 1'!H9 -> 495 | ... BY9: ='[3]TEAM 1'!BY9 -> 0
A10: ='[3]TEAM 1'!A10 -> Price in China, Product 2 | B10: ='[3]TEAM 1'!B10 -> Yuan | C10: ='[3]TEAM 1'!C10 -> 550 | D10: ='[3]TEAM 1'!D10 -> 450 | E10: ='[3]TEAM 1'!E10 -> 504 | F10: ='[3]TEAM 1'!F10 -> 472.5 | G10: ='[3]TEAM 1'!G10 -> 472.5 | H10: ='[3]TEAM 1'!H10 -> 472.5 | ... BY10: ='[3]TEAM 1'!BY10 -> 0
A11: ='[3]TEAM 1'!A11 -> Price in U.K., Product 2 | B11: ='[3]TEAM 1'!B11 -> Pound | C11: ='[3]TEAM 1'!C11 -> 46 | D11: ='[3]TEAM 1'!D11 -> 36.9 | E11: ='[3]TEAM 1'!E11 -> 39.6 | F11: ='[3]TEAM 1'!F11 -> 39.6 | G11: ='[3]TEAM 1'!G11 -> 39.6 | H11: ='[3]TEAM 1'!H11 -> 39.6 | ... BY11: ='[3]TEAM 1'!BY11 -> 0
A12: ='[3]TEAM 1'!A12 -> Price in Germany, Product 2 | B12: ='[3]TEAM 1'!B12 -> Euro | C12: ='[3]TEAM 1'!C12 -> 60 | D12: ='[3]TEAM 1'!D12 -> 49.5 | E12: ='[3]TEAM 1'!E12 -> 54 | F12: ='[3]TEAM 1'!F12 -> 54.9 | G12: ='[3]TEAM 1'!G12 -> 54.9 | H12: ='[3]TEAM 1'!H12 -> 54.9 | ... BY12: ='[3]TEAM 1'!BY12 -> 0
... A82: ='[3]TEAM 1'!A82 -> Sell Currency Forward Contract, Yuan | B82: ='[3]TEAM 1'!B82 -> 000,000 Yuan | C82: ='[3]TEAM 1'!C82 -> 0 | D82: ='[3]TEAM 1'!D82 -> 0 | E82: ='[3]TEAM 1'!E82 -> 2 | F82: ='[3]TEAM 1'!F82 -> 2 | G82: ='[3]TEAM 1'!G82 -> 2 | H82: ='[3]TEAM 1'!H82 -> 2 | ... BY82: ='[3]TEAM 1'!BY82 -> 0
A83: GreenP1 | B83: 000 USD | C83: ='[3]TEAM 1'!C83 -> 0 | D83: ='[3]TEAM 1'!D83 -> 0 | E83: ='[3]TEAM 1'!E83 -> 1 | F83: ='[3]TEAM 1'!F83 -> 1 | G83: ='[3]TEAM 1'!G83 -> 1 | H83: ='[3]TEAM 1'!H83 -> 1 | I83: ='[3]TEAM 1'!I83 -> 1 | J83: ='[3]TEAM 1'!J83 -> 1 | ... BY83: ='[3]TEAM 1'!BY83 -> 0
A84: GreenP2 | B84: 000 USD | C84: ='[3]TEAM 1'!C84 -> 0 | D84: ='[3]TEAM 1'!D84 -> 0 | E84: ='[3]TEAM 1'!E84 -> 1 | F84: ='[3]TEAM 1'!F84 -> 1 | G84: ='[3]TEAM 1'!G84 -> 1 | H84: ='[3]TEAM 1'!H84 -> 1 | I84: ='[3]TEAM 1'!I84 -> 1 | J84: ='[3]TEAM 1'!J84 -> 1 | ... BY84: ='[3]TEAM 1'!BY84 -> 0

Sheet P0
C1: OUTPUT PERIOD 1
A2: 1 | B2: JAPAN | C2: MEXICO | D2: CHINA | E2: U.K. | F2: GERMAN | G2: U.S. | H2: TOTAL
A3: Demand - Units P1 | B3: 274090 | C3: 184335 | D3: 104550 | E3: 155510 | F3: 126340 | G3: 372385 | H3: 1217210 | I3: 0 | J3: 0 | K3: 0
A4: Sales - Units P1 | B4: 274090 | C4: 184335 | D4: 104550 | E4: 155510 | F4: 126340 | G4: 372385 | H4: 1217210 | I4: 0 | J4: 0 | K4: 0
A5: Domestic Units sold P1 | B5: 274090 | C5: 0 | D5: 0 | E5: 0 | F5: 0 | G5: 0 | H5: 0 | I5: 0 | J5: 0 | K5: 0
A6: Imported Units sold P1 | B6: 0 | C6: 184335 | D6: 104550 | E6: 155510 | F6: 126340 | G6: 372385 | H6: 0 | I6: 0 | J6: 0 | K6: 0
A7: Exported units P1 | B7: 943120 | C7: 0 | D7: 0 | E7: 0 | F7: 0 | G7: 0 | H7: 0 | I7: 0 | J7: 0 | K7: 0
A8: Demand - Units P2 | B8: 232685 | C8: 144010 | D8: 70710 | E8: 132335 | F8: 107765 | G8: 323970 | H8: 1011475 | I8: 0 | J8: 0 | K8: 0
A9: Sales - Units P2 | B9: 232685 | C9: 144010 | D9: 70710 | E9: 132335 | F9: 107765 | G9: 323970 | H9: 1011475 | I9: 0 | J9: 0 | K9: 0
A10: Domestic Units sold P2 | B10: 0 | C10: 0 | D10: 0 | E10: 0 | F10: 64659 | G10: 129588 | H10: 0 | I10: 0 | J10: 0 | K10: 0
A11: Imported Units sold P2 | B11: 232685 | C11: 144010 | D11: 70710 | E11: 132335 | F11: 43106 | G11: 194382 | H11: 0 | I11: 0 | J11: 0 | K11: 0
A12: Exported units P2 | B12: 0 | C12: 0 | D12: 0 | E12: 0 | F12: 542226 | G12: 275002 | H12: 0 | I12: 0 | J12: 0 | K12: 0
A13: Price company 1 P1 | B13: 4500 | C13: 243 | D13: 382.5 | E13: 29.25 | F13: 68.65 | G13: 45 | H13: 0 | I13: 0 | J13: 0 | K13: 0
A14: Price company 2 P1 | B14: 4500 | C14: 243 | D14: 382.5 | E14: 29.25 | F14: 68.65 | G14: 45 | H14: 0 | I14: 0 | J14: 0 | K14: 0
... A51: Inflation Rates | B51: 4.8 | C51: 2.5462366 | D51: 7.3253012 | E51: 6.3188406 | F51: 4.8 | G51: 4.8 | H51: 0 | I51: 0 | J51: 0 | K51: 0
A52: Cash and Securities | B52: =2696892-696215 -> 2000677 | C52: 2696892 | D52: 2696892 | E52: 2696892 | F52: 2696892 | G52: 0 | H52: 0 | I52: 0 | J52: 0 | K52: 0
A53: Receivables | B53: 12000000 | C53: 12000000 | D53: 12000000 | E53: 12000000 | F53: 12000000 | G53: 0 | H53: 0 | I53: 0 | J53: 0 | K53: 0
A54: Inventory P1 | B54: 934826 | C54: 934826 | D54: 934826 | E54: 934826 | F54: 934826 | G54: 0 | H54: 0 | I54: 0 | J54: 0 | K54: 0
A55: Inventory P2 | B55: 2634970 | C55: 2587409 | D55: 2634970 | E55: 2634970 | F55: 2587409 | G55: 0 | H55: 0 | I55: 0 | J55: 0 | K55: 0
A56: Total Inventory val | B56: 4386978 | C56: 4386978 | D56: 4386978 | E56: 4386978 | F56: 4386978 | G56: 0 | H56: 0 | I56: 0 | J56: 0 | K56: 0
A57: Ship Containers Net | B57: 1342624 | C57: 1342624 | D57: 1342624 | E57: 1342624 | F57: 1342624 | G57: 0 | H57: 0 | I57: 0 | J57: 0 | K57: 0
A58: Factory 1 Net | B58: 5576582 | C58: 5576582 | D58: 5576582 | E58: 5576582 | F58: 5576582 | G58: 0 | H58: 0 | I58: 0 | J58: 0 | K58: 0
A59: Factory 2 Net | B59: 5364270 | C59: 4460707 | D59: 5364270 | E59: 5364270 | F59: 4460707 | G59: 0 | H59: 0 | I59: 0 | J59: 0 | K59: 0
A60: Total Factory net | B60: 10940852 | C60: 10037289 | D60: 10940852 | E60: 10940852 | F60: 10037289 | G60: 0 | H60: 0 | I60: 0 | J60: 0 | K60: 0
A61: Total Assets | B61: 34288738 | C61: 34239157 | D61: 34288738 | E61: 34288738 | F61: 34239157 | G61: 0 | H61: 0 | I61: 0 | J61: 0 | K61: 0
A62: Trade Payables | B62: 5000000 | C62: 5000000 | D62: 5000000 | E62: 5000000 | F62: 5000000 | G62: 0 | H62: 0 | I62: 0 | J62: 0 | K62: 0
A63: Taxes Payable | B63: 0 | C63: 0 | D63: 0 | E63: 0 | F63: 0 | G63: 0 | H63: 0 | I63: 0 | J63: 0 | K63: 0
A64: Loans Outstanding | B64: 4149437 | C64: 4149437 | D64: 4149437 | E64: 4149437 | F64: 4149437 | G64: 0 | H64: 0 | I64: 0 | J64: 0 | K64: 0
... A77: New Plant capacity P2 | B77: 0 | C77: 0 | D77: 0 | E77: 0 | F77: 0 | G77: 0 | H77: 0 | I77: 0 | J77: 0 | K77: 0
A78: COMPANY DATA | B78: 3
A79: Contract Vol Demand | B79: 40000
A80: Total cont Vol Sold | B80: 40000
A81: Contract Price | B81: 40
A82: Contract units sold | B82: 8000
A83: Contract sales dollars | B83: 320000
A84: Contract unit cost | B84: 35.006775
A85: Demand Units Japan P1 | B85: 54818
A86: Demand Units Mexico P1 | B86: 36867
A87: Demand Units China P1 | B87: 20910
A88: Demand Units UK P1 | B88: 31102
A89: Demand Units German P1 | B89: 25268
... A259: Number of companies Play | B259: 5

Sheet P1
C1: OUTPUT PERIOD 1
A2: 1 | B2: JAPAN | C2: MEXICO | D2: CHINA | E2: U.K. | F2: GERMAN | G2: U.S. | H2: TOTAL
A3: Demand - Units P1 | B3: =[4]p01!B3 -> 241745 | C3: =[4]p01!C3 -> 136200 | D3: =[4]p01!D3 -> 82340 | E3: =[4]p01!E3 -> 153180 | F3: =[4]p01!F3 -> 191395 | G3: =[4]p01!G3 -> 418415 | H3: =[4]p01!H3 -> 1223275 | I3: =[4]p01!I3 -> 0 | ... K3: =[4]p01!K3 -> 0
A4: Sales - Units P1 | B4: =[4]p01!B4 -> 241745 | C4: =[4]p01!C4 -> 136200 | D4: =[4]p01!D4 -> 82340 | E4: =[4]p01!E4 -> 153180 | F4: =[4]p01!F4 -> 191395 | G4: =[4]p01!G4 -> 418415 | H4: =[4]p01!H4 -> 1223275 | I4: =[4]p01!I4 -> 0 | ... K4: =[4]p01!K4 -> 0
A5: Domestic Units sold P1 | B5: =[4]p01!B5 -> 0 | C5: =[4]p01!C5 -> 0 | D5: =[4]p01!D5 -> 82340 | E5: =[4]p01!E5 -> 0 | F5: =[4]p01!F5 -> 0 | G5: =[4]p01!G5 -> 0 | H5: =[4]p01!H5 -> 0 | I5: =[4]p01!I5 -> 0 | ... K5: =[4]p01!K5 -> 0
A6: Imported Units sold P1 | B6: =[4]p01!B6 -> 241745 | C6: =[4]p01!C6 -> 136200 | D6: =[4]p01!D6 -> 0 | E6: =[4]p01!E6 -> 153180 | F6: =[4]p01!F6 -> 191395 | G6: =[4]p01!G6 -> 418415 | H6: =[4]p01!H6 -> 0 | I6: =[4]p01!I6 -> 0 | ... K6: =[4]p01!K6 -> 0
A7: Exported units P1 | B7: =[4]p01!B7 -> 0 | C7: =[4]p01!C7 -> 0 | D7: =[4]p01!D7 -> 1140935 | E7: =[4]p01!E7 -> 0 | F7: =[4]p01!F7 -> 0 | G7: =[4]p01!G7 -> 0 | H7: =[4]p01!H7 -> 0 | I7: =[4]p01!I7 -> 0 | ... K7: =[4]p01!K7 -> 0
A8: Demand - Units P2 | B8: =[4]p01!B8 -> 223760 | C8: =[4]p01!C8 -> 126560 | D8: =[4]p01!D8 -> 80470 | E8: =[4]p01!E8 -> 160115 | F8: =[4]p01!F8 -> 210975 | G8: =[4]p01!G8 -> 412370 | H8: =[4]p01!H8 -> 1214250 | I8: =[4]p01!I8 -> 0 | ... K8: =[4]p01!K8 -> 0
A9: Sales - Units P2 | B9: =[4]p01!B9 -> 223760 | C9: =[4]p01!C9 -> 126560 | D9: =[4]p01!D9 -> 80470 | E9: =[4]p01!E9 -> 160115 | F9: =[4]p01!F9 -> 210975 | G9: =[4]p01!G9 -> 412370 | H9: =[4]p01!H9 -> 1214250 | I9: =[4]p01!I9 -> 0 | ... K9: =[4]p01!K9 -> 0
A10: Domestic Units sold P2 | B10: =[4]p01!B10 -> 0 | C10: =[4]p01!C10 -> 0 | D10: =[4]p01!D10 -> 0 | E10: =[4]p01!E10 -> 0 | F10: =[4]p01!F10 -> 0 | G10: =[4]p01!G10 -> 412370 | H10: =[4]p01!H10 -> 0 | I10: =[4]p01!I10 -> 0 | ... K10: =[4]p01!K10 -> 0
A11: Imported Units sold P2 | B11: =[4]p01!B11 -> 223760 | C11: =[4]p01!C11 -> 126560 | D11: =[4]p01!D11 -> 80470 | E11: =[4]p01!E11 -> 160115 | F11: =[4]p01!F11 -> 210975 | G11: =[4]p01!G11 -> 0 | H11: =[4]p01!H11 -> 0 | I11: =[4]p01!I11 -> 0 | ... K11: =[4]p01!K11 -> 0
A12: Exported units P2 | B12: =[4]p01!B12 -> 0 | C12: =[4]p01!C12 -> 0 | D12: =[4]p01!D12 -> 0 | E12: =[4]p01!E12 -> 0 | F12: =[4]p01!F12 -> 0 | G12: =[4]p01!G12 -> 801880 | H12: =[4]p01!H12 -> 0 | I12: =[4]p01!I12 -> 0 | ... K12: =[4]p01!K12 -> 0
A13: Price company 1 P1 | B13: =[4]p01!B13 -> 4300 | C13: =[4]p01!C13 -> 450 | D13: =[4]p01!D13 -> 400 | E13: =[4]p01!E13 -> 36 | F13: =[4]p01!F13 -> 49 | G13: =[4]p01!G13 -> 50 | H13: =[4]p01!H13 -> 0 | I13: =[4]p01!I13 -> 0 | ... K13: =[4]p01!K13 -> 0
A14: Price company 2 P1 | B14: =[4]p01!B14 -> 4300 | C14: =[4]p01!C14 -> 450 | D14: =[4]p01!D14 -> 400 | E14: =[4]p01!E14 -> 36 | F14: =[4]p01!F14 -> 49 | G14: =[4]p01!G14 -> 50 | H14: =[4]p01!H14 -> 0 | I14: =[4]p01!I14 -> 0 | ... K14: =[4]p01!K14 -> 0
... A77: New Plant capacity P2 | B77: =[4]p01!B77 -> 0 | C77: =[4]p01!C77 -> 0 | D77: =[4]p01!D77 -> 0 | E77: =[4]p01!E77 -> 0 | F77: =[4]p01!F77 -> 0 | G77: =[4]p01!G77 -> 0 | H77: =[4]p01!H77 -> 0 | I77: =[4]p01!I77 -> 0 | ... K77: =[4]p01!K77 -> 0
A78: COMPANY DATA | B78: =[4]p01!B78 -> 1
A79: Contract Vol Demand | B79: =[4]p01!B79 -> 40000
A80: Total cont Vol Sold | B80: =[4]p01!B80 -> 40000
A81: Contract Price | B81: =[4]p01!B81 -> 0
A82: Contract units sold | B82: =[4]p01!B82 -> 0
A83: Contract sales dollars | B83: =[4]p01!B83 -> 0
A84: Contract unit cost | B84: =[4]p01!B84 -> 0
A85: Demand Units Japan P1 | B85: =[4]p01!B85 -> 48349
A86: Demand Units Mexico P1 | B86: =[4]p01!B86 -> 27240
A87: Demand Units China P1 | B87: =[4]p01!B87 -> 16468
A88: Demand Units UK P1 | B88: =[4]p01!B88 -> 30636
A89: Demand Units German P1 | B89: =[4]p01!B89 -> 38279
... A291: Return on Invested Capital | B291: =[4]p01!B291 -> 0.51529752

Sheet P2
C1: OUTPUT PERIOD 2
A2: 2 | B2: JAPAN | C2: MEXICO | D2: CHINA | E2: U.K. | F2: GERMAN | G2: U.S. | H2: TOTAL
A3: Demand - Units P1 | B3: =[4]p02!B3 -> 225257 | C3: =[4]p02!C3 -> 126511 | D3: =[4]p02!D3 -> 78886 | E3: =[4]p02!E3 -> 152944 | F3: =[4]p02!F3 -> 200207 | G3: =[4]p02!G3 -> 437859 | H3: =[4]p02!H3 -> 1221664 | I3: =[4]p02!I3 -> 0 | ... K3: =[4]p02!K3 -> 0
A4: Sales - Units P1 | B4: =[4]p02!B4 -> 225257 | C4: =[4]p02!C4 -> 126511 | D4: =[4]p02!D4 -> 78886 | E4: =[4]p02!E4 -> 152944 | F4: =[4]p02!F4 -> 200207 | G4: =[4]p02!G4 -> 437859 | H4: =[4]p02!H4 -> 1221664 | I4: =[4]p02!I4 -> 0 | ... K4: =[4]p02!K4 -> 0
A5: Domestic Units sold P1 | B5: =[4]p02!B5 -> 0 | C5: =[4]p02!C5 -> 0 | D5: =[4]p02!D5 -> 78886 | E5: =[4]p02!E5 -> 0 | F5: =[4]p02!F5 -> 0 | G5: =[4]p02!G5 -> 0 | H5: =[4]p02!H5 -> 0 | I5: =[4]p02!I5 -> 0 | ... K5: =[4]p02!K5 -> 0
A6: Imported Units sold P1 | B6: =[4]p02!B6 -> 225257 | C6: =[4]p02!C6 -> 126511 | D6: =[4]p02!D6 -> 0 | E6: =[4]p02!E6 -> 152944 | F6: =[4]p02!F6 -> 200207 | G6: =[4]p02!G6 -> 437859 | H6: =[4]p02!H6 -> 0 | I6: =[4]p02!I6 -> 0 | ... K6: =[4]p02!K6 -> 0
A7: Exported units P1 | B7: =[4]p02!B7 -> 0 | C7: =[4]p02!C7 -> 0 | D7: =[4]p02!D7 -> 1142778 | E7: =[4]p02!E7 -> 0 | F7: =[4]p02!F7 -> 0 | G7: =[4]p02!G7 -> 0 | H7: =[4]p02!H7 -> 0 | I7: =[4]p02!I7 -> 0 | ... K7: =[4]p02!K7 -> 0
A8: Demand - Units P2 | B8: =[4]p02!B8 -> 199296 | C8: =[4]p02!C8 -> 132781 | D8: =[4]p02!D8 -> 86257 | E8: =[4]p02!E8 -> 159048 | F8: =[4]p02!F8 -> 205077 | G8: =[4]p02!G8 -> 439554 | H8: =[4]p02!H8 -> 1222013 | I8: =[4]p02!I8 -> 0 | ... K8: =[4]p02!K8 -> 0
A9: Sales - Units P2 | B9: =[4]p02!B9 -> 199296 | C9: =[4]p02!C9 -> 132781 | D9: =[4]p02!D9 -> 86257 | E9: =[4]p02!E9 -> 159048 | F9: =[4]p02!F9 -> 205077 | G9: =[4]p02!G9 -> 439554 | H9: =[4]p02!H9 -> 1222013 | I9: =[4]p02!I9 -> 0 | ... K9: =[4]p02!K9 -> 0
A10: Domestic Units sold P2 | B10: =[4]p02!B10 -> 0 | C10: =[4]p02!C10 -> 0 | D10: =[4]p02!D10 -> 0 | E10: =[4]p02!E10 -> 0 | F10: =[4]p02!F10 -> 0 | G10: =[4]p02!G10 -> 439554 | H10: =[4]p02!H10 -> 0 | I10: =[4]p02!I10 -> 0 | ... K10: =[4]p02!K10 -> 0
A11: Imported Units sold P2 | B11: =[4]p02!B11 -> 199296 | C11: =[4]p02!C11 -> 132781 | D11: =[4]p02!D11 -> 86257 | E11: =[4]p02!E11 -> 159048 | F11: =[4]p02!F11 -> 205077 | G11: =[4]p02!G11 -> 0 | H11: =[4]p02!H11 -> 0 | I11: =[4]p02!I11 -> 0 | ... K11: =[4]p02!K11 -> 0
A12: Exported units P2 | B12: =[4]p02!B12 -> 0 | C12: =[4]p02!C12 -> 0 | D12: =[4]p02!D12 -> 0 | E12: =[4]p02!E12 -> 0 | F12: =[4]p02!F12 -> 0 | G12: =[4]p02!G12 -> 782459 | H12: =[4]p02!H12 -> 0 | I12: =[4]p02!I12 -> 0 | ... K12: =[4]p02!K12 -> 0
A13: Price company 1 P1 | B13: =[4]p02!B13 -> 4050 | C13: =[4]p02!C13 -> 414 | D13: =[4]p02!D13 -> 378 | E13: =[4]p02!E13 -> 32.4 | F13: =[4]p02!F13 -> 44.1 | G13: =[4]p02!G13 -> 44.1 | H13: =[4]p02!H13 -> 0 | I13: =[4]p02!I13 -> 0 | ... K13: =[4]p02!K13 -> 0
A14: Price company 2 P1 | B14: =[4]p02!B14 -> 4230 | C14: =[4]p02!C14 -> 427.5 | D14: =[4]p02!D14 -> 378 | E14: =[4]p02!E14 -> 30.15 | F14: =[4]p02!F14 -> 39.6 | G14: =[4]p02!G14 -> 42.3 | H14: =[4]p02!H14 -> 0 | I14: =[4]p02!I14 -> 0 | ... K14: =[4]p02!K14 -> 0
... A77: New Plant capacity P2 | B77: =[4]p02!B77 -> 0 | C77: =[4]p02!C77 -> 0 | D77: =[4]p02!D77 -> 0 | E77: =[4]p02!E77 -> 0 | F77: =[4]p02!F77 -> 0 | G77: =[4]p02!G77 -> 0 | H77: =[4]p02!H77 -> 0 | I77: =[4]p02!I77 -> 0 | ... K77: =[4]p02!K77 -> 0
A78: COMPANY DATA | B78: =[4]p02!B78 -> 1
A79: Contract Vol Demand | B79: =[4]p02!B79 -> 30000
A80: Total cont Vol Sold | B80: =[4]p02!B80 -> 30000
A81: Contract Price | B81: =[4]p02!B81 -> 0
A82: Contract units sold | B82: =[4]p02!B82 -> 0
A83: Contract sales dollars | B83: =[4]p02!B83 -> 0
A84: Contract unit cost | B84: =[4]p02!B84 -> 0
A85: Demand Units Japan P1 | B85: =[4]p02!B85 -> 46345
A86: Demand Units Mexico P1 | B86: =[4]p02!B86 -> 26121
A87: Demand Units China P1 | B87: =[4]p02!B87 -> 16000
A88: Demand Units UK P1 | B88: =[4]p02!B88 -> 28325
A89: Demand Units German P1 | B89: =[4]p02!B89 -> 35903
... A291: Return on Invested Capital | B291: =[4]p02!B291 -> 0.37361981

Sheet P3
C1: OUTPUT PERIOD 3
A2: 3 | B2: JAPAN | C2: MEXICO | D2: CHINA | E2: U.K. | F2: GERMAN | G2: U.S. | H2: TOTAL
A3: Demand - Units P1 | B3: =[4]p03!B3 -> 218948 | C3: =[4]p03!C3 -> 122421 | D3: =[4]p03!D3 -> 80719 | E3: =[4]p03!E3 -> 149314 | F3: =[4]p03!F3 -> 186528 | G3: =[4]p03!G3 -> 427732 | H3: =[4]p03!H3 -> 1185662 | I3: =[4]p03!I3 -> 0 | ... K3: =[4]p03!K3 -> 0
A4: Sales - Units P1 | B4: =[4]p03!B4 -> 218948 | C4: =[4]p03!C4 -> 122421 | D4: =[4]p03!D4 -> 80719 | E4: =[4]p03!E4 -> 149314 | F4: =[4]p03!F4 -> 186528 | G4: =[4]p03!G4 -> 427732 | H4: =[4]p03!H4 -> 1185662 | I4: =[4]p03!I4 -> 0 | ... K4: =[4]p03!K4 -> 0
A5: Domestic Units sold P1 | B5: =[4]p03!B5 -> 0 | C5: =[4]p03!C5 -> 0 | D5: =[4]p03!D5 -> 80719 | E5: =[4]p03!E5 -> 0 | F5: =[4]p03!F5 -> 0 | G5: =[4]p03!G5 -> 0 | H5: =[4]p03!H5 -> 0 | I5: =[4]p03!I5 -> 0 | ... K5: =[4]p03!K5 -> 0
A6: Imported Units sold P1 | B6: =[4]p03!B6 -> 218948 | C6: =[4]p03!C6 -> 122421 | D6: =[4]p03!D6 -> 0 | E6: =[4]p03!E6 -> 149314 | F6: =[4]p03!F6 -> 186528 | G6: =[4]p03!G6 -> 427732 | H6: =[4]p03!H6 -> 0 | I6: =[4]p03!I6 -> 0 | ... K6: =[4]p03!K6 -> 0
A7: Exported units P1 | B7: =[4]p03!B7 -> 0 | C7: =[4]p03!C7 -> 0 | D7: =[4]p03!D7 -> 1104943 | E7: =[4]p03!E7 -> 0 | F7: =[4]p03!F7 -> 0 | G7: =[4]p03!G7 -> 0 | H7: =[4]p03!H7 -> 0 | I7: =[4]p03!I7 -> 0 | ... K7: =[4]p03!K7 -> 0
A8: Demand - Units P2 | B8: =[4]p03!B8 -> 195273 | C8: =[4]p03!C8 -> 123385 | D8: =[4]p03!D8 -> 85305 | E8: =[4]p03!E8 -> 146202 | F8: =[4]p03!F8 -> 195967 | G8: =[4]p03!G8 -> 424516 | H8: =[4]p03!H8 -> 1170648 | I8: =[4]p03!I8 -> 0 | ... K8: =[4]p03!K8 -> 0
A9: Sales - Units P2 | B9: =[4]p03!B9 -> 195273 | C9: =[4]p03!C9 -> 123385 | D9: =[4]p03!D9 -> 85305 | E9: =[4]p03!E9 -> 146202 | F9: =[4]p03!F9 -> 195967 | G9: =[4]p03!G9 -> 424516 | H9: =[4]p03!H9 -> 1170648 | I9: =[4]p03!I9 -> 0 | ... K9: =[4]p03!K9 -> 0
A10: Domestic Units sold P2 | B10: =[4]p03!B10 -> 0 | C10: =[4]p03!C10 -> 0 | D10: =[4]p03!D10 -> 0 | E10: =[4]p03!E10 -> 0 | F10: =[4]p03!F10 -> 0 | G10: =[4]p03!G10 -> 424516 | H10: =[4]p03!H10 -> 0 | I10: =[4]p03!I10 -> 0 | ... K10: =[4]p03!K10 -> 0
A11: Imported Units sold P2 | B11: =[4]p03!B11 -> 195273 | C11: =[4]p03!C11 -> 123385 | D11: =[4]p03!D11 -> 85305 | E11: =[4]p03!E11 -> 146202 | F11: =[4]p03!F11 -> 195967 | G11: =[4]p03!G11 -> 0 | H11: =[4]p03!H11 -> 0 | I11: =[4]p03!I11 -> 0 | ... K11: =[4]p03!K11 -> 0
A12: Exported units P2 | B12: =[4]p03!B12 -> 0 | C12: =[4]p03!C12 -> 0 | D12: =[4]p03!D12 -> 0 | E12: =[4]p03!E12 -> 0 | F12: =[4]p03!F12 -> 0 | G12: =[4]p03!G12 -> 746132 | H12: =[4]p03!H12 -> 0 | I12: =[4]p03!I12 -> 0 | ... K12: =[4]p03!K12 -> 0
A13: Price company 1 P1 | B13: =[4]p03!B13 -> 4050 | C13: =[4]p03!C13 -> 382.5 | D13: =[4]p03!D13 -> 360 | E13: =[4]p03!E13 -> 31.5 | F13: =[4]p03!F13 -> 42.3 | G13: =[4]p03!G13 -> 43.2 | H13: =[4]p03!H13 -> 0 | I13: =[4]p03!I13 -> 0 | ... K13: =[4]p03!K13 -> 0
A14: Price company 2 P1 | B14: =[4]p03!B14 -> 4500 | C14: =[4]p03!C14 -> 427.5 | D14: =[4]p03!D14 -> 405 | E14: =[4]p03!E14 -> 30.15 | F14: =[4]p03!F14 -> 42.3 | G14: =[4]p03!G14 -> 45 | H14: =[4]p03!H14 -> 0 | I14: =[4]p03!I14 -> 0 | ... K14: =[4]p03!K14 -> 0
... A77: New Plant capacity P2 | B77: =[4]p03!B77 -> 0 | C77: =[4]p03!C77 -> 0 | D77: =[4]p03!D77 -> 0 | E77: =[4]p03!E77 -> 0 | F77: =[4]p03!F77 -> 0 | G77: =[4]p03!G77 -> 0 | H77: =[4]p03!H77 -> 0 | I77: =[4]p03!I77 -> 0 | ... K77: =[4]p03!K77 -> 0
A78: COMPANY DATA | B78: =[4]p03!B78 -> 1
A79: Contract Vol Demand | B79: =[4]p03!B79 -> 45000
A80: Total cont Vol Sold | B80: =[4]p03!B80 -> 45000
A81: Contract Price | B81: =[4]p03!B81 -> 0
A82: Contract units sold | B82: =[4]p03!B82 -> 0
A83: Contract sales dollars | B83: =[4]p03!B83 -> 0
A84: Contract unit cost | B84: =[4]p03!B84 -> 0
A85: Demand Units Japan P1 | B85: =[4]p03!B85 -> 43155
A86: Demand Units Mexico P1 | B86: =[4]p03!B86 -> 25137
A87: Demand Units China P1 | B87: =[4]p03!B87 -> 16839
A88: Demand Units UK P1 | B88: =[4]p03!B88 -> 27134
A89: Demand Units German P1 | B89: =[4]p03!B89 -> 35509
... A291: Return on Invested Capital | B291: =[4]p03!B291 -> 0.29721483

Sheet P4
C1: OUTPUT PERIOD 4
A2: 4 | B2: JAPAN | C2: MEXICO | D2: CHINA | E2: U.K. | F2: GERMAN | G2: U.S. | H2: TOTAL
A3: Demand - Units P1 | B3: =[4]p04!B3 -> 226105 | C3: =[4]p04!C3 -> 109741 | D3: =[4]p04!D3 -> 73151 | E3: =[4]p04!E3 -> 152440 | F3: =[4]p04!F3 -> 193917 | G3: =[4]p04!G3 -> 440159 | H3: =[4]p04!H3 -> 1195513 | I3: =[4]p04!I3 -> 0 | ... K3: =[4]p04!K3 -> 0
A4: Sales - Units P1 | B4: =[4]p04!B4 -> 226105 | C4: =[4]p04!C4 -> 109741 | D4: =[4]p04!D4 -> 73151 | E4: =[4]p04!E4 -> 152440 | F4: =[4]p04!F4 -> 193917 | G4: =[4]p04!G4 -> 440159 | H4: =[4]p04!H4 -> 1195513 | I4: =[4]p04!I4 -> 0 | ... K4: =[4]p04!K4 -> 0
A5: Domestic Units sold P1 | B5: =[4]p04!B5 -> 0 | C5: =[4]p04!C5 -> 0 | D5: =[4]p04!D5 -> 73151 | E5: =[4]p04!E5 -> 0 | F5: =[4]p04!F5 -> 0 | G5: =[4]p04!G5 -> 0 | H5: =[4]p04!H5 -> 0 | I5: =[4]p04!I5 -> 0 | ... K5: =[4]p04!K5 -> 0
A6: Imported Units sold P1 | B6: =[4]p04!B6 -> 226105 | C6: =[4]p04!C6 -> 109741 | D6: =[4]p04!D6 -> 0 | E6: =[4]p04!E6 -> 152440 | F6: =[4]p04!F6 -> 193917 | G6: =[4]p04!G6 -> 440159 | H6: =[4]p04!H6 -> 0 | I6: =[4]p04!I6 -> 0 | ... K6: =[4]p04!K6 -> 0
A7: Exported units P1 | B7: =[4]p04!B7 -> 0 | C7: =[4]p04!C7 -> 0 | D7: =[4]p04!D7 -> 1122362 | E7: =[4]p04!E7 -> 0 | F7: =[4]p04!F7 -> 0 | G7: =[4]p04!G7 -> 0 | H7: =[4]p04!H7 -> 0 | I7: =[4]p04!I7 -> 0 | ... K7: =[4]p04!K7 -> 0
A8: Demand - Units P2 | B8: =[4]p04!B8 -> 201373 | C8: =[4]p04!C8 -> 120933 | D8: =[4]p04!D8 -> 81545 | E8: =[4]p04!E8 -> 150989 | F8: =[4]p04!F8 -> 204705 | G8: =[4]p04!G8 -> 442925 | H8: =[4]p04!H8 -> 1202470 | I8: =[4]p04!I8 -> 0 | ... K8: =[4]p04!K8 -> 0
A9: Sales - Units P2 | B9: =[4]p04!B9 -> 201373 | C9: =[4]p04!C9 -> 120933 | D9: =[4]p04!D9 -> 81545 | E9: =[4]p04!E9 -> 150989 | F9: =[4]p04!F9 -> 204705 | G9: =[4]p04!G9 -> 442925 | H9: =[4]p04!H9 -> 1202470 | I9: =[4]p04!I9 -> 0 | ... K9: =[4]p04!K9 -> 0
A10: Domestic Units sold P2 | B10: =[4]p04!B10 -> 0 | C10: =[4]p04!C10 -> 0 | D10: =[4]p04!D10 -> 0 | E10: =[4]p04!E10 -> 0 | F10: =[4]p04!F10 -> 0 | G10: =[4]p04!G10 -> 442925 | H10: =[4]p04!H10 -> 0 | I10: =[4]p04!I10 -> 0 | ... K10: =[4]p04!K10 -> 0
A11: Imported Units sold P2 | B11: =[4]p04!B11 -> 201373 | C11: =[4]p04!C11 -> 120933 | D11: =[4]p04!D11 -> 81545 | E11: =[4]p04!E11 -> 150989 | F11: =[4]p04!F11 -> 204705 | G11: =[4]p04!G11 -> 0 | H11: =[4]p04!H11 -> 0 | I11: =[4]p04!I11 -> 0 | ... K11: =[4]p04!K11 -> 0
A12: Exported units P2 | B12: =[4]p04!B12 -> 0 | C12: =[4]p04!C12 -> 0 | D12: =[4]p04!D12 -> 0 | E12: =[4]p04!E12 -> 0 | F12: =[4]p04!F12 -> 0 | G12: =[4]p04!G12 -> 759545 | H12: =[4]p04!H12 -> 0 | I12: =[4]p04!I12 -> 0 | ... K12: =[4]p04!K12 -> 0
A13: Price company 1 P1 | B13: =[4]p04!B13 -> 3780 | C13: =[4]p04!C13 -> 382.5 | D13: =[4]p04!D13 -> 360 | E13: =[4]p04!E13 -> 28.8 | F13: =[4]p04!F13 -> 40.5 | G13: =[4]p04!G13 -> 41.4 | H13: =[4]p04!H13 -> 0 | I13: =[4]p04!I13 -> 0 | ... K13: =[4]p04!K13 -> 0
A14: Price company 2 P1 | B14: =[4]p04!B14 -> 4590 | C14: =[4]p04!C14 -> 436.5 | D14: =[4]p04!D14 -> 405 | E14: =[4]p04!E14 -> 30.15 | F14: =[4]p04!F14 -> 42.3 | G14: =[4]p04!G14 -> 45 | H14: =[4]p04!H14 -> 0 | I14: =[4]p04!I14 -> 0 | ... K14: =[4]p04!K14 -> 0
... A77: New Plant capacity P2 | B77: =[4]p04!B77 -> 0 | C77: =[4]p04!C77 -> 0 | D77: =[4]p04!D77 -> 0 | E77: =[4]p04!E77 -> 0 | F77: =[4]p04!F77 -> 0 | G77: =[4]p04!G77 -> 0 | H77: =[4]p04!H77 -> 0 | I77: =[4]p04!I77 -> 0 | ... K77: =[4]p04!K77 -> 0
A78: COMPANY DATA | B78: =[4]p04!B78 -> 1
A79: Contract Vol Demand | B79: =[4]p04!B79 -> 55000
A80: Total cont Vol Sold | B80: =[4]p04!B80 -> 55000
A81: Contract Price | B81: =[4]p04!B81 -> 0
A82: Contract units sold | B82: =[4]p04!B82 -> 0
A83: Contract sales dollars | B83: =[4]p04!B83 -> 0
A84: Contract unit cost | B84: =[4]p04!B84 -> 0
A85: Demand Units Japan P1 | B85: =[4]p04!B85 -> 53140
A86: Demand Units Mexico P1 | B86: =[4]p04!B86 -> 26950
A87: Demand Units China P1 | B87: =[4]p04!B87 -> 18573
A88: Demand Units UK P1 | B88: =[4]p04!B88 -> 34614
A89: Demand Units German P1 | B89: =[4]p04!B89 -> 44243
... A291: Return on Invested Capital | B291: =[4]p04!B291 -> 0.47025026

Sheet P5
C1: OUTPUT PERIOD 5
A2: 5 | B2: JAPAN | C2: MEXICO | D2: CHINA | E2: U.K. | F2: GERMAN | G2: U.S. | H2: TOTAL
A3: Demand - Units P1 | B3: =[4]p05!B3 -> 232168 | C3: =[4]p05!C3 -> 111733 | D3: =[4]p05!D3 -> 74884 | E3: =[4]p05!E3 -> 160736 | F3: =[4]p05!F3 -> 200974 | G3: =[4]p05!G3 -> 451831 | H3: =[4]p05!H3 -> 1232326 | I3: =[4]p05!I3 -> 0 | ... K3: =[4]p05!K3 -> 0
A4: Sales - Units P1 | B4: =[4]p05!B4 -> 232168 | C4: =[4]p05!C4 -> 111733 | D4: =[4]p05!D4 -> 74884 | E4: =[4]p05!E4 -> 160736 | F4: =[4]p05!F4 -> 200974 | G4: =[4]p05!G4 -> 451831 | H4: =[4]p05!H4 -> 1232326 | I4: =[4]p05!I4 -> 0 | ... K4: =[4]p05!K4 -> 0
A5: Domestic Units sold P1 | B5: =[4]p05!B5 -> 0 | C5: =[4]p05!C5 -> 0 | D5: =[4]p05!D5 -> 74884 | E5: =[4]p05!E5 -> 0 | F5: =[4]p05!F5 -> 0 | G5: =[4]p05!G5 -> 0 | H5: =[4]p05!H5 -> 0 | I5: =[4]p05!I5 -> 0 | ... K5: =[4]p05!K5 -> 0
A6: Imported Units sold P1 | B6: =[4]p05!B6 -> 232168 | C6: =[4]p05!C6 -> 111733 | D6: =[4]p05!D6 -> 0 | E6: =[4]p05!E6 -> 160736 | F6: =[4]p05!F6 -> 200974 | G6: =[4]p05!G6 -> 451831 | H6: =[4]p05!H6 -> 0 | I6: =[4]p05!I6 -> 0 | ... K6: =[4]p05!K6 -> 0
A7: Exported units P1 | B7: =[4]p05!B7 -> 0 | C7: =[4]p05!C7 -> 0 | D7: =[4]p05!D7 -> 1157442 | E7: =[4]p05!E7 -> 0 | F7: =[4]p05!F7 -> 0 | G7: =[4]p05!G7 -> 0 | H7: =[4]p05!H7 -> 0 | I7: =[4]p05!I7 -> 0 | ... K7: =[4]p05!K7 -> 0
A8: Demand - Units P2 | B8: =[4]p05!B8 -> 204670 | C8: =[4]p05!C8 -> 121839 | D8: =[4]p05!D8 -> 82683 | E8: =[4]p05!E8 -> 155425 | F8: =[4]p05!F8 -> 210534 | G8: =[4]p05!G8 -> 450949 | H8: =[4]p05!H8 -> 1226100 | I8: =[4]p05!I8 -> 0 | ... K8: =[4]p05!K8 -> 0
A9: Sales - Units P2 | B9: =[4]p05!B9 -> 204670 | C9: =[4]p05!C9 -> 121839 | D9: =[4]p05!D9 -> 82683 | E9: =[4]p05!E9 -> 155425 | F9: =[4]p05!F9 -> 210534 | G9: =[4]p05!G9 -> 450949 | H9: =[4]p05!H9 -> 1226100 | I9: =[4]p05!I9 -> 0 | ... K9: =[4]p05!K9 -> 0
A10: Domestic Units sold P2 | B10: =[4]p05!B10 -> 0 | C10: =[4]p05!C10 -> 0 | D10: =[4]p05!D10 -> 0 | E10: =[4]p05!E10 -> 0 | F10: =[4]p05!F10 -> 0 | G10: =[4]p05!G10 -> 450949 | H10: =[4]p05!H10 -> 0 | I10: =[4]p05!I10 -> 0 | ... K10: =[4]p05!K10 -> 0
A11: Imported Units sold P2 | B11: =[4]p05!B11 -> 204670 | C11: =[4]p05!C11 -> 121839 | D11: =[4]p05!D11 -> 82683 | E11: =[4]p05!E11 -> 155425 | F11: =[4]p05!F11 -> 210534 | G11: =[4]p05!G11 -> 0 | H11: =[4]p05!H11 -> 0 | I11: =[4]p05!I11 -> 0 | ... K11: =[4]p05!K11 -> 0
A12: Exported units P2 | B12: =[4]p05!B12 -> 0 | C12: =[4]p05!C12 -> 0 | D12: =[4]p05!D12 -> 0 | E12: =[4]p05!E12 -> 0 | F12: =[4]p05!F12 -> 0 | G12: =[4]p05!G12 -> 775151 | H12: =[4]p05!H12 -> 0 | I12: =[4]p05!I12 -> 0 | ... K12: =[4]p05!K12 -> 0
A13: Price company 1 P1 | B13: =[4]p05!B13 -> 3780 | C13: =[4]p05!C13 -> 382.5 | D13: =[4]p05!D13 -> 360 | E13: =[4]p05!E13 -> 28.8 | F13: =[4]p05!F13 -> 40.5 | G13: =[4]p05!G13 -> 41.4 | H13: =[4]p05!H13 -> 0 | I13: =[4]p05!I13 -> 0 | ... K13: =[4]p05!K13 -> 0
A14: Price company 2 P1 | B14: =[4]p05!B14 -> 4590 | C14: =[4]p05!C14 -> 418.5 | D14: =[4]p05!D14 -> 405 | E14: =[4]p05!E14 -> 28.35 | F14: =[4]p05!F14 -> 42.3 | G14: =[4]p05!G14 -> 45 | H14: =[4]p05!H14 -> 0 | I14: =[4]p05!I14 -> 0 | ... K14: =[4]p05!K14 -> 0
... A77: New Plant capacity P2 | B77: =[4]p05!B77 -> 0 | C77: =[4]p05!C77 -> 0 | D77: =[4]p05!D77 -> 0 | E77: =[4]p05!E77 -> 0 | F77: =[4]p05!F77 -> 0 | G77: =[4]p05!G77 -> 0 | H77: =[4]p05!H77 -> 0 | I77: =[4]p05!I77 -> 0 | ... K77: =[4]p05!K77 -> 0
A78: COMPANY DATA | B78: =[4]p05!B78 -> 1
A79: Contract Vol Demand | B79: =[4]p05!B79 -> 45000
A80: Total cont Vol Sold | B80: =[4]p05!B80 -> 45000
A81: Contract Price | B81: =[4]p05!B81 -> 0
A82: Contract units sold | B82: =[4]p05!B82 -> 0
A83: Contract sales dollars | B83: =[4]p05!B83 -> 0
A84: Contract unit cost | B84: =[4]p05!B84 -> 0
A85: Demand Units Japan P1 | B85: =[4]p05!B85 -> 52951
A86: Demand Units Mexico P1 | B86: =[4]p05!B86 -> 25409
A87: Demand Units China P1 | B87: =[4]p05!B87 -> 17915
A88: Demand Units UK P1 | B88: =[4]p05!B88 -> 37378
A89: Demand Units German P1 | B89: =[4]p05!B89 -> 45560
... A291: Return on Invested Capital | B291: =[4]p05!B291 -> 0.43855125

Sheet P6
C1: OUTPUT PERIOD 6
A2: 6 | B2: JAPAN | C2: MEXICO | D2: CHINA | E2: U.K. | F2: GERMAN | G2: U.S. | H2: TOTAL
A3: Demand - Units P1 | B3: =[4]p06!B3 -> 238165 | C3: =[4]p06!C3 -> 116452 | D3: =[4]p06!D3 -> 76976 | E3: =[4]p06!E3 -> 158008 | F3: =[4]p06!F3 -> 197732 | G3: =[4]p06!G3 -> 457443 | H3: =[4]p06!H3 -> 1244776 | I3: =[4]p06!I3 -> 0 | ... K3: =[4]p06!K3 -> 0
A4: Sales - Units P1 | B4: =[4]p06!B4 -> 238165 | C4: =[4]p06!C4 -> 116452 | D4: =[4]p06!D4 -> 76976 | E4: =[4]p06!E4 -> 158008 | F4: =[4]p06!F4 -> 197732 | G4: =[4]p06!G4 -> 457443 | H4: =[4]p06!H4 -> 1244776 | I4: =[4]p06!I4 -> 0 | ... K4: =[4]p06!K4 -> 0
A5: Domestic Units sold P1 | B5: =[4]p06!B5 -> 0 | C5: =[4]p06!C5 -> 0 | D5: =[4]p06!D5 -> 76976 | E5: =[4]p06!E5 -> 0 | F5: =[4]p06!F5 -> 0 | G5: =[4]p06!G5 -> 0 | H5: =[4]p06!H5 -> 0 | I5: =[4]p06!I5 -> 0 | ... K5: =[4]p06!K5 -> 0
A6: Imported Units sold P1 | B6: =[4]p06!B6 -> 238165 | C6: =[4]p06!C6 -> 116452 | D6: =[4]p06!D6 -> 0 | E6: =[4]p06!E6 -> 158008 | F6: =[4]p06!F6 -> 197732 | G6: =[4]p06!G6 -> 457443 | H6: =[4]p06!H6 -> 0 | I6: =[4]p06!I6 -> 0 | ... K6: =[4]p06!K6 -> 0
A7: Exported units P1 | B7: =[4]p06!B7 -> 0 | C7: =[4]p06!C7 -> 0 | D7: =[4]p06!D7 -> 1167800 | E7: =[4]p06!E7 -> 0 | F7: =[4]p06!F7 -> 0 | G7: =[4]p06!G7 -> 0 | H7: =[4]p06!H7 -> 0 | I7: =[4]p06!I7 -> 0 | ... K7: =[4]p06!K7 -> 0
A8: Demand - Units P2 | B8: =[4]p06!B8 -> 211571 | C8: =[4]p06!C8 -> 126731 | D8: =[4]p06!D8 -> 85377 | E8: =[4]p06!E8 -> 153654 | F8: =[4]p06!F8 -> 209593 | G8: =[4]p06!G8 -> 461060 | H8: =[4]p06!H8 -> 1247986 | I8: =[4]p06!I8 -> 0 | ... K8: =[4]p06!K8 -> 0
A9: Sales - Units P2 | B9: =[4]p06!B9 -> 211571 | C9: =[4]p06!C9 -> 126731 | D9: =[4]p06!D9 -> 85377 | E9: =[4]p06!E9 -> 153654 | F9: =[4]p06!F9 -> 209593 | G9: =[4]p06!G9 -> 461060 | H9: =[4]p06!H9 -> 1247986 | I9: =[4]p06!I9 -> 0 | ... K9: =[4]p06!K9 -> 0
A10: Domestic Units sold P2 | B10: =[4]p06!B10 -> 0 | C10: =[4]p06!C10 -> 0 | D10: =[4]p06!D10 -> 0 | E10: =[4]p06!E10 -> 0 | F10: =[4]p06!F10 -> 0 | G10: =[4]p06!G10 -> 461060 | H10: =[4]p06!H10 -> 0 | I10: =[4]p06!I10 -> 0 | ... K10: =[4]p06!K10 -> 0
A11: Imported Units sold P2 | B11: =[4]p06!B11 -> 211571 | C11: =[4]p06!C11 -> 126731 | D11: =[4]p06!D11 -> 85377 | E11: =[4]p06!E11 -> 153654 | F11: =[4]p06!F11 -> 209593 | G11: =[4]p06!G11 -> 0 | H11: =[4]p06!H11 -> 0 | I11: =[4]p06!I11 -> 0 | ... K11: =[4]p06!K11 -> 0
A12: Exported units P2 | B12: =[4]p06!B12 -> 0 | C12: =[4]p06!C12 -> 0 | D12: =[4]p06!D12 -> 0 | E12: =[4]p06!E12 -> 0 | F12: =[4]p06!F12 -> 0 | G12: =[4]p06!G12 -> 786926 | H12: =[4]p06!H12 -> 0 | I12: =[4]p06!I12 -> 0 | ... K12: =[4]p06!K12 -> 0
A13: Price company 1 P1 | B13: =[4]p06!B13 -> 3780 | C13: =[4]p06!C13 -> 382.5 | D13: =[4]p06!D13 -> 360 | E13: =[4]p06!E13 -> 28.8 | F13: =[4]p06!F13 -> 40.5 | G13: =[4]p06!G13 -> 41.4 | H13: =[4]p06!H13 -> 0 | I13: =[4]p06!I13 -> 0 | ... K13: =[4]p06!K13 -> 0
A14: Price company 2 P1 | B14: =[4]p06!B14 -> 4590 | C14: =[4]p06!C14 -> 418.5 | D14: =[4]p06!D14 -> 405 | E14: =[4]p06!E14 -> 28.35 | F14: =[4]p06!F14 -> 42.3 | G14: =[4]p06!G14 -> 45 | H14: =[4]p06!H14 -> 0 | I14: =[4]p06!I14 -> 0 | ... K14: =[4]p06!K14 -> 0
... A77: New Plant capacity P2 | B77: =[4]p06!B77 -> 0 | C77: =[4]p06!C77 -> 0 | D77: =[4]p06!D77 -> 0 | E77: =[4]p06!E77 -> 0 | F77: =[4]p06!F77 -> 0 | G77: =[4]p06!G77 -> 0 | H77: =[4]p06!H77 -> 0 | I77: =[4]p06!I77 -> 0 | ... K77: =[4]p06!K77 -> 0
A78: COMPANY DATA | B78: =[4]p06!B78 -> 1
A79: Contract Vol Demand | B79: =[4]p06!B79 -> 60000
A80: Total cont Vol Sold | B80: =[4]p06!B80 -> 60000
A81: Contract Price | B81: =[4]p06!B81 -> 0
A82: Contract units sold | B82: =[4]p06!B82 -> 0
A83: Contract sales dollars | B83: =[4]p06!B83 -> 0
A84: Contract unit cost | B84: =[4]p06!B84 -> 0
A85: Demand Units Japan P1 | B85: =[4]p06!B85 -> 39420
A86: Demand Units Mexico P1 | B86: =[4]p06!B86 -> 19363
A87: Demand Units China P1 | B87: =[4]p06!B87 -> 13535
A88: Demand Units UK P1 | B88: =[4]p06!B88 -> 27634
A89: Demand Units German P1 | B89: =[4]p06!B89 -> 32868
... A291: Return on Invested Capital | B291: =[4]p06!B291 -> 0.17405346

Sheet P7
C1: OUTPUT PERIOD 7
A2: 7 | B2: JAPAN | C2: MEXICO | D2: CHINA | E2: U.K. | F2: GERMAN | G2: U.S. | H2: TOTAL
A3: Demand - Units P1 | B3: =[4]p07!B3 -> 240805 | C3: =[4]p07!C3 -> 119191 | D3: =[4]p07!D3 -> 79297 | E3: =[4]p07!E3 -> 165803 | F3: =[4]p07!F3 -> 206016 | G3: =[4]p07!G3 -> 479034 | H3: =[4]p07!H3 -> 1290146 | I3: =[4]p07!I3 -> 0 | ... K3: =[4]p07!K3 -> 0
A4: Sales - Units P1 | B4: =[4]p07!B4 -> 240805 | C4: =[4]p07!C4 -> 119191 | D4: =[4]p07!D4 -> 79297 | E4: =[4]p07!E4 -> 165803 | F4: =[4]p07!F4 -> 206016 | G4: =[4]p07!G4 -> 479034 | H4: =[4]p07!H4 -> 1290146 | I4: =[4]p07!I4 -> 0 | ... K4: =[4]p07!K4 -> 0
A5: Domestic Units sold P1 | B5: =[4]p07!B5 -> 0 | C5: =[4]p07!C5 -> 0 | D5: =[4]p07!D5 -> 79297 | E5: =[4]p07!E5 -> 0 | F5: =[4]p07!F5 -> 0 | G5: =[4]p07!G5 -> 0 | H5: =[4]p07!H5 -> 0 | I5: =[4]p07!I5 -> 0 | ... K5: =[4]p07!K5 -> 0
A6: Imported Units sold P1 | B6: =[4]p07!B6 -> 240805 | C6: =[4]p07!C6 -> 119191 | D6: =[4]p07!D6 -> 0 | E6: =[4]p07!E6 -> 165803 | F6: =[4]p07!F6 -> 206016 | G6: =[4]p07!G6 -> 479034 | H6: =[4]p07!H6 -> 0 | I6: =[4]p07!I6 -> 0 | ... K6: =[4]p07!K6 -> 0
A7: Exported units P1 | B7: =[4]p07!B7 -> 0 | C7: =[4]p07!C7 -> 0 | D7: =[4]p07!D7 -> 1210849 | E7: =[4]p07!E7 -> 0 | F7: =[4]p07!F7 -> 0 | G7: =[4]p07!G7 -> 0 | H7: =[4]p07!H7 -> 0 | I7: =[4]p07!I7 -> 0 | ... K7: =[4]p07!K7 -> 0
A8: Demand - Units P2 | B8: =[4]p07!B8 -> 216853 | C8: =[4]p07!C8 -> 131078 | D8: =[4]p07!D8 -> 83345 | E8: =[4]p07!E8 -> 163272 | F8: =[4]p07!F8 -> 214997 | G8: =[4]p07!G8 -> 482004 | H8: =[4]p07!H8 -> 1291549 | I8: =[4]p07!I8 -> 0 | ... K8: =[4]p07!K8 -> 0
A9: Sales - Units P2 | B9: =[4]p07!B9 -> 216853 | C9: =[4]p07!C9 -> 131078 | D9: =[4]p07!D9 -> 83345 | E9: =[4]p07!E9 -> 163272 | F9: =[4]p07!F9 -> 214997 | G9: =[4]p07!G9 -> 482004 | H9: =[4]p07!H9 -> 1291549 | I9: =[4]p07!I9 -> 0 | ... K9: =[4]p07!K9 -> 0
A10: Domestic Units sold P2 | B10: =[4]p07!B10 -> 0 | C10: =[4]p07!C10 -> 0 | D10: =[4]p07!D10 -> 0 | E10: =[4]p07!E10 -> 0 | F10: =[4]p07!F10 -> 0 | G10: =[4]p07!G10 -> 482004 | H10: =[4]p07!H10 -> 0 | I10: =[4]p07!I10 -> 0 | ... K10: =[4]p07!K10 -> 0
A11: Imported Units sold P2 | B11: =[4]p07!B11 -> 216853 | C11: =[4]p07!C11 -> 131078 | D11: =[4]p07!D11 -> 83345 | E11: =[4]p07!E11 -> 163272 | F11: =[4]p07!F11 -> 214997 | G11: =[4]p07!G11 -> 0 | H11: =[4]p07!H11 -> 0 | I11: =[4]p07!I11 -> 0 | ... K11: =[4]p07!K11 -> 0
A12: Exported units P2 | B12: =[4]p07!B12 -> 0 | C12: =[4]p07!C12 -> 0 | D12: =[4]p07!D12 -> 0 | E12: =[4]p07!E12 -> 0 | F12: =[4]p07!F12 -> 0 | G12: =[4]p07!G12 -> 809545 | H12: =[4]p07!H12 -> 0 | I12: =[4]p07!I12 -> 0 | ... K12: =[4]p07!K12 -> 0
A13: Price company 1 P1 | B13: =[4]p07!B13 -> 3780 | C13: =[4]p07!C13 -> 382.5 | D13: =[4]p07!D13 -> 360 | E13: =[4]p07!E13 -> 28.8 | F13: =[4]p07!F13 -> 40.5 | G13: =[4]p07!G13 -> 41.4 | H13: =[4]p07!H13 -> 0 | I13: =[4]p07!I13 -> 0 | ... K13: =[4]p07!K13 -> 0
A14: Price company 2 P1 | B14: =[4]p07!B14 -> 4410 | C14: =[4]p07!C14 -> 418.5 | D14: =[4]p07!D14 -> 378 | E14: =[4]p07!E14 -> 28.35 | F14: =[4]p07!F14 -> 40.5 | G14: =[4]p07!G14 -> 42.3 | H14: =[4]p07!H14 -> 0 | I14: =[4]p07!I14 -> 0 | ... K14: =[4]p07!K14 -> 0
... A77: New Plant capacity P2 | B77: =[4]p07!B77 -> 0 | C77: =[4]p07!C77 -> 0 | D77: =[4]p07!D77 -> 0 | E77: =[4]p07!E77 -> 0 | F77: =[4]p07!F77 -> 0 | G77: =[4]p07!G77 -> 0 | H77: =[4]p07!H77 -> 0 | I77: =[4]p07!I77 -> 0 | ... K77: =[4]p07!K77 -> 0
A78: COMPANY DATA | B78: =[4]p07!B78 -> 1
A79: Contract Vol Demand | B79: =[4]p07!B79 -> 45000
A80: Total cont Vol Sold | B80: =[4]p07!B80 -> 45000
A81: Contract Price | B81: =[4]p07!B81 -> 0
A82: Contract units sold | B82: =[4]p07!B82 -> 0
A83: Contract sales dollars | B83: =[4]p07!B83 -> 0
A84: Contract unit cost | B84: =[4]p07!B84 -> 0
A85: Demand Units Japan P1 | B85: =[4]p07!B85 -> 39834
A86: Demand Units Mexico P1 | B86: =[4]p07!B86 -> 19944
A87: Demand Units China P1 | B87: =[4]p07!B87 -> 13645
A88: Demand Units UK P1 | B88: =[4]p07!B88 -> 30782
A89: Demand Units German P1 | B89: =[4]p07!B89 -> 34330
... A291: Return on Invested Capital | B291: =[4]p07!B291 -> 0.073057559

Sheet P8
C1: OUTPUT PERIOD 8
A2: 8 | B2: JAPAN | C2: MEXICO | D2: CHINA | E2: U.K. | F2: GERMAN | G2: U.S. | H2: TOTAL
A3: Demand - Units P1 | B3: =[4]p08!B3 -> 263252 | C3: =[4]p08!C3 -> 118194 | D3: =[4]p08!D3 -> 90558 | E3: =[4]p08!E3 -> 158979 | F3: =[4]p08!F3 -> 178697 | G3: =[4]p08!G3 -> 483160 | H3: =[4]p08!H3 -> 1292840 | I3: =[4]p08!I3 -> 0 | ... K3: =[4]p08!K3 -> 0
A4: Sales - Units P1 | B4: =[4]p08!B4 -> 263252 | C4: =[4]p08!C4 -> 118194 | D4: =[4]p08!D4 -> 90558 | E4: =[4]p08!E4 -> 158979 | F4: =[4]p08!F4 -> 178697 | G4: =[4]p08!G4 -> 483160 | H4: =[4]p08!H4 -> 1292840 | I4: =[4]p08!I4 -> 0 | ... K4: =[4]p08!K4 -> 0
A5: Domestic Units sold P1 | B5: =[4]p08!B5 -> 0 | C5: =[4]p08!C5 -> 0 | D5: =[4]p08!D5 -> 90558 | E5: =[4]p08!E5 -> 0 | F5: =[4]p08!F5 -> 0 | G5: =[4]p08!G5 -> 0 | H5: =[4]p08!H5 -> 0 | I5: =[4]p08!I5 -> 0 | ... K5: =[4]p08!K5 -> 0
A6: Imported Units sold P1 | B6: =[4]p08!B6 -> 263252 | C6: =[4]p08!C6 -> 118194 | D6: =[4]p08!D6 -> 0 | E6: =[4]p08!E6 -> 158979 | F6: =[4]p08!F6 -> 178697 | G6: =[4]p08!G6 -> 483160 | H6: =[4]p08!H6 -> 0 | I6: =[4]p08!I6 -> 0 | ... K6: =[4]p08!K6 -> 0
A7: Exported units P1 | B7: =[4]p08!B7 -> 0 | C7: =[4]p08!C7 -> 0 | D7: =[4]p08!D7 -> 1202282 | E7: =[4]p08!E7 -> 0 | F7: =[4]p08!F7 -> 0 | G7: =[4]p08!G7 -> 0 | H7: =[4]p08!H7 -> 0 | I7: =[4]p08!I7 -> 0 | ... K7: =[4]p08!K7 -> 0
A8: Demand - Units P2 | B8: =[4]p08!B8 -> 216069 | C8: =[4]p08!C8 -> 126628 | D8: =[4]p08!D8 -> 78225 | E8: =[4]p08!E8 -> 166095 | F8: =[4]p08!F8 -> 216338 | G8: =[4]p08!G8 -> 493638 | H8: =[4]p08!H8 -> 1296993 | I8: =[4]p08!I8 -> 0 | ... K8: =[4]p08!K8 -> 0
A9: Sales - Units P2 | B9: =[4]p08!B9 -> 216069 | C9: =[4]p08!C9 -> 126628 | D9: =[4]p08!D9 -> 78225 | E9: =[4]p08!E9 -> 166095 | F9: =[4]p08!F9 -> 216338 | G9: =[4]p08!G9 -> 493638 | H9: =[4]p08!H9 -> 1296993 | I9: =[4]p08!I9 -> 0 | ... K9: =[4]p08!K9 -> 0
A10: Domestic Units sold P2 | B10: =[4]p08!B10 -> 0 | C10: =[4]p08!C10 -> 0 | D10: =[4]p08!D10 -> 0 | E10: =[4]p08!E10 -> 0 | F10: =[4]p08!F10 -> 0 | G10: =[4]p08!G10 -> 493638 | H10: =[4]p08!H10 -> 0 | I10: =[4]p08!I10 -> 0 | ... K10: =[4]p08!K10 -> 0
A11: Imported Units sold P2 | B11: =[4]p08!B11 -> 216069 | C11: =[4]p08!C11 -> 126628 | D11: =[4]p08!D11 -> 78225 | E11: =[4]p08!E11 -> 166095 | F11: =[4]p08!F11 -> 216338 | G11: =[4]p08!G11 -> 0 | H11: =[4]p08!H11 -> 0 | I11: =[4]p08!I11 -> 0 | ... K11: =[4]p08!K11 -> 0
A12: Exported units P2 | B12: =[4]p08!B12 -> 0 | C12: =[4]p08!C12 -> 0 | D12: =[4]p08!D12 -> 0 | E12: =[4]p08!E12 -> 0 | F12: =[4]p08!F12 -> 0 | G12: =[4]p08!G12 -> 803355 | H12: =[4]p08!H12 -> 0 | I12: =[4]p08!I12 -> 0 | ... K12: =[4]p08!K12 -> 0
A13: Price company 1 P1 | B13: =[4]p08!B13 -> 3600 | C13: =[4]p08!C13 -> 387 | D13: =[4]p08!D13 -> 315 | E13: =[4]p08!E13 -> 33.3 | F13: =[4]p08!F13 -> 48.6 | G13: =[4]p08!G13 -> 43.2 | H13: =[4]p08!H13 -> 0 | I13: =[4]p08!I13 -> 0 | ... K13: =[4]p08!K13 -> 0
A14: Price company 2 P1 | B14: =[4]p08!B14 -> 4410 | C14: =[4]p08!C14 -> 400.5 | D14: =[4]p08!D14 -> 378 | E14: =[4]p08!E14 -> 31.05 | F14: =[4]p08!F14 -> 51.3 | G14: =[4]p08!G14 -> 42.3 | H14: =[4]p08!H14 -> 0 | I14: =[4]p08!I14 -> 0 | ... K14: =[4]p08!K14 -> 0
... A77: New Plant capacity P2 | B77: =[4]p08!B77 -> 0 | C77: =[4]p08!C77 -> 0 | D77: =[4]p08!D77 -> 0 | E77: =[4]p08!E77 -> 0 | F77: =[4]p08!F77 -> 0 | G77: =[4]p08!G77 -> 0 | H77: =[4]p08!H77 -> 0 | I77: =[4]p08!I77 -> 0 | ... K77: =[4]p08!K77 -> 0
A78: COMPANY DATA | B78: =[4]p08!B78 -> 1
A79: Contract Vol Demand | B79: =[4]p08!B79 -> 50000
A80: Total cont Vol Sold | B80: =[4]p08!B80 -> 50000
A81: Contract Price | B81: =[4]p08!B81 -> 0
A82: Contract units sold | B82: =[4]p08!B82 -> 0
A83: Contract sales dollars | B83: =[4]p08!B83 -> 0
A84: Contract unit cost | B84: =[4]p08!B84 -> 0
A85: Demand Units Japan P1 | B85: =[4]p08!B85 -> 65978
A86: Demand Units Mexico P1 | B86: =[4]p08!B86 -> 26522
A87: Demand Units China P1 | B87: =[4]p08!B87 -> 23436
A88: Demand Units UK P1 | B88: =[4]p08!B88 -> 36330
A89: Demand Units German P1 | B89: =[4]p08!B89 -> 39768
... A291: Return on Invested Capital | B291: =[4]p08!B291 -> 0.36032662

Sheet P9
C1: OUTPUT PERIOD 9
A2: 9 | B2: JAPAN | C2: MEXICO | D2: CHINA | E2: U.K. | F2: GERMAN | G2: U.S. | H2: TOTAL
A3: Demand - Units P1 | B3: =[4]p09!B3 -> 272636 | C3: =[4]p09!C3 -> 113982 | D3: =[4]p09!D3 -> 89668 | E3: =[4]p09!E3 -> 157446 | F3: =[4]p09!F3 -> 182670 | G3: =[4]p09!G3 -> 491176 | H3: =[4]p09!H3 -> 1307578 | I3: =[4]p09!I3 -> 0 | ... K3: =[4]p09!K3 -> 0
A4: Sales - Units P1 | B4: =[4]p09!B4 -> 272636 | C4: =[4]p09!C4 -> 113982 | D4: =[4]p09!D4 -> 89668 | E4: =[4]p09!E4 -> 157446 | F4: =[4]p09!F4 -> 182670 | G4: =[4]p09!G4 -> 491176 | H4: =[4]p09!H4 -> 1307578 | I4: =[4]p09!I4 -> 0 | ... K4: =[4]p09!K4 -> 0
A5: Domestic Units sold P1 | B5: =[4]p09!B5 -> 0 | C5: =[4]p09!C5 -> 0 | D5: =[4]p09!D5 -> 89668 | E5: =[4]p09!E5 -> 0 | F5: =[4]p09!F5 -> 0 | G5: =[4]p09!G5 -> 0 | H5: =[4]p09!H5 -> 0 | I5: =[4]p09!I5 -> 0 | ... K5: =[4]p09!K5 -> 0
A6: Imported Units sold P1 | B6: =[4]p09!B6 -> 272636 | C6: =[4]p09!C6 -> 113982 | D6: =[4]p09!D6 -> 0 | E6: =[4]p09!E6 -> 157446 | F6: =[4]p09!F6 -> 182670 | G6: =[4]p09!G6 -> 491176 | H6: =[4]p09!H6 -> 0 | I6: =[4]p09!I6 -> 0 | ... K6: =[4]p09!K6 -> 0
A7: Exported units P1 | B7: =[4]p09!B7 -> 0 | C7: =[4]p09!C7 -> 0 | D7: =[4]p09!D7 -> 1217910 | E7: =[4]p09!E7 -> 0 | F7: =[4]p09!F7 -> 0 | G7: =[4]p09!G7 -> 0 | H7: =[4]p09!H7 -> 0 | I7: =[4]p09!I7 -> 0 | ... K7: =[4]p09!K7 -> 0
A8: Demand - Units P2 | B8: =[4]p09!B8 -> 203766 | C8: =[4]p09!C8 -> 132974 | D8: =[4]p09!D8 -> 88582 | E8: =[4]p09!E8 -> 157639 | F8: =[4]p09!F8 -> 204734 | G8: =[4]p09!G8 -> 496156 | H8: =[4]p09!H8 -> 1283851 | I8: =[4]p09!I8 -> 0 | ... K8: =[4]p09!K8 -> 0
A9: Sales - Units P2 | B9: =[4]p09!B9 -> 203766 | C9: =[4]p09!C9 -> 132974 | D9: =[4]p09!D9 -> 88582 | E9: =[4]p09!E9 -> 157639 | F9: =[4]p09!F9 -> 204734 | G9: =[4]p09!G9 -> 496156 | H9: =[4]p09!H9 -> 1283851 | I9: =[4]p09!I9 -> 0 | ... K9: =[4]p09!K9 -> 0
A10: Domestic Units sold P2 | B10: =[4]p09!B10 -> 0 | C10: =[4]p09!C10 -> 0 | D10: =[4]p09!D10 -> 0 | E10: =[4]p09!E10 -> 0 | F10: =[4]p09!F10 -> 0 | G10: =[4]p09!G10 -> 496156 | H10: =[4]p09!H10 -> 0 | I10: =[4]p09!I10 -> 0 | ... K10: =[4]p09!K10 -> 0
A11: Imported Units sold P2 | B11: =[4]p09!B11 -> 203766 | C11: =[4]p09!C11 -> 132974 | D11: =[4]p09!D11 -> 88582 | E11: =[4]p09!E11 -> 157639 | F11: =[4]p09!F11 -> 204734 | G11: =[4]p09!G11 -> 0 | H11: =[4]p09!H11 -> 0 | I11: =[4]p09!I11 -> 0 | ... K11: =[4]p09!K11 -> 0
A12: Exported units P2 | B12: =[4]p09!B12 -> 0 | C12: =[4]p09!C12 -> 0 | D12: =[4]p09!D12 -> 0 | E12: =[4]p09!E12 -> 0 | F12: =[4]p09!F12 -> 0 | G12: =[4]p09!G12 -> 787695 | H12: =[4]p09!H12 -> 0 | I12: =[4]p09!I12 -> 0 | ... K12: =[4]p09!K12 -> 0
A13: Price company 1 P1 | B13: =[4]p09!B13 -> 3420 | C13: =[4]p09!C13 -> 396 | D13: =[4]p09!D13 -> 315 | E13: =[4]p09!E13 -> 33.3 | F13: =[4]p09!F13 -> 46.8 | G13: =[4]p09!G13 -> 43.2 | H13: =[4]p09!H13 -> 0 | I13: =[4]p09!I13 -> 0 | ... K13: =[4]p09!K13 -> 0
A14: Price company 2 P1 | B14: =[4]p09!B14 -> 4230 | C14: =[4]p09!C14 -> 409.5 | D14: =[4]p09!D14 -> 360 | E14: =[4]p09!E14 -> 31.05 | F14: =[4]p09!F14 -> 49.5 | G14: =[4]p09!G14 -> 40.5 | H14: =[4]p09!H14 -> 0 | I14: =[4]p09!I14 -> 0 | ... K14: =[4]p09!K14 -> 0
... A77: New Plant capacity P2 | B77: =[4]p09!B77 -> 0 | C77: =[4]p09!C77 -> 0 | D77: =[4]p09!D77 -> 0 | E77: =[4]p09!E77 -> 0 | F77: =[4]p09!F77 -> 0 | G77: =[4]p09!G77 -> 0 | H77: =[4]p09!H77 -> 0 | I77: =[4]p09!I77 -> 0 | ... K77: =[4]p09!K77 -> 0
A78: COMPANY DATA | B78: =[4]p09!B78 -> 1
A79: Contract Vol Demand | B79: =[4]p09!B79 -> 60000
A80: Total cont Vol Sold | B80: =[4]p09!B80 -> 60000
A81: Contract Price | B81: =[4]p09!B81 -> 0
A82: Contract units sold | B82: =[4]p09!B82 -> 0
A83: Contract sales dollars | B83: =[4]p09!B83 -> 0
A84: Contract unit cost | B84: =[4]p09!B84 -> 0
A85: Demand Units Japan P1 | B85: =[4]p09!B85 -> 71082
A86: Demand Units Mexico P1 | B86: =[4]p09!B86 -> 26065
A87: Demand Units China P1 | B87: =[4]p09!B87 -> 22814
A88: Demand Units UK P1 | B88: =[4]p09!B88 -> 35819
A89: Demand Units German P1 | B89: =[4]p09!B89 -> 40538
... A291: Return on Invested Capital | B291: =[4]p09!B291 -> 0.19139814

Sheet P10
C1: OUTPUT PERIOD 10
A2: 10 | B2: JAPAN | C2: MEXICO | D2: CHINA | E2: U.K. | F2: GERMAN | G2: U.S. | H2: TOTAL
A3: Demand - Units P1 | B3: =[4]p10!B3 -> 274351 | C3: =[4]p10!C3 -> 106101 | D3: =[4]p10!D3 -> 89100 | E3: =[4]p10!E3 -> 159595 | F3: =[4]p10!F3 -> 185206 | G3: =[4]p10!G3 -> 500748 | H3: =[4]p10!H3 -> 1315101 | I3: =[4]p10!I3 -> 0 | ... K3: =[4]p10!K3 -> 0
A4: Sales - Units P1 | B4: =[4]p10!B4 -> 274351 | C4: =[4]p10!C4 -> 106101 | D4: =[4]p10!D4 -> 89100 | E4: =[4]p10!E4 -> 159595 | F4: =[4]p10!F4 -> 185206 | G4: =[4]p10!G4 -> 500748 | H4: =[4]p10!H4 -> 1315101 | I4: =[4]p10!I4 -> 0 | ... K4: =[4]p10!K4 -> 0
A5: Domestic Units sold P1 | B5: =[4]p10!B5 -> 0 | C5: =[4]p10!C5 -> 0 | D5: =[4]p10!D5 -> 89100 | E5: =[4]p10!E5 -> 0 | F5: =[4]p10!F5 -> 0 | G5: =[4]p10!G5 -> 0 | H5: =[4]p10!H5 -> 0 | I5: =[4]p10!I5 -> 0 | ... K5: =[4]p10!K5 -> 0
A6: Imported Units sold P1 | B6: =[4]p10!B6 -> 274351 | C6: =[4]p10!C6 -> 106101 | D6: =[4]p10!D6 -> 0 | E6: =[4]p10!E6 -> 159595 | F6: =[4]p10!F6 -> 185206 | G6: =[4]p10!G6 -> 500748 | H6: =[4]p10!H6 -> 0 | I6: =[4]p10!I6 -> 0 | ... K6: =[4]p10!K6 -> 0
A7: Exported units P1 | B7: =[4]p10!B7 -> 0 | C7: =[4]p10!C7 -> 0 | D7: =[4]p10!D7 -> 1226001 | E7: =[4]p10!E7 -> 0 | F7: =[4]p10!F7 -> 0 | G7: =[4]p10!G7 -> 0 | H7: =[4]p10!H7 -> 0 | I7: =[4]p10!I7 -> 0 | ... K7: =[4]p10!K7 -> 0
A8: Demand - Units P2 | B8: =[4]p10!B8 -> 217092 | C8: =[4]p10!C8 -> 121902 | D8: =[4]p10!D8 -> 85261 | E8: =[4]p10!E8 -> 164149 | F8: =[4]p10!F8 -> 214667 | G8: =[4]p10!G8 -> 522160 | H8: =[4]p10!H8 -> 1325231 | I8: =[4]p10!I8 -> 0 | ... K8: =[4]p10!K8 -> 0
A9: Sales - Units P2 | B9: =[4]p10!B9 -> 217092 | C9: =[4]p10!C9 -> 121902 | D9: =[4]p10!D9 -> 85261 | E9: =[4]p10!E9 -> 164149 | F9: =[4]p10!F9 -> 214667 | G9: =[4]p10!G9 -> 522160 | H9: =[4]p10!H9 -> 1325231 | I9: =[4]p10!I9 -> 0 | ... K9: =[4]p10!K9 -> 0
A10: Domestic Units sold P2 | B10: =[4]p10!B10 -> 0 | C10: =[4]p10!C10 -> 0 | D10: =[4]p10!D10 -> 0 | E10: =[4]p10!E10 -> 0 | F10: =[4]p10!F10 -> 0 | G10: =[4]p10!G10 -> 522160 | H10: =[4]p10!H10 -> 0 | I10: =[4]p10!I10 -> 0 | ... K10: =[4]p10!K10 -> 0
A11: Imported Units sold P2 | B11: =[4]p10!B11 -> 217092 | C11: =[4]p10!C11 -> 121902 | D11: =[4]p10!D11 -> 85261 | E11: =[4]p10!E11 -> 164149 | F11: =[4]p10!F11 -> 214667 | G11: =[4]p10!G11 -> 0 | H11: =[4]p10!H11 -> 0 | I11: =[4]p10!I11 -> 0 | ... K11: =[4]p10!K11 -> 0
A12: Exported units P2 | B12: =[4]p10!B12 -> 0 | C12: =[4]p10!C12 -> 0 | D12: =[4]p10!D12 -> 0 | E12: =[4]p10!E12 -> 0 | F12: =[4]p10!F12 -> 0 | G12: =[4]p10!G12 -> 803071 | H12: =[4]p10!H12 -> 0 | I12: =[4]p10!I12 -> 0 | ... K12: =[4]p10!K12 -> 0
A13: Price company 1 P1 | B13: =[4]p10!B13 -> 3420 | C13: =[4]p10!C13 -> 396 | D13: =[4]p10!D13 -> 315 | E13: =[4]p10!E13 -> 33.3 | F13: =[4]p10!F13 -> 46.8 | G13: =[4]p10!G13 -> 43.2 | H13: =[4]p10!H13 -> 0 | I13: =[4]p10!I13 -> 0 | ... K13: =[4]p10!K13 -> 0
A14: Price company 2 P1 | B14: =[4]p10!B14 -> 4230 | C14: =[4]p10!C14 -> 409.5 | D14: =[4]p10!D14 -> 360 | E14: =[4]p10!E14 -> 31.05 | F14: =[4]p10!F14 -> 49.5 | G14: =[4]p10!G14 -> 40.5 | H14: =[4]p10!H14 -> 0 | I14: =[4]p10!I14 -> 0 | ... K14: =[4]p10!K14 -> 0
... A77: New Plant capacity P2 | B77: =[4]p10!B77 -> 0 | C77: =[4]p10!C77 -> 0 | D77: =[4]p10!D77 -> 0 | E77: =[4]p10!E77 -> 0 | F77: =[4]p10!F77 -> 0 | G77: =[4]p10!G77 -> 0 | H77: =[4]p10!H77 -> 0 | I77: =[4]p10!I77 -> 0 | ... K77: =[4]p10!K77 -> 0
A78: COMPANY DATA | B78: =[4]p10!B78 -> 1
A79: Contract Vol Demand | B79: =[4]p10!B79 -> 75000
